Workbook

Sheet FS (2)
B3: For the year ended December 31,
B4: (LKR '000 except per share data) | C4: 2017 | D4: 2018 | E4: 2019 | F4: 2020 | G4: 2021 | H4: 2022 | I4: 2023F | J4: 2024F | K4: 2025F | L4: 2026F
B5: INCOME STATEMENT
B6: Gross income | C6: 115605156 | D6: 139657195 | E6: 150741129 | F6: 151966413 | G6: 163675312 | H6: 280386944 | I6: =I7+I10+I13+I14+I15 -> 0 | J6: =J7+J10+J13+J14+J15 -> 0 | K6: =K7+K10+K13+K14+K15 -> 0 | L6: =L7+L10+L13+L14+L15 -> 0
B7: Interest income | C7: 104049102 | D7: 118551239 | E7: 129287743 | F7: 124087713 | G7: 132818178 | H7: 222393079
B8: Less: Interest expense | C8: 64481804 | D8: 72933030 | E8: 80931352 | F8: 73218911 | G8: 66401846 | H8: 137727868
B9: Net interest income | C9: 39567298 | D9: 45618209 | E9: 48356391 | F9: 50868802 | G9: 66416332 | H9: 84665211 | I9: =I7-I8 -> 0 | J9: =J7-J8 -> 0 | K9: =K7-K8 -> 0 | L9: =L7-L8 -> 0
B10: Fee and commission income | C10: 10510800 | D10: 12494090 | E10: 12874966 | F10: 11839689 | G10: 15917337 | H10: 26191530
B11: Less: Fee and commission expense | C11: 1586334 | D11: 1859698 | E11: 2123128 | F11: 2018014 | G11: 3675143 | H11: 6022429
B12: Net fee and commission income | C12: 8924466 | D12: 10634392 | E12: 10751838 | F12: 9821675 | G12: 12242194 | H12: 20169101 | I12: =I10-I11 -> 0 | J12: =J10-J11 -> 0 | K12: =K10-K11 -> 0 | L12: =L10-L11 -> 0
B13: Net gains/(losses) from trading | C13: 233956 | D13: -3033236 | E13: 1360833 | F13: 1878060 | G13: 1936007 | H13: 35297450
B14: Net gains/(losses) from derecognition of financial assets | C14: 91272 | D14: 272004 | E14: 1135711 | F14: 6390197 | G14: 3001574 | H14: 276884
B15: Net other operating income | C15: 720026 | D15: 11373098 | E15: 6081876 | F15: 7770754 | G15: 10002216 | H15: -3771999
B16: Total operating income | C16: 49537018 | D16: 64864467 | E16: 67686649 | F16: 76729488 | G16: 93598323 | H16: 136636647 | I16: =I9+I12+I13+I14+I15 -> 0 | J16: =J9+J12+J13+J14+J15 -> 0 | K16: =K9+K12+K13+K14+K15 -> 0 | L16: =L9+L12+L13+L14+L15 -> 0
B17: Less: Impairment charges and other losses | C17: 989315 | D17: 8833362 | E17: 11331523 | F17: 21419532 | G17: 25139926 | H17: 71924260
B18: Net operating income | C18: 48547703 | D18: 56031105 | E18: 56355126 | F18: 55309956 | G18: 68458397 | H18: 64712387 | I18: =I16-I17 -> 0 | J18: =J16-J17 -> 0 | K18: =K16-K17 -> 0 | L18: =L16-L17 -> 0
B19: Less: Expenses
B20: Personnel expenses | C20: 11338517 | D20: 13289668 | E20: 14408914 | F20: 14992748 | G20: 16799212 | H20: 19788283
B21: Depreciation and amortisation | C21: 1416927 | D21: 1603118 | E21: 2841264 | F21: 3102695 | G21: 3220066 | H21: 3598371
B22: Other operating expenses | C22: 7618993 | D22: 8993958 | E22: 8875316 | F22: 8167170 | G22: 9638461 | H22: 12895587
B23: Total operating expenses | C23: 20374437 | D23: 23886744 | E23: 26125494 | F23: 26262613 | G23: 29657739 | H23: 36282241 | I23: =I20+I21+I22 -> 0 | J23: =J20+J21+J22 -> 0 | K23: =K20+K21+K22 -> 0 | L23: =L20+L21+L22 -> 0
B24: Operating profit before taxes on financial services | C24: 28173266 | D24: 32144361 | E24: 30229632 | F24: 29047343 | G24: 38800658 | H24: 28430146 | I24: =I18-I23 -> 0
B25: Less: Taxes on financial services | C25: 4896620 | D25: 6051861 | E25: 7255728 | F25: 4531381 | G25: 5845230 | H25: 3921381
B26: Operating profit after taxes on financial services | C26: 23276646 | D26: 26092500 | E26: 22973904 | F26: 24515962 | G26: 32955428 | H26: 24508765 | I26: =I24-I25 -> 0 | J26: =J24-J25 -> 0 | K26: =K24-K25 -> 0 | L26: =L24-L25 -> 0
B27: Share of profit/(loss) of associate, net of tax | C27: 3678 | D27: 6048 | E27: 9992 | F27: 3898 | G27: 1896 | H27: -3727
B28: Profit before tax | C28: 23280324 | D28: 26098548 | E28: 22983896 | F28: 24519860 | G28: 32957324 | H28: 24505038 | I28: =I26+I27 -> 0 | J28: =J26+J27 -> 0 | K28: =K26+K27 -> 0 | L28: =L26+L27 -> 0
B29: Less: Income tax expense/(reversal) | C29: 6653817 | D29: 8235717 | E29: 5563500 | F29: 7433063 | G29: 8667036 | H29: 105566
B30: Profit for the year | C30: 16626507 | D30: 17862831 | E30: 17420396 | F30: 17086797 | G30: 24290288 | H30: 24399472 | I30: =I28-I29 -> 0 | J30: =J28-J29 -> 0 | K30: =K28-K29 -> 0 | L30: =L28-L29 -> 0
B31: Profit attributable to: Equity holders of the Bank | C31: 16605963 | D31: 17734706 | E31: 17263259 | F31: 16939950 | G31: 24062469 | H31: 23811914
B32: Non-controlling interest | C32: 20544 | D32: 128125 | E32: 157137 | F32: 146847 | G32: 227819 | H32: 587558
B33: Profit for the year | C33: 16626507 | D33: 17862831 | E33: 17420396 | F33: 17086797 | G33: 24290288 | H33: 24399472 | I33: =I30 -> 0 | J33: =J30 -> 0 | K33: =K30 -> 0 | L33: =L30 -> 0
B34: Earnings per share Basic earnings per ordinary share (Rs.) | C34: 17.05 | D34: 17.55 | E34: 16.41 | F34: 15.7 | G34: 19.41 | H34: 19.21
B35: Diluted earnings per ordinary share (Rs.) | C35: 17.03 | D35: 17.55 | E35: 16.41 | F35: 15.7 | G35: 19.41 | H35: 19.21
B37: OCI
B38: Transfer of FV losses reclassification of debt from FVTOCI to AC | G38: 0 | H38: 26481256
B40: IS check | C40: =IF(C18-C23-C25+C27-C29-C30=0,"OK","FLAG") -> OK | D40: =IF(D18-D23-D25+D27-D29-D30=0,"OK","FLAG") -> OK | E40: =IF(E18-E23-E25+E27-E29-E30=0,"OK","FLAG") -> OK | F40: =IF(F18-F23-F25+F27-F29-F30=0,"OK","FLAG") -> OK | G40: =IF(G18-G23-G25+G27-G29-G30=0,"OK","FLAG") -> OK | H40: =IF(H18-H23-H25+H27-H29-H30=0,"OK","FLAG") -> OK
B42: BALANCE SHEET
B43: Assets
B44: Cash and cash equivalents | C44: 34673424 | D44: 44355962 | E44: 53681118 | F44: 51255030 | G44: 69335379 | H44: 151109490
B45: Balances with Central Banks | C45: 45546349 | D45: 55406535 | E45: 46101232 | F45: 115358732 | G45: 56777465 | H45: 78597120
B46: Placements with banks | C46: 17633269 | D46: 19898515 | E46: 24903809 | F46: 16421867 | G46: 12498709 | H46: 96082937
B47: Securities purchased under resale agreements | C47: 0 | D47: 9513512 | E47: 13147534 | F47: 0 | G47: 3000490 | H47: 1517308
B48: Derivative financial assets | C48: 2334536 | D48: 7909962 | E48: 1830927 | F48: 2636717 | G48: 3245120 | H48: 8345091
B49: Financial assets recognised through profit or loss – measured at fair value | C49: 4410913 | D49: 5520167 | E49: 21468033 | F49: 35189471 | G49: 23436123 | H49: 24873057
B50: Financial assets at amortised cost – loans and advances to banks | C50: 640512 | D50: 763074 | E50: 757787 | F50: 779705
B51: Financial assets at amortised cost – loans and advances to other customers | C51: 742444130 | D51: 867611976 | E51: 893919311 | F51: 909829172 | G51: 1029584075 | H51: 1155492527
B52: Financial assets at amortised cost – debt and other financial instruments | C52: 118078273 | D52: 89274413 | E52: 107059021 | F52: 302059529 | G52: 385390598 | H52: 761650234
B53: Financial assets measured at fair value through other comprehensive income | C53: 154913643 | D53: 176760611 | E53: 197825017 | F53: 278716794 | G53: 335953802 | H53: 118652257
B54: Investments in subsidiaries | C54: 0 | D54: 0 | E54: 0 | F54: 0 | G54: 0 | H54: 0
B55: Investment in associate | C55: 109844 | D55: 105320 | E55: 56821 | F55: 64155 | G55: 60428 | H55: 55302
B56: Property, plant and equipment and right-of-use assets | C56: 16317044 | D56: 17015236 | E56: 22524658 | F56: 25386630 | G56: 24744634 | H56: 27446607
B57: Investment properties | C57: 104516 | D57: 103064 | E57: 46350 | F57: 67116 | G57: 72400 | H57: 80350
B58: Intangible assets | C58: 1251226 | D58: 1433931 | E58: 1645714 | F58: 1800516 | G58: 2272639 | H58: 4113200
B59: Deferred tax assets | C59: 0 | D59: 188487 | E59: 530165 | F59: 2735566 | G59: 10036105 | H59: 30727213
B60: Other assets | C60: 17362977 | D60: 24051472 | E60: 23443869 | F60: 20195153 | G60: 27083177 | H60: 40811211
B61: Total assets | C61: 1155820656 | D61: 1319912237 | E61: 1408941366 | F61: 1762496153 | G61: 1983491144 | H61: 2499553904
B62: Liabilities
B63: Due to banks | C63: 60244892 | D63: 52362052 | E63: 53807425 | F63: 88248056 | G63: 73801195 | H63: 64971170
B64: Derivative financial liabilities | C64: 3678494 | D64: 8021783 | E64: 1495317 | F64: 1501262 | G64: 2092198 | H64: 2880667
B65: Securities sold under repurchase agreements | C65: 49532385 | D65: 48951394 | E65: 51117342 | F65: 91411522 | G65: 151424854 | H65: 97726435
B66: Financial liabilities at amortised cost – due to depositors | C66: 857269981 | D66: 994370875 | E66: 1068982587 | F66: 1286616399 | G66: 1472640456 | H66: 1977743661
B67: Financial liabilities at amortised cost – other borrowings | C67: 23786094 | D67: 25361912 | E67: 23248893 | F67: 54555933 | G67: 32587051 | H67: 16150356
B68: Current tax liabilities | C68: 4202850 | D68: 6735997 | E68: 5197188 | F68: 6991005 | G68: 9486772 | H68: 24916074
B69: Deferred tax liabilities | C69: 3565215 | D69: 971424 | E69: 416458 | F69: 403846 | G69: 349106 | H69: 437123
B70: Other liabilities | C70: 19508115 | D70: 24547513 | E70: 30775884 | F70: 33572283 | G70: 33253518 | H70: 40354877
B71: Due to subsidiaries | C71: 0 | D71: 0 | E71: 0 | F71: 0 | G71: 0 | H71: 0
B72: Subordinated liabilities | C72: 25165924 | D72: 37992457 | E72: 37886789 | F72: 38247138 | G72: 38303466 | H72: 61400967
B73: Total liabilities | C73: 1046953950 | D73: 1199315407 | E73: 1272927883 | F73: 1601547444 | G73: 1813938616 | H73: 2286581330
B74: Equity
B75: Stated capital | C75: 37143541 | D75: 39147882 | E75: 40916958 | F75: 52187747 | G75: 54566957 | H75: 58149621
B76: Statutory reserves | C76: 6492552 | D76: 7444178 | E76: 8387701 | F76: 9285233 | G76: 10590338 | H76: 12079670
B77: Retained earnings | C77: 5086609 | D77: 4949955 | E77: 5182185 | F77: 8124261 | G77: 9890762 | H77: 6790304
B78: Other reserves | C78: 59272098 | D78: 67855834 | E78: 79937405 | F78: 89595571 | G78: 92426660 | H78: 131845571
B79: Total equity attributable to equity holders of the Bank | C79: 107994800 | D79: 119397849 | E79: 134424249 | F79: 159192812 | G79: 167474717 | H79: 208865166
B80: Non-controlling interest | C80: 871906 | D80: 1198981 | E80: 1589234 | F80: 1755897 | G80: 2077811 | H80: 4107408
B81: Total equity | C81: 108866706 | D81: 120596830 | E81: 136013483 | F81: 160948709 | G81: 169552528 | H81: 212972574
B82: Total liabilities and equity | C82: 1155820656 | D82: 1319912237 | E82: 1408941366 | F82: 1762496153 | G82: 1983491144 | H82: 2499553904
B83: Contingent liabilities and commitments | C83: 565277821 | D83: 658860264 | E83: 580961807 | F83: 730561685 | G83: 685379028 | H83: 555531537
B84: Net assets value per ordinary share (Rs.) | C84: 108.44 | D84: 118.13 | E84: 130.83 | F84: 136.42 | G84: 140.24 | H84: 168.47
B85: Memorandum information
B86: Number of employees | C86: 4982 | D86: 5027 | E86: 5062 | F86: 5057 | G86: 5072 | H86: 5121
B87: Number of customer service centres | C87: 280 | D87: 285 | E87: 287 | F87: 287 | G87: 287 | H87: 289
B89: BS check | C89: =SUM(C44:C60)-SUM(C63:C72)-SUM(C75:C78)-C80 -> 0 | D89: =SUM(D44:D60)-SUM(D63:D72)-SUM(D75:D78)-D80 -> 0 | E89: =SUM(E44:E60)-SUM(E63:E72)-SUM(E75:E78)-E80 -> 0 | F89: =SUM(F44:F60)-SUM(F63:F72)-SUM(F75:F78)-F80 -> 0 | G89: =SUM(G44:G60)-SUM(G63:G72)-SUM(G75:G78)-G80 -> 0 | H89: =SUM(H44:H60)-SUM(H63:H72)-SUM(H75:H78)-H80 -> 0
B91: CASH FLOW STATEMENT
B93: Cash flows from operating activities Profit before income tax | C93: 23280324 | D93: 26098548 | E93: 22983896 | F93: 24519860 | G93: 32957324 | H93: 24505038
B94: Adjustments for:
B95: Non-cash items included in profit before tax | C95: 1078540 | D95: 12380685 | E95: 14014272 | F95: 24764927 | G95: 30473593 | H95: 91299070
B96: Change in operating assets | C96: -125489870 | D96: -169379105 | E96: -84218375 | F96: -374761711 | G96: -230261220 | H96: -463345077
B97: Change in operating liabilities | C97: 100265879 | D97: 138876499 | E97: 69879669 | F97: 325708382 | G97: 208070200 | H97: 430778836
B98: (Gains)/losses on sale of property, plant and equipment | C98: 18774 | D98: -9311 | E98: -19731 | F98: -5820 | G98: -4054 | H98: -20118
B99: Share of (profit)/loss of associate, net of tax | C99: -3678 | D99: -6048 | E99: -9992 | F99: -3898 | G99: -1896 | H99: 3727
B100: Dividends received from investments in associate and subsidiaries | C100: 0 | D100: 0 | E100: 0 | F100: 0 | G100: 0 | H100: 0
B101: Interest expense on subordinated liabilities | C101: 2377694 | D101: 3105553 | E101: 3848979 | F101: 3756921 | G101: 3398554 | H101: 4843571
B102: Net unrealised gains/(losses) arising from translating the Financial Statements of foreign operations | C102: -503140 | D102: 3003952 | E102: -396201 | F102: 596723 | G102: 1278891 | H102: 18347815
B103: Benefits paid on defined benefit plans | C103: -184464 | D103: -382409 | E103: -198799 | F103: -673106 | G103: -1116195 | H103: -780828
B104: Income tax paid | C104: -3810701 | D104: -5971026 | E104: -8301839 | F104: -7748870 | G104: -8963620 | H104: -11143271
B105: Surcharge tax paid | C105: 0 | D105: 0 | E105: 0 | F105: 0 | G105: 0 | H105: -5216574
B106: Net cash from/(used in) operating activities | C106: -2970642 | D106: 7717338 | E106: 17581879 | F106: -3846592 | G106: 35831577 | H106: 89272189
B107: Cash flows from investing activities
B108: Purchase of property, plant and equipment | C108: -2163733 | D108: -2079875 | E108: -1372832 | F108: -1159712 | G108: -1034299 | H108: -3370339
...

Sheet Cover
B3: COMMERCIAL BANK OF CEYLON PLC
B4: COMB N
B5: COMB X

Sheet FS
L2: l
B3: For the year ended December 31,
B4: (LKR '000 except per share data) | C4: 2017 | D4: 2018 | E4: 2019 | G4: 2020 | H4: 2021 | I4: 2022 | J4: 2023F | K4: 2024F | L4: 2025F | M4: 2026F | O4: Annualised | P4: 9M Sep23 | Q4: 1H2023 | R4: 1H2022
B5: INCOME STATEMENT
B6: Gross income | C6: 115605156 | D6: 139657195 | E6: 150741129 | G6: 151966413 | H6: 163675312 | I6: 280386944 | J6: =J7+J10+J13+J14+J15 -> 3.4870888e+08 | K6: =K7+K10+K13+K14+K15 -> 3.6286483e+08 | L6: =L7+L10+L13+L14+L15 -> 4.1272143e+08 | M6: =M7+M10+M13+M14+M15 -> 4.6464828e+08 | O6: =P6/9*12 -> 3.4128382e+08 | P6: 255962864 | Q6: 167668267 | R6: 119517450 | S6: =Q6*2 -> 335336534
B7: Interest income | C7: 104049102 | D7: 118551239 | E7: 129287743 | G7: 124087713 | H7: 132818178 | I7: 222393079 | J7: =Drivers!I7 -> 3.0585734e+08 | K7: =Drivers!J7 -> 2.9513936e+08 | L7: =Drivers!K7 -> 3.3784948e+08 | M7: =Drivers!L7 -> 3.8175485e+08 | O7: =P7/9*12 -> 2.9942669e+08 | P7: 224570014 | Q7: 150811644 | R7: 88116673 | S7: =Q7*2 -> 301623288
B8: Less: Interest expense | C8: 64481804 | D8: 72933030 | E8: 80931352 | G8: 73218911 | H8: 66401846 | I8: 137727868 | J8: =Drivers!I58 -> 2.2269493e+08 | K8: =Drivers!J58 -> 2.3202049e+08 | L8: =Drivers!K58 -> 2.6615841e+08 | M8: =Drivers!L58 -> 3.0080788e+08 | O8: =P8/9*12 -> 2.18251e+08 | P8: 163688252 | Q8: 113361974 | R8: 47404088 | S8: =Q8*2 -> 226723948
B9: Net interest income | C9: 39567298 | D9: 45618209 | E9: 48356391 | G9: 50868802 | H9: 66416332 | I9: 84665211 | J9: =J7-J8 -> 83162406 | K9: =K7-K8 -> 63118873 | L9: =L7-L8 -> 71691068 | M9: =M7-M8 -> 80946963 | O9: =P9/9*12 -> 81175683 | P9: 60881762 | Q9: 37449670 | R9: 40712585 | S9: =Q9*2 -> 74899340
B10: Fee and commission income | C10: 10510800 | D10: 12494090 | E10: 12874966 | G10: 11839689 | H10: 15917337 | I10: 26191530 | J10: =Drivers!I78 -> 30373717 | K10: =Drivers!J78 -> 35658826 | L10: =Drivers!K78 -> 41280198 | M10: =Drivers!L78 -> 47701081 | O10: =P10/9*12 -> 29379307 | P10: 22034480 | Q10: 14377446 | R10: 11758745 | S10: =Q10*2 -> 28754892
B11: Less: Fee and commission expense | C11: 1586334 | D11: 1859698 | E11: 2123128 | G11: 2018014 | H11: 3675143 | I11: 6022429 | J11: =Drivers!I93 -> 7593429.2 | K11: =Drivers!J93 -> 8201529.9 | L11: =Drivers!K93 -> 9494445.4 | M11: =Drivers!L93 -> 10971249 | O11: =P11/9*12 -> 7766089.3 | P11: 5824567 | Q11: 3786488 | R11: 2881243 | S11: =Q11*2 -> 7572976
B12: Net fee and commission income | C12: 8924466 | D12: 10634392 | E12: 10751838 | G12: 9821675 | H12: 12242194 | I12: 20169101 | J12: =J10-J11 -> 22780287 | K12: =K10-K11 -> 27457296 | L12: =L10-L11 -> 31785752 | M12: =M10-M11 -> 36729832 | O12: =P12/9*12 -> 21613217 | P12: 16209913 | Q12: 10590958 | R12: 8877502 | S12: =Q12*2 -> 21181916
B13: Net gains/(losses) from trading | C13: 233956 | D13: -3033236 | E13: 1360833 | G13: 1878060 | H13: 1936007 | I13: 35297450 | J13: =Drivers!I106 -> -16199576 | K13: =Drivers!J106 -> 1955367.1 | L13: =Drivers!K106 -> 1974920.7 | M13: =Drivers!L106 -> 1994669.9 | O13: =P13/9*12 -> -16199576 | P13: -12149682 | Q13: -15531353 | R13: 32101899 | S13: =Q13*2 -> -31062706
B14: Net gains/(losses) from derecognition of financial assets | C14: 91272 | D14: 272004 | E14: 1135711 | G14: 6390197 | H14: 3001574 | I14: 276884 | J14: =P14/9*12 -> 3517693.3 | K14: =J14*1.05 -> 3693578 | L14: =K14*1.05 -> 3878256.9 | M14: =L14*1.05 -> 4072169.7 | O14: =P14/9*12 -> 3517693.3 | P14: 2638270 | Q14: 924510 | R14: 64262 | S14: =Q14*2 -> 1849020
B15: Net other operating income | C15: 720026 | D15: 11373098 | E15: 6081876 | G15: 7770754 | H15: 10002216 | I15: -3771999 | J15: =Drivers!I123 -> 25159709 | K15: =Drivers!J123 -> 26417695 | L15: =Drivers!K123 -> 27738580 | M15: =Drivers!L123 -> 29125509 | O15: =P15/9*12 -> 25159709 | P15: 18869782 | Q15: 17086020 | R15: -12524129 | S15: =Q15*2 -> 34172040
B16: Total operating income | C16: 49537018 | D16: 64864467 | E16: 67686649 | G16: 76729488 | H16: 93598323 | I16: 136636647 | J16: =J9+J12+J13+J14+J15 -> 1.1842052e+08 | K16: =K9+K12+K13+K14+K15 -> 1.2264281e+08 | L16: =L9+L12+L13+L14+L15 -> 1.3706858e+08 | M16: =M9+M12+M13+M14+M15 -> 1.5286914e+08 | O16: =P16/9*12 -> 1.1526673e+08 | P16: 86450045 | Q16: 50519805 | R16: 69232119 | S16: =Q16*2 -> 101039610
B17: Less: Impairment charges and other losses | C17: 989315 | D17: 8833362 | E17: 11331523 | G17: 21419532 | H17: 25139926 | I17: 71924260 | J17: =Drivers!I138 -> 35328926 | K17: =Drivers!J138 -> 30095011 | L17: =Drivers!K138 -> 34609262 | M17: =Drivers!L138 -> 39800652 | O17: =P17/9*12 -> 34376147 | P17: 25782110 | Q17: 13210963 | R17: 35218619 | S17: =Q17*2 -> 26421926
B18: Net operating income | C18: 48547703 | D18: 56031105 | E18: 56355126 | G18: 55309956 | H18: 68458397 | I18: 64712387 | J18: =J16-J17 -> 83091594 | K18: =K16-K17 -> 92547798 | L18: =L16-L17 -> 1.0245931e+08 | M18: =M16-M17 -> 1.1306849e+08 | O18: =P18/9*12 -> 80890580 | P18: 60667935 | Q18: 37308842 | R18: 34013500 | S18: =Q18*2 -> 74617684
B19: Less: Expenses | O19: =P19/9*12 -> 0 | S19: =Q19*2 -> 0
B20: Personnel expenses | C20: 11338517 | D20: 13289668 | E20: 14408914 | G20: 14992748 | H20: 16799212 | I20: 19788283 | J20: =Drivers!I155 -> 21767111 | K20: =Drivers!J155 -> 23943822 | L20: =Drivers!K155 -> 26338205 | M20: =Drivers!L155 -> 28972025 | O20: =P20/9*12 -> 22412377 | P20: 16809283 | Q20: 11296515 | R20: 9584347 | S20: =Q20*2 -> 22593030
B21: Depreciation and amortisation | C21: 1416927 | D21: 1603118 | E21: 2841264 | G21: 3102695 | H21: 3220066 | I21: 3598371 | J21: =Drivers!I172 -> 4116991 | K21: =Drivers!J172 -> 4240227.2 | L21: =Drivers!K172 -> 4381833.5 | M21: =Drivers!L172 -> 4529601.5 | O21: =P21/9*12 -> 4106025.3 | P21: 3079519 | Q21: 2084338 | R21: 1724022 | S21: =Q21*2 -> 4168676
B22: Other operating expenses | C22: 7618993 | D22: 8993958 | E22: 8875316 | G22: 8167170 | H22: 9638461 | I22: 12895587 | J22: =Drivers!I184 -> 16764263 | K22: =Drivers!J184 -> 20117116 | L22: =Drivers!K184 -> 24140539 | M22: =Drivers!L184 -> 28968647 | O22: =P22/9*12 -> 16116592 | P22: 12087444 | Q22: 7903941 | R22: 6723078 | S22: =Q22*2 -> 15807882
B23: Total operating expenses | C23: 20374437 | D23: 23886744 | E23: 26125494 | G23: 26262613 | H23: 29657739 | I23: 36282241 | J23: =J20+J21+J22 -> 42648365 | K23: =K20+K21+K22 -> 48301165 | L23: =L20+L21+L22 -> 54860577 | M23: =M20+M21+M22 -> 62470273 | O23: =P23/9*12 -> 42634995 | P23: 31976246 | Q23: 21284794 | R23: 18031447 | S23: =Q23*2 -> 42569588
B24: Operating profit before taxes on financial services | C24: 28173266 | D24: 32144361 | E24: 30229632 | G24: 29047343 | H24: 38800658 | I24: 28430146 | J24: =J18-J23 -> 40443229 | K24: =K18-K23 -> 44246633 | L24: =L18-L23 -> 47598738 | M24: =M18-M23 -> 50598219 | O24: =P24/9*12 -> 38255585 | P24: 28691689 | Q24: 16024048 | R24: 15982053 | S24: =Q24*2 -> 32048096
B25: Less: Taxes on financial services | C25: 4896620 | D25: 6051861 | E25: 7255728 | G25: 4531381 | H25: 5845230 | I25: 3921381 | J25: =Drivers!I196 -> 4893717.4 | K25: =Drivers!J196 -> 5902787.2 | L25: =Drivers!K196 -> 6756989.5 | M25: =Drivers!L196 -> 7635097 | O25: =P25/9*12 -> 4886169.3 | P25: 3664627 | Q25: 1933968 | R25: 2602781 | S25: =Q25*2 -> 3867936
B26: Operating profit after taxes on financial services | C26: 23276646 | D26: 26092500 | E26: 22973904 | G26: 24515962 | H26: 32955428 | I26: 24508765 | J26: =J24-J25 -> 35549511 | K26: =K24-K25 -> 38343846 | L26: =L24-L25 -> 40841748 | M26: =M24-M25 -> 42963122 | O26: =P26/9*12 -> 33369416 | P26: 25027062 | Q26: 14090080 | R26: 13379272 | S26: =Q26*2 -> 28180160
B27: Share of profit/(loss) of associate, net of tax | C27: 3678 | D27: 6048 | E27: 9992 | G27: 3898 | H27: 1896 | I27: -3727 | J27: =P27/9*12 -> 5197.3333 | K27: =J27*1.01 -> 5249.3067 | L27: =K27*1.01 -> 5301.7997 | M27: =L27*1.01 -> 5354.8177 | O27: =P27/9*12 -> 5197.3333 | P27: 3898 | Q27: 2352 | R27: -3476 | S27: =Q27*2 -> 4704
B28: Profit before tax | C28: 23280324 | D28: 26098548 | E28: 22983896 | G28: 24519860 | H28: 32957324 | I28: 24505038 | J28: =J26+J27 -> 35554709 | K28: =K26+K27 -> 38349095 | L28: =L26+L27 -> 40847050 | M28: =M26+M27 -> 42968476 | O28: =P28/9*12 -> 33374613 | P28: 25030960 | Q28: 14092432 | R28: 13375796 | S28: =Q28*2 -> 28184864
B29: Less: Income tax expense/(reversal) | C29: 6653817 | D29: 8235717 | E29: 5563500 | G29: 7433063 | H29: 8667036 | I29: 105566 | J29: =Drivers!I206 -> 14932978 | K29: =Drivers!J206 -> 11504728 | L29: =Drivers!K206 -> 12254115 | M29: =Drivers!L206 -> 12890543 | O29: =P29/9*12 -> 13689807 | P29: 10267355 | Q29: 5801958 | R29: 4198046 | S29: =Q29*2 -> 11603916
B30: Profit for the year | C30: 16626507 | D30: 17862831 | E30: 17420396 | G30: 17086797 | H30: 24290288 | I30: 24399472 | J30: =J28-J29 -> 20621731 | K30: =K28-K29 -> 26844366 | L30: =L28-L29 -> 28592935 | M30: =M28-M29 -> 30077933 | O30: =P30/9*12 -> 19684807 | P30: 14763605 | Q30: 8290474 | R30: 9177750 | S30: =Q30*2 -> 16580948
B31: Profit attributable to: Equity holders of the Bank | C31: 16605963 | D31: 17734706 | E31: 17263259 | G31: 16939950 | H31: 24062469 | I31: 23811914 | J31: =J30*0.96 -> 19796862 | K31: =K30*0.96 -> 25770592 | L31: =L30*0.96 -> 27449218 | M31: =M30*0.96 -> 28874816 | O31: =P31/9*12 -> 18933237 | P31: 14199928 | Q31: 7966526 | R31: 8940996
B32: Non-controlling interest | C32: 20544 | D32: 128125 | E32: 157137 | G32: 146847 | H32: 227819 | I32: 587558 | J32: =J30*0.04 -> 824869.24 | K32: =K30*0.04 -> 1073774.7 | L32: =L30*0.04 -> 1143717.4 | M32: =M30*0.04 -> 1203117.3 | O32: =P32/9*12 -> 751569.33 | P32: 563677 | Q32: 323948 | R32: 236754
B33: Profit for the year | C33: 16626507 | D33: 17862831 | E33: 17420396 | G33: 17086797 | H33: 24290288 | I33: 24399472 | J33: =J30 -> 20621731 | K33: =K30 -> 26844366 | L33: =L30 -> 28592935 | M33: =M30 -> 30077933 | O33: =P33/9*12 -> 19684807 | P33: =P30 -> 14763605 | Q33: =Q30 -> 8290474 | R33: =R30 -> 9177750
B34: Earnings per share Basic earnings per ordinary share (Rs.) | C34: 17.05 | D34: 17.55 | E34: 16.41 | G34: 15.7 | H34: 19.41 | I34: 19.21 | J34: =J31*1000/Drivers!I586 -> 15.064716 | K34: =K31*1000/Drivers!J586 -> 19.610515 | L34: =L31*1000/Drivers!K586 -> 20.88789 | M34: =M31*1000/Drivers!L586 -> 21.97272 | P34: 10.81 | Q34: 6.07 | R34: 7.21
B35: Diluted earnings per ordinary share (Rs.) | C35: 17.03 | D35: 17.55 | E35: 16.41 | G35: 15.7 | H35: 19.41 | I35: 19.21 | P35: 10.81 | Q35: 6.07 | R35: 7.21
B36: Diviend per share | D36: 6.5 | E36: 6.5 | G36: 6.5 | H36: 7.5 | I36: 4.5 | J36: =#REF! -> #REF! | K36: =-Drivers!J619*1000/Drivers!J586 -> 6.8636802 | L36: =-Drivers!K619*1000/Drivers!K586 -> 7.3107615 | M36: =-Drivers!L619*1000/Drivers!L586 -> 7.6904522
B38: OCI
B39: Transfer of FV losses reclassification of debt from FVTOCI to AC | H39: 0 | I39: 26481256
B41: IS check | C41: =IF(C18-C23-C25+C27-C29-C30+C31+C32-C33=0,"OK","FLAG") -> OK | D41: =IF(D18-D23-D25+D27-D29-D30+D31+D32-D33=0,"OK","FLAG") -> OK | E41: =IF(E18-E23-E25+E27-E29-E30+E31+E32-E33=0,"OK","FLAG") -> OK | G41: =IF(G18-G23-G25+G27-G29-G30+G31+G32-G33=0,"OK","FLAG") -> OK | H41: =IF(H18-H23-H25+H27-H29-H30+H31+H32-H33=0,"OK","FLAG") -> OK | I41: =IF(I18-I23-I25+I27-I29-I30+I31+I32-I33=0,"OK","FLAG") -> OK | J41: =J18-J23-J25+J27-J29-J30+J31+J32-J33 -> 0 | K41: =K18-K23-K25+K27-K29-K30+K31+K32-K33 -> 0 | L41: =L18-L23-L25+L27-L29-L30+L31+L32-L33 -> 0 | M41: =M18-M23-M25+M27-M29-M30+M31+M32-M33 -> 0 | Q41: =IF(Q18-Q23-Q25+Q27-Q29-Q30=0,"OK","FLAG") -> OK | R41: =IF(R18-R23-R25+R27-R29-R30=0,"OK","FLAG") -> OK
B43: BALANCE SHEET
B44: Assets
B45: Cash and cash equivalents | C45: 34673424 | D45: 44355962 | E45: 53681118 | G45: 51255030 | H45: 69335379 | I45: 151109490 | J45: =J62-SUM(J46:J61) -> 1.0591632e+08 | K45: =K62-SUM(K46:K61) -> 1.0969008e+08 | L45: =L62-SUM(L46:L61) -> 1.5908379e+08 | M45: =M62-SUM(M46:M61) -> 1.6813355e+08 | P45: 114518140 | Q45: 112544293 | R45: 151109490
B46: Balances with Central Banks | C46: 45546349 | D46: 55406535 | E46: 46101232 | G46: 115358732 | H46: 56777465 | I46: 78597120 | J46: =Drivers!I234 -> 52339149 | K46: =Drivers!J234 -> 94799284 | L46: =Drivers!K234 -> 1.0901918e+08 | M46: =Drivers!L234 -> 1.2537205e+08 | P46: 37516912 | Q46: 61871953 | R46: 78597120
B47: Placements with banks | C47: 17633269 | D47: 19898515 | E47: 24903809 | G47: 16421867 | H47: 12498709 | I47: 96082937 | J47: =Drivers!I252 -> 76866350 | K47: =Drivers!J252 -> 80709667 | L47: =Drivers!K252 -> 84745150 | M47: =Drivers!L252 -> 88982408 | P47: 66538167 | Q47: 53920816 | R47: 96082937
B48: Securities purchased under resale agreements | C48: 0 | D48: 9513512 | E48: 13147534 | G48: 0 | H48: 3000490 | I48: 1517308 | J48: =Drivers!I264 -> 606923.2 | K48: =Drivers!J264 -> 637269.36 | L48: =Drivers!K264 -> 669132.83 | M48: =Drivers!L264 -> 702589.47 | P48: 549770 | Q48: 3378561 | R48: 1517308
B49: Derivative financial assets | C49: 2334536 | D49: 7909962 | E49: 1830927 | G49: 2636717 | H49: 3245120 | I49: 8345091 | J49: =Drivers!I266 -> 5841563.7 | K49: =Drivers!J266 -> 6133641.9 | L49: =Drivers!K266 -> 6440324 | M49: =Drivers!L266 -> 6762340.2 | P49: 6091290 | Q49: 7032972 | R49: 8345091
B50: Financial assets recognised through profit or loss – measured at fair value | C50: 4410913 | D50: 5520167 | E50: 21468033 | G50: 35189471 | H50: 23436123 | I50: 24873057 | J50: =Drivers!I271 -> 98932873 | K50: =Drivers!J271 -> 1.5596006e+08 | L50: =Drivers!K271 -> 1.7155607e+08 | M50: =Drivers!L271 -> 1.8871168e+08 | P50: 98042540 | Q50: 50791983 | R50: 24873057
B51: Financial assets at amortised cost – loans and advances to banks | C51: 640512 | D51: 763074 | E51: 757787 | G51: 779705 | H51: 0 | I51: 0
B52: Financial assets at amortised cost – loans and advances to other customers | C52: 742444130 | D52: 867611976 | E52: 893919311 | G52: 909829172 | H52: 1029584075 | I52: 1155492527 | J52: =Drivers!I289 -> 1.2149487e+09 | K52: =Drivers!J289 -> 1.426353e+09 | L52: =Drivers!K289 -> 1.6512079e+09 | M52: =Drivers!L289 -> 1.9080432e+09 | P52: 1148276787 | Q52: 1096826774 | R52: 1155492527
B53: Financial assets at amortised cost – debt and other financial instruments | C53: 118078273 | D53: 89274413 | E53: 107059021 | G53: 302059529 | H53: 385390598 | I53: 761650234 | J53: =Drivers!I341 -> 7.0929112e+08 | K53: =Drivers!J341 -> 6.6835832e+08 | L53: =Drivers!K341 -> 7.3775418e+08 | M53: =Drivers!L341 -> 7.9117557e+08 | P53: 706747778 | Q53: 740197253 | R53: 761650234
B54: Financial assets measured at fair value through other comprehensive income | C54: 154913643 | D54: 176760611 | E54: 197825017 | G54: 278716794 | H54: 335953802 | I54: 118652257 | J54: =Drivers!I384 -> 296954728 | K54: =Drivers!J384 -> 3.266502e+08 | L54: =Drivers!K384 -> 3.5931522e+08 | M54: =Drivers!L384 -> 3.9524674e+08 | P54: 246477855 | Q54: 230826265 | R54: 118652257
B55: Investments in subsidiaries | C55: 0 | D55: 0 | E55: 0 | G55: 0 | H55: 0 | I55: 0 | J55: =I55 -> 0 | K55: =J55 -> 0 | L55: =K55 -> 0 | M55: =L55 -> 0 | P55: 0
B56: Investment in associate | C56: 109844 | D56: 105320 | E56: 56821 | G56: 64155 | H56: 60428 | I56: 55302 | J56: =Drivers!I396 -> 55302 | K56: =Drivers!J396 -> 55302 | L56: =Drivers!K396 -> 55302 | M56: =Drivers!L396 -> 55302 | P56: 59475 | Q56: 57856 | R56: 55302
B57: Property, plant and equipment and right-of-use assets | C57: 16317044 | D57: 17015236 | E57: 22524658 | G57: 25386630 | H57: 24744634 | I57: 27446607 | J57: =Drivers!I401 -> 28268182 | K57: =Drivers!J401 -> 29212223 | L57: =Drivers!K401 -> 30197343 | M57: =Drivers!L401 -> 31229666 | P57: 26538514 | Q57: 26649043 | R57: 27446607
B58: Investment properties | C58: 104516 | D58: 103064 | E58: 46350 | G58: 67116 | H58: 72400 | I58: 80350 | J58: =Drivers!I430 -> 642800 | K58: =Drivers!J430 -> 707080 | L58: =Drivers!K430 -> 777788 | M58: =Drivers!L430 -> 855566.8 | P58: 545850 | Q58: 424550 | R58: 80350
B59: Intangible assets | C59: 1251226 | D59: 1433931 | E59: 1645714 | G59: 1800516 | H59: 2272639 | I59: 4113200 | J59: =Drivers!I435 -> 4090774.5 | K59: =Drivers!J435 -> 4409448.7 | L59: =Drivers!K435 -> 7206711.9 | M59: =Drivers!L435 -> 7793697.9 | P59: 4061409 | Q59: 4042878 | R59: 4113200
B60: Deferred tax assets | C60: 0 | D60: 188487 | E60: 530165 | G60: 2735566 | H60: 10036105 | I60: 30727213 | J60: =Drivers!I462 -> 32878118 | K60: =Drivers!J462 -> 16439059 | L60: =Drivers!K462 -> 17261012 | M60: =Drivers!L462 -> 18124062 | P60: 32664942 | Q60: 30251431 | R60: 30727213
B61: Other assets | C61: 17362977 | D61: 24051472 | E61: 23443869 | G61: 20195153 | H61: 27083177 | I61: 40811211 | J61: =Drivers!I468 -> 34689529 | K61: =Drivers!J468 -> 32955053 | L61: =Drivers!K468 -> 33614154 | M61: =Drivers!L468 -> 34286437 | P61: 36882221 | Q61: 43351569 | R61: 40811211
B62: Total assets | C62: 1155820656 | D62: 1319912237 | E62: 1408941366 | G62: 1762496153 | H62: 1983491144 | I62: 2499553904 | J62: =J83 -> 2.6623224e+09 | K62: =K83 -> 2.9530697e+09 | L62: =L83 -> 3.3689033e+09 | M62: =M83 -> 3.7654749e+09 | P62: 2525511650 | Q62: 2462168197 | R62: 2499553904
B63: Liabilities
B64: Due to banks | C64: 60244892 | D64: 52362052 | E64: 53807425 | G64: 88248056 | H64: 73801195 | I64: 64971170 | J64: =Drivers!I475 -> 39254362 | K64: =Drivers!J475 -> 60190021 | L64: =Drivers!K475 -> 69218525 | M64: =Drivers!L475 -> 79601303 | P64: 48268948 | Q64: 50020369 | R64: 64971170
B65: Derivative financial liabilities | C65: 3678494 | D65: 8021783 | E65: 1495317 | G65: 1501262 | H65: 2092198 | I65: 2880667 | J65: =Drivers!I488 -> 1440333.5 | K65: =Drivers!J488 -> 1584366.9 | L65: =Drivers!K488 -> 1742803.5 | M65: =Drivers!L488 -> 1917083.9 | P65: 1560980 | Q65: 5309026 | R65: 2880667
B66: Securities sold under repurchase agreements | C66: 49532385 | D66: 48951394 | E66: 51117342 | G66: 91411522 | H66: 151424854 | I66: 97726435 | J66: =Drivers!I494 -> 1.0794949e+08 | K66: =Drivers!J494 -> 1.1812292e+08 | L66: =Drivers!K494 -> 1.3411089e+08 | M66: =Drivers!L494 -> 1.4925244e+08 | P66: 117895187 | Q66: 133588179 | R66: 97726435
B67: Financial liabilities at amortised cost – due to depositors | C67: 857269981 | D67: 994370875 | E67: 1068982587 | G67: 1286616399 | H67: 1472640456 | I67: 1977743661 | J67: =Drivers!I501 -> 2.1589899e+09 | K67: =Drivers!J501 -> 2.3624583e+09 | L67: =Drivers!K501 -> 2.6822178e+09 | M67: =Drivers!L501 -> 2.9850489e+09 | P67: 2038498641 | Q67: 1958690813 | R67: 1977743661
B68: Financial liabilities at amortised cost – other borrowings | C68: 23786094 | D68: 25361912 | E68: 23248893 | G68: 54555933 | H68: 32587051 | I68: 16150356 | J68: =Drivers!I534 -> 23481198 | K68: =Drivers!J534 -> 35221797 | L68: =Drivers!K534 -> 52832696 | M68: =Drivers!L534 -> 79249043 | P68: 13243625 | Q68: 11481198 | R68: 16150356
B69: Current tax liabilities | C69: 4202850 | D69: 6735997 | E69: 5197188 | G69: 6991005 | H69: 9486772 | I69: 24916074 | J69: =Drivers!I546 -> 9913347.5 | K69: =Drivers!J546 -> 8703757.9 | L69: =Drivers!K546 -> 9505552.3 | M69: =Drivers!L546 -> 10262820 | P69: 14420344 | Q69: 23513300 | R69: 24916074
B70: Deferred tax liabilities | C70: 3565215 | D70: 971424 | E70: 416458 | G70: 403846 | H70: 349106 | I70: 437123 | J70: =Drivers!I547 -> 437123 | K70: =Drivers!J547 -> 437123 | L70: =Drivers!K547 -> 437123 | M70: =Drivers!L547 -> 437123 | P70: 431708 | Q70: 433316 | R70: 437123
B71: Other liabilities | C71: 19508115 | D71: 24547513 | E71: 30775884 | G71: 33572283 | H71: 33253518 | I71: 40354877 | J71: =Drivers!I553 -> 53974747 | K71: =Drivers!J553 -> 59061458 | L71: =Drivers!K553 -> 67055446 | M71: =Drivers!L553 -> 74626222 | P71: 48296812 | Q71: 36253554 | R71: 40354877
B72: Due to subsidiaries | C72: 0 | D72: 0 | E72: 0 | G72: 0 | H72: 0 | I72: 0 | P72: 0
B73: Subordinated liabilities | C73: 25165924 | D73: 37992457 | E73: 37886789 | G73: 38247138 | H73: 38303466 | I73: 61400967 | J73: =Drivers!I559 -> 32384848 | K73: =Drivers!J559 -> 47249167 | L73: =Drivers!K559 -> 67055446 | M73: =Drivers!L559 -> 74626222 | P73: 24869883 | Q73: 33262957 | R73: 61400967
B74: Total liabilities | C74: 1046953950 | D74: 1199315407 | E74: 1272927883 | G74: 1601547444 | H74: 1813938616 | I74: 2286581330 | J74: =SUM(J64:J73) -> 2.4278254e+09 | K74: =SUM(K64:K73) -> 2.6930289e+09 | L74: =SUM(L64:L73) -> 3.0841763e+09 | M74: =SUM(M64:M73) -> 3.4550211e+09 | P74: 2307486128 | Q74: 2252552712 | R74: 2286581330
B75: Equity
B76: Stated capital | C76: 37143541 | D76: 39147882 | E76: 40916958 | G76: 52187747 | H76: 54566957 | I76: 58149621 | J76: =Drivers!I599 -> 62948003 | K76: =Drivers!J599 -> 69242803 | L76: =Drivers!K599 -> 72704943 | M76: =Drivers!L599 -> 76340191 | P76: 62948003 | Q76: 62891772 | R76: 58149621
B77: Statutory reserves | C77: 6492552 | D77: 7444178 | E77: 8387701 | G77: 9285233 | H77: 10590338 | I77: 12079670 | J77: =Drivers!I609 -> 15112929 | K77: =Drivers!J609 -> 16537208 | L77: =Drivers!K609 -> 18775525 | M77: =Drivers!L609 -> 20895342 | P77: 12079670 | Q77: 12079670 | R77: 12079670
B78: Retained earnings | C78: 5086609 | D78: 4949955 | E78: 5182185 | G78: 8124261 | H78: 9890762 | I78: 6790304 | J78: =Drivers!I615 -> 15698892 | K78: =Drivers!J615 -> 26007129 | L78: =Drivers!K615 -> 35614355 | M78: =Drivers!L615 -> 45720540 | P78: 15470462 | Q78: 9216216 | R78: 6790304
B79: Other reserves | C79: 59272098 | D79: 67855834 | E79: 79937405 | G79: 89595571 | H79: 92426660 | I79: 131845571 | J79: =Drivers!I631 -> 1.3580494e+08 | K79: =Drivers!J631 -> 1.4224759e+08 | L79: =Drivers!K631 -> 1.5048236e+08 | M79: =Drivers!L631 -> 1.591448e+08 | P79: 123309743 | Q79: 121617007 | R79: 131845571
B80: Total equity attributable to equity holders of the Bank | C80: 107994800 | D80: 119397849 | E80: 134424249 | G80: 159192812 | H80: 167474717 | I80: 208865166 | J80: =SUM(J76:J79) -> 2.2956477e+08 | K80: =SUM(K76:K79) -> 2.5403473e+08 | L80: =SUM(L76:L79) -> 2.7757718e+08 | M80: =SUM(M76:M79) -> 3.0210087e+08 | P80: 213807878 | Q80: 205804665 | R80: 208865166
B81: Non-controlling interest | C81: 871906 | D81: 1198981 | E81: 1589234 | G81: 1755897 | H81: 2077811 | I81: 4107408 | J81: =I81+J32 -> 4932277.2 | K81: =J81+K32 -> 6006051.9 | L81: =K81+L32 -> 7149769.3 | M81: =L81+M32 -> 8352886.6 | P81: 4217644 | Q81: 3810820 | R81: 4107408
B82: Total equity | C82: 108866706 | D82: 120596830 | E82: 136013483 | G82: 160948709 | H82: 169552528 | I82: 212972574 | J82: =J80+J81 -> 2.3449704e+08 | K82: =K80+K81 -> 2.6004078e+08 | L82: =L80+L81 -> 2.8472695e+08 | M82: =M80+M81 -> 3.1045376e+08 | P82: 218025522 | Q82: 209615485 | R82: 212972574
B83: Total liabilities and equity | C83: 1155820656 | D83: 1319912237 | E83: 1408941366 | G83: 1762496153 | H83: 1983491144 | I83: 2499553904 | J83: =J74+J82 -> 2.6623224e+09 | K83: =K74+K82 -> 2.9530697e+09 | L83: =L74+L82 -> 3.3689033e+09 | M83: =M74+M82 -> 3.7654749e+09 | P83: 2525511650 | Q83: 2462168197 | R83: 2499553904
B84: Contingent liabilities and commitments | C84: 565277821 | D84: 658860264 | E84: 580961807 | G84: 730561685 | H84: 685379028 | I84: 555531537 | Q84: 605333607 | R84: 555531537
B85: Net assets value per ordinary share (Rs.) | C85: 108.44 | D85: 118.13 | E85: 130.83 | G85: 136.42 | H85: 140.24 | I85: 168.47 | J85: =Drivers!I595 -> 174.69072 | K85: =Drivers!J595 -> 193.3115 | L85: =Drivers!K595 -> 211.22648 | M85: =Drivers!L595 -> 229.88815 | P85: 162.7 | Q85: 156.68 | R85: 168.47
B86: Memorandum information
B87: Number of employees | C87: 4982 | D87: 5027 | E87: 5062 | G87: 5057 | H87: 5072 | I87: 5121 | J87: =I87*1.01 -> 5172.21 | K87: =J87*1.01 -> 5223.9321 | L87: =K87*1.01 -> 5276.1714 | M87: =L87*1.01 -> 5328.9331
B88: Number of customer service centres | C88: 280 | D88: 285 | E88: 287 | G88: 287 | H88: 287 | I88: 289 | J88: =I88*1.005 -> 290.445 | K88: =J88*1.005 -> 291.89722 | L88: =K88*1.005 -> 293.35671 | M88: =L88*1.005 -> 294.82349
B90: BS check | C90: =SUM(C45:C61)-SUM(C64:C73)-SUM(C76:C79)-C81 -> 0 | D90: =SUM(D45:D61)-SUM(D64:D73)-SUM(D76:D79)-D81 -> 0 | E90: =SUM(E45:E61)-SUM(E64:E73)-SUM(E76:E79)-E81 -> 0 | G90: =SUM(G45:G61)-SUM(G64:G73)-SUM(G76:G79)-G81 -> 0 | H90: =SUM(H45:H61)-SUM(H64:H73)-SUM(H76:H79)-H81 -> 0 | I90: =SUM(I45:I61)-SUM(I64:I73)-SUM(I76:I79)-I81 -> 0 | Q90: =SUM(Q45:Q61)-SUM(Q64:Q73)-SUM(Q76:Q79)-Q81 -> 0 | R90: =SUM(R45:R61)-SUM(R64:R73)-SUM(R76:R79)-R81 -> 0
B92: Cash / total assets | C92: =C45/C62 -> 0.029998966 | D92: =D45/D62 -> 0.033605236 | E92: =E45/E62 -> 0.038100321 | G92: =G45/G62 -> 0.029080932 | H92: =H45/H62 -> 0.034956233 | I92: =I45/I62 -> 0.060454583 | J92: =J45/J62 -> 0.039783431 | K92: =K45/K62 -> 0.037144427 | L92: =L45/L62 -> 0.047221241 | M92: =M45/M62 -> 0.044651353 | P92: =P45/P62 -> 0.04534453
I93: =((I88/E88)^(1/3))-1 -> 0.0023175054
B94: CASH FLOW STATEMENT
B96: Cash flows from operating activities Profit before income tax | C96: 23280324 | D96: 26098548 | E96: 22983896 | G96: 24519860 | H96: 32957324 | I96: 24505038
B97: Adjustments for:
B98: Non-cash items included in profit before tax | C98: 1078540 | D98: 12380685 | E98: 14014272 | G98: 24764927 | H98: 30473593 | I98: 91299070
B99: Change in operating assets | C99: -125489870 | D99: -169379105 | E99: -84218375 | G99: -374761711 | H99: -230261220 | I99: -463345077
B100: Change in operating liabilities | C100: 100265879 | D100: 138876499 | E100: 69879669 | G100: 325708382 | H100: 208070200 | I100: 430778836
B101: (Gains)/losses on sale of property, plant and equipment | C101: 18774 | D101: -9311 | E101: -19731 | G101: -5820 | H101: -4054 | I101: -20118
B102: Share of (profit)/loss of associate, net of tax | C102: -3678 | D102: -6048 | E102: -9992 | G102: -3898 | H102: -1896 | I102: 3727
B103: Dividends received from investments in associate and subsidiaries | C103: 0 | D103: 0 | E103: 0 | G103: 0 | H103: 0 | I103: 0
B104: Interest expense on subordinated liabilities | C104: 2377694 | D104: 3105553 | E104: 3848979 | G104: 3756921 | H104: 3398554 | I104: 4843571
B105: Net unrealised gains/(losses) arising from translating the Financial Statements of foreign operations | C105: -503140 | D105: 3003952 | E105: -396201 | G105: 596723 | H105: 1278891 | I105: 18347815
B106: Benefits paid on defined benefit plans | C106: -184464 | D106: -382409 | E106: -198799 | G106: -673106 | H106: -1116195 | I106: -780828
B107: Income tax paid | C107: -3810701 | D107: -5971026 | E107: -8301839 | G107: -7748870 | H107: -8963620 | I107: -11143271
...

Sheet Drivers
B3: For the year ended December 31, | N3: Annualised | P3: Period | Q3: Quarter
B4: (LKR '000 except per share data) | C4: 2017 | D4: 2018 | E4: 2019 | F4: 2020 | G4: 2021 | H4: 2022 | I4: 2023F | J4: 2024F | K4: 2025F | L4: 2026F | N4: 45192 | O4: 45100 | P4: 45078
B5: INCOME STATEMENT
B7: Interest income | C7: 104049102 | D7: 118551239 | E7: 129287743 | F7: 124087713 | G7: 132818178 | H7: 222393079 | I7: =I13+SUM(I14:I19) -> 3.0585734e+08 | J7: =J13+SUM(J14:J19) -> 2.9513936e+08 | K7: =K13+SUM(K14:K19) -> 3.3784948e+08 | L7: =L13+SUM(L14:L19) -> 3.8175485e+08 | N7: =FS!P7/9*12 -> 2.9942669e+08 | P7: 150811644 | Q7: 88116673 | R7: =P7*2 -> 301623288
B9: Cash and cash equivalents | C9: 362695 | D9: 411412 | E9: 1290697 | F9: 1053757 | G9: 447742 | H9: 945450 | I9: =FS!I45*Drivers!I55 -> 2055089.1 | J9: =FS!J45*Drivers!J55 -> 1440462 | K9: =FS!K45*Drivers!K55 -> 1491785.1 | L9: =FS!L45*Drivers!L55 -> 2163539.6
B10: Balances with Central Banks | C10: 4400 | D10: 26734 | E10: 62572 | F10: 1175509 | G10: 1299948 | H10: 815979
B11: Placements with Banks | C11: 215909 | D11: 529738 | E11: 931571 | F11: 777425 | G11: 778021 | H11: 1685996 | I11: =I252*I28 -> 1348796.8 | J11: =J252*J28 -> 1416236.6 | K11: =K252*K28 -> 1487048.5 | L11: =L252*L28 -> 1561400.9
B12: Securities purchased under resale agreements | C12: 139153 | D12: 508616 | E12: 1906902 | F12: 836773 | G12: 375398 | H12: 1133583 | I12: =I264*I29 -> 453433.2 | J12: =J264*J29 -> 476104.86 | K12: =K264*K29 -> 499910.1 | L12: =L264*L29 -> 524905.61
B13: Financial assets recognized through profit or loss | C13: 469012 | D13: 323335 | E13: 474478 | F13: 1831327 | G13: 1101385 | H13: 1516691 | I13: =SUM(I9:I12) -> 3857319.1 | J13: =SUM(J9:J12) -> 3332803.5 | K13: =SUM(K9:K12) -> 3478743.7 | L13: =SUM(L9:L12) -> 4249846.1
B14: Derivatives | C14: 24111 | D14: 56173 | E14: 67453 | F14: 34902 | G14: 167377 | H14: 237438 | I14: =I266*I31 -> 166206.6 | J14: =J266*J31 -> 174516.93 | K14: =K266*K31 -> 183242.78 | L14: =L266*L31 -> 192404.92
B15: Other financial instruments | C15: 444901 | D15: 267162 | E15: 407025 | F15: 1796425 | G15: 934008 | H15: 1279253 | I15: =I271*I32 -> 4946643.7 | J15: =J271*J32 -> 7798003.1 | K15: =K271*K32 -> 8577803.4 | L15: =L271*L32 -> 9435583.8
B16: Financial assets at amortized cost - loans and advances to other customers | C16: 78132371 | D16: 95081154 | E16: 100444369 | F16: 84257196 | G16: 79654575 | H16: 144253496 | I16: =I33*I305 -> 2.028142e+08 | J16: =J33*J305 -> 1.8785541e+08 | K16: =K33*K305 -> 2.1976882e+08 | L16: =L33*L305 -> 2.5273414e+08
B17: Financial assets at amortized cost - debt and other financial instruments | C17: 8512118 | D17: 6828671 | E17: 7819563 | F17: 13194851 | G17: 25951467 | H17: 51750895 | I17: =I50*I341 -> 48193316 | J17: =J50*J341 -> 45412106 | K17: =K50*K341 -> 50127260 | L17: =L50*L341 -> 53757016
B18: Financial assets measured at fair value through other comprehensive income | C18: 15349974 | D18: 14478042 | E18: 15091368 | F18: 18053545 | G18: 22034788 | H18: 18995711 | I18: =I52*I384 -> 44543209 | J18: =J52*J384 -> 48997530 | K18: =K52*K384 -> 53897283 | L18: =L52*L384 -> 59287011
B19: Interest accrued on impaired loans and advances to other customers | C19: 861057 | D19: 360876 | E19: 1258339 | F19: 2895955 | G19: 1174854 | H19: 1295278 | I19: =I53*I289 -> 1336443.5 | J19: =J53*J289 -> 1568988.3 | K19: =K53*K289 -> 1816328.7 | L19: =L53*L289 -> 2098847.6
C20: 2413 | D20: 2661 | E20: 7884 | F20: 11375 | G20: 0 | H20: 0
B22: Check | C22: =SUM(C9:C13)+C16+C17+C18+C19+C20-C7 -> 0 | D22: =SUM(D9:D13)+D16+D17+D18+D19+D20-D7 -> 0 | E22: =SUM(E9:E13)+E16+E17+E18+E19+E20-E7 -> 0 | F22: =SUM(F9:F13)+F16+F17+F18+F19+F20-F7 -> 0 | G22: =SUM(G9:G13)+G16+G17+G18+G19+G20-G7 -> 0 | H22: =SUM(H9:H13)+H16+H17+H18+H19+H20-H7 -> 0
B24: Interest rate
B26: Cash and cash equivalents | C26: =C9/FS!C45 -> 0.010460317 | D26: =D9/FS!D45 -> 0.0092752356 | E26: =E9/FS!E45 -> 0.02404378 | F26: =F9/FS!G45 -> 0.020559094 | G26: =G9/FS!H45 -> 0.0064576268 | H26: =H9/FS!I45 -> 0.0062567215 | I26: 0.0062567215 | J26: 0.0062567215 | K26: 0.0062567215 | L26: 0.0062567215
B27: Balances with Central Banks | C27: =C10/FS!C46 -> 9.6604889e-05 | D27: =D10/FS!D46 -> 0.00048250626 | E27: =E10/FS!E46 -> 0.0013572739 | F27: =F10/FS!G46 -> 0.010190031 | G27: =G10/FS!H46 -> 0.022895492 | H27: =H10/FS!I46 -> 0.010381793 | I27: 0.010381793 | J27: 0.010381793 | K27: 0.010381793 | L27: 0.010381793
B28: Placements with Banks | C28: =C11/FS!C47 -> 0.012244411 | D28: =D11/FS!D47 -> 0.026621987 | E28: =E11/FS!E47 -> 0.037406768 | F28: =F11/FS!G47 -> 0.047340841 | G28: =G11/FS!H47 -> 0.062248109 | H28: =H11/FS!I47 -> 0.017547299 | I28: 0.017547299 | J28: 0.017547299 | K28: 0.017547299 | L28: 0.017547299
B29: Securities purchased under resale agreements | C29: =C12/FS!C48 -> #DIV/0! | D29: =D12/FS!D48 -> 0.053462486 | E29: =E12/FS!E48 -> 0.14503876 | F29: =F12/FS!G48 -> #DIV/0! | G29: =G12/FS!H48 -> 0.12511223 | H29: =H12/FS!I48 -> 0.74710145 | I29: 0.74710145 | J29: 0.74710145 | K29: 0.74710145 | L29: 0.74710145
B30: Financial assets recognized through profit or loss
B31: Derivatives | C31: =C14/FS!C49 -> 0.010327962 | D31: =D14/FS!D49 -> 0.0071015512 | E31: =E14/FS!E49 -> 0.036840901 | F31: =F14/FS!G49 -> 0.013236915 | G31: =G14/FS!H49 -> 0.051578062 | H31: =H14/FS!I49 -> 0.028452416 | I31: 0.028452416 | J31: 0.028452416 | K31: 0.028452416 | L31: 0.028452416
B32: Other financial instruments | C32: =C15/C271 -> 0.1008637 | D32: =D15/D271 -> 0.048397449 | E32: =E15/E271 -> 0.018959585 | F32: =F15/F271 -> 0.051050071 | G32: =G15/G271 -> 0.039853349 | H32: =H15/H271 -> 0.051431274 | I32: 0.05 | J32: 0.05 | K32: 0.05 | L32: 0.05
B33: Financial assets at amortized cost - loans and advances to other customers | C33: =C16/FS!C52 -> 0.1052367 | D33: =D16/FS!D52 -> 0.10958949 | E33: =E16/FS!E52 -> 0.11236402 | F33: =F16/FS!G52 -> 0.09260771 | G33: =G16/FS!H52 -> 0.07736578 | H33: =H16/FS!I52 -> 0.12484157 | I33: 0.155 | J33: 0.12484157 | K33: 0.127 | L33: 0.127
B34: Overdrafts | H34: 0.28 | I34: 0.28 | J34: 0.28 | K34: 0.28 | L34: 0.28
B35: Trade finance | H35: 0.155 | I35: 0.155 | J35: 0.155 | K35: 0.155 | L35: 0.155
B36: Lease/hire purchase receivable | H36: 0.16 | I36: 0.16 | J36: 0.16 | K36: 0.16 | L36: 0.16
B37: Credit cards | H37: 0.28 | I37: 0.28 | J37: 0.28 | K37: 0.28 | L37: 0.28
B38: Pawning
B39: Staff loans
B40: Housing loans | H40: 0.15 | I40: 0.15 | J40: 0.15 | K40: 0.15 | L40: 0.15
B41: Personal loans
B42: Term loans
B43: Short term
B44: Long term | H44: =H47+2% -> 0.16 | I44: 0.16 | J44: 0.16 | K44: 0.16 | L44: 0.16
B45: Bills of exchange
B47: Average AWPLR throughout the year | H47: 0.14 | I47: 0.14 | J47: 0.14 | K47: 0.14 | L47: 0.14
B50: Financial assets at amortized cost - debt and other financial instruments | C50: =C17/FS!C53 -> 0.072088775 | D50: =D17/FS!D53 -> 0.076490797 | E50: =E17/FS!E53 -> 0.073039739 | F50: =F17/FS!G53 -> 0.043682949 | G50: =G17/FS!H53 -> 0.067338091 | H50: =H17/FS!I53 -> 0.067945748 | I50: 0.067945748 | J50: 0.067945748 | K50: 0.067945748 | L50: 0.067945748
B52: Financial assets measured at fair value through other comprehensive income | C52: =C18/FS!C54 -> 0.099087296 | D52: =D18/FS!D54 -> 0.081907626 | E52: =E18/FS!E54 -> 0.076286449 | F52: =F18/FS!G54 -> 0.064773797 | G52: =G18/FS!H54 -> 0.065588744 | H52: =H18/FS!I54 -> 0.16009566 | I52: 0.15 | J52: 0.15 | K52: 0.15 | L52: 0.15
B53: Interest accrued on impaired loans and advances to other customers | C53: =C19/C289 -> 0.00115976 | D53: =D19/D289 -> 0.0004159417 | E53: =E19/E289 -> 0.0014076651 | F53: =F19/F289 -> 0.0031829656 | G53: =G19/G289 -> 0.0011410957 | H53: =H19/H289 -> 0.0011209748 | I53: 0.0011 | J53: 0.0011 | K53: 0.0011 | L53: 0.0011
B55: Interest on opening cash | E55: =E9/FS!D45 -> 0.029098614 | F55: =F9/FS!E45 -> 0.019629938 | G55: =G9/FS!G45 -> 0.0087355719 | H55: =H9/FS!H45 -> 0.013635896 | I55: 0.0136 | J55: 0.0136 | K55: 0.0136 | L55: 0.0136
B58: Interest expense | C58: 64481804 | D58: 72933030 | E58: 80931352 | F58: 73218911 | G58: 66401846 | H58: 137727868 | I58: =I63+I69 -> 2.2269493e+08 | J58: =J63+J69 -> 2.3202049e+08 | K58: =K63+K69 -> 2.6615841e+08 | L58: =L63+L69 -> 3.0080788e+08 | N58: =FS!P8/9*12 -> 2.18251e+08 | P58: 113361974 | Q58: 47404088 | R58: =P58*2 -> 226723948
B60: Due to banks | C60: 2069416 | D60: 2313673 | E60: 2484166 | F60: 2845641 | G60: 3326777 | H60: 4019415
B61: Derivative financial liabilities | C61: 38702 | D61: 57860 | E61: 63161 | F61: 65473 | G61: 196903 | H61: 422823
B62: Securities sold under repurchase agreements | C62: 5943417 | D62: 3815335 | E62: 3256622 | F62: 3516363 | G62: 6190149 | H62: 21906770
B63: Financial liabilities at amortised cost – due to depositors | C63: 53385259 | D63: 62397741 | E63: 69503417 | F63: 61416382 | G63: 51533473 | H63: 105008989 | I63: =I501*I71 -> 1.8999111e+08 | J63: =J501*J71 -> 1.8899667e+08 | K63: =K501*K71 -> 2.1457743e+08 | L63: =L501*L71 -> 2.3880391e+08
B64: Refinance borrowings | C64: 352074 | D64: 427958 | E64: 472813 | F64: 578780 | G64: 679976 | H64: 551968
B65: Foreign currency borrowings | C65: 315242 | D65: 814910 | E65: 872931 | F65: 603597 | G65: 624395 | H65: 476698
B66: Subordinated liabilities | C66: 2377694 | D66: 3105553 | E66: 3848979 | F66: 3756921 | G66: 3398554 | H66: 4843571
B67: Interest expense on lease liabilities | E67: 429263 | F67: 435754 | G67: 451619 | H67: 497634
B69: Interest expense except depositors | C69: =C60+C61+C62+C64+C65+C66+C67 -> 11096545 | D69: =D60+D61+D62+D64+D65+D66+D67 -> 10535289 | E69: =E60+E61+E62+E64+E65+E66+E67 -> 11427935 | F69: =F60+F61+F62+F64+F65+F66+F67 -> 11802529 | G69: =G60+G61+G62+G64+G65+G66+G67 -> 14868373 | H69: =H60+H61+H62+H64+H65+H66+H67 -> 32718879 | I69: =I72*(FS!J64+FS!J65+FS!J66+FS!J68) -> 32703824 | J69: =J72*(FS!K64+FS!K65+FS!K66+FS!K68) -> 43023820 | K69: =K72*(FS!L64+FS!L65+FS!L66+FS!L68) -> 51580983 | L69: =L72*(FS!M64+FS!M65+FS!M66+FS!M68) -> 62003975
B71: Deposit interest rate | C71: =C63/C501 -> 0.062273566 | D71: =D63/D501 -> 0.062750974 | E71: =E63/E501 -> 0.065018287 | F71: =F63/F501 -> 0.047734804 | G71: =G63/G501 -> 0.034993927 | H71: =H63/H501 -> 0.053095349 | I71: 0.088 | J71: 0.08 | K71: 0.08 | L71: 0.08
B72: Other financial liabilities | C72: =(C60+C61+C62+C64+C65+C66+C67)/(FS!C64+FS!C65+FS!C66+FS!C68) -> 0.080853936 | D72: =(D60+D61+D62+D64+D65+D66+D67)/(FS!D64+FS!D65+FS!D66+FS!D68) -> 0.078214645 | E72: =(E60+E61+E62+E64+E65+E66+E67)/(FS!E64+FS!E65+FS!E66+FS!E68) -> 0.088131605 | F72: =(F60+F61+F62+F64+F65+F66+F67)/(FS!G64+FS!G65+FS!G66+FS!G68) -> 0.050070807 | G72: =(G60+G61+G62+G64+G65+G66+G67)/(FS!H64+FS!H65+FS!H66+FS!H68) -> 0.057206887 | H72: =(H60+H61+H62+H64+H65+H66+H67)/(FS!I64+FS!I65+FS!I66+FS!I68) -> 0.18004251 | I72: 0.19 | J72: 0.2 | K72: 0.2 | L72: 0.2
B74: Check | C74: =SUM(C60:C67)-C58 -> 0 | D74: =SUM(D60:D67)-D58 -> 0 | E74: =SUM(E60:E67)-E58 -> 0 | F74: =SUM(F60:F67)-F58 -> 0 | G74: =SUM(G60:G67)-G58 -> 0 | H74: =SUM(H60:H67)-H58 -> 0
B78: Fee and commission income | C78: 10510800 | D78: 12494090 | E78: 12874966 | F78: 11839689 | G78: 15917337 | H78: 26191530 | I78: =I89*FS!J52 -> 30373717 | J78: =J89*FS!K52 -> 35658826 | K78: =K89*FS!L52 -> 41280198 | L78: =L89*FS!M52 -> 47701081 | N78: =FS!P10/9*12 -> 29379307 | P78: 14377446 | Q78: 11758745 | R78: =P78*2 -> 28754892
B80: Loans and advances related services | C80: 834468 | D80: 944858 | E80: 881213 | F80: 861317 | G80: 995957 | H80: 683255
B81: Credit and debit cards related services | C81: 3389773 | D81: 4191679 | E81: 4566923 | F81: 3723129 | G81: 6011952 | H81: 9963857
B82: Trade and remittances related services | C82: 3184574 | D82: 3812516 | E82: 3998926 | F82: 4431425 | G82: 5618954 | H82: 11155415
B83: Deposits related services | C83: 1687448 | D83: 1952323 | E83: 1852565 | F83: 1151909 | G83: 1152602 | H83: 1333869
B84: Guarantees related services | C84: 798583 | D84: 1063585 | E84: 942615 | F84: 908508 | G84: 1091690 | H84: 1342030
B85: Other financial services | C85: 615954 | D85: 529129 | E85: 632724 | F85: 763401 | G85: 1046182 | H85: 1713104
B87: Check | C87: =SUM(C80:C85)-C78 -> 0 | D87: =SUM(D80:D85)-D78 -> 0 | E87: =SUM(E80:E85)-E78 -> 0 | F87: =SUM(F80:F85)-F78 -> 0 | G87: =SUM(G80:G85)-G78 -> 0 | H87: =SUM(H80:H85)-H78 -> 0
B89: As a % of loan book | E89: =E78/FS!E52 -> 0.014402828 | F89: =F78/FS!G52 -> 0.01301309 | G89: =G78/FS!H52 -> 0.015459968 | H89: =H78/FS!I52 -> 0.022666983 | I89: 0.025 | J89: 0.025 | K89: 0.025 | L89: 0.025
B93: Fee and commission expense | C93: 1586334 | D93: 1859698 | E93: 2123128 | F93: 2018014 | G93: 3675143 | H93: 6022429 | I93: =I102*I78 -> 7593429.2 | J93: =J102*J78 -> 8201529.9 | K93: =K102*K78 -> 9494445.4 | L93: =L102*L78 -> 10971249 | N93: =FS!P11/9*12 -> 7766089.3 | P93: 3786488 | Q93: 2881243 | R93: =P93*2 -> 7572976
B95: Loans and advances related services | C95: 58313 | D95: 66131 | E95: 54028 | F95: 48591 | G95: 52020 | H95: 57915
B96: Credit and debit cards related services | C96: 1385010 | D96: 1631600 | E96: 1877797 | F96: 1811962 | G96: 3439222 | H96: 5721589
B97: Trade and remittances related services | C97: 44205 | D97: 47204 | E97: 62299 | F97: 55456 | G97: 63092 | H97: 89244
B98: Other financial services | C98: 98806 | D98: 114763 | E98: 129004 | F98: 102005 | G98: 120809 | H98: 153681
B100: Check | C100: =SUM(C95:C98)-C93 -> 0 | D100: =SUM(D95:D98)-D93 -> 0 | E100: =SUM(E95:E98)-E93 -> 0 | F100: =SUM(F95:F98)-F93 -> 0 | G100: =SUM(G95:G98)-G93 -> 0 | H100: =SUM(H95:H98)-H93 -> 0
B102: As a % of fee income | C102: =C93/C78 -> 0.15092419 | D102: =D93/D78 -> 0.14884621 | E102: =E93/E78 -> 0.16490358 | F102: =F93/F78 -> 0.17044485 | G102: =G93/G78 -> 0.23088931 | H102: =H93/H78 -> 0.22993804 | I102: 0.25 | J102: 0.23 | K102: 0.23 | L102: 0.23
B106: Net gains/(losses) from trading | C106: 233956 | D106: -3033236 | E106: 1360833 | F106: 1878060 | G106: 1936007 | H106: 35297450 | I106: =FS!P13/9*12 -> -16199576 | J106: =G106*1.01 -> 1955367.1 | K106: =J106*1.01 -> 1974920.7 | L106: =K106*1.01 -> 1994669.9 | P106: -15531353 | Q106: 32101899 | R106: =P106*2 -> -31062706
B108: Derivative financial instruments | C108: 107201 | D108: -3121949 | E108: 1078749 | F108: 977206 | G108: 1748834 | H108: 35903416
B109: Foreign exchange gains/(losses) from banks and other customers | C109: 107201 | D109: -3121949 | E109: 1078749 | F109: 977206 | G109: 1804014 | H109: 36357421
B110: Financial assets recognised through profit or loss – measured at fair value | G110: -55180 | H110: -454004
B111: Government Securities | C111: 122390 | D111: -4839 | E111: 67548 | F111: 557579 | G111: -162829 | H111: -1169637
B112: Net mark-to-market gains/(losses) | C112: 94672 | D112: -24572 | E112: 26386 | F112: 226036 | G112: -583205 | H112: -1320747
B113: Net capital gains | C113: 27718 | D113: 19733 | E113: 41162 | F113: 331543 | G113: 420376 | H113: 150809
B114: Equities | C114: 4365 | D114: 93552 | E114: 214536 | F114: 343275 | G114: 350002 | H114: 563971
B115: Net mark-to-market gains/(losses) | C115: -9046 | D115: 80151 | E115: 200299 | F115: 303612 | G115: 105673 | H115: 348256
B116: Net capital gains | C116: 3251 | D116: 1026 | E116: 916 | F116: 20468 | G116: 207954 | H116: 175531
B117: Dividend income | C117: 10160 | D117: 12375 | E117: 13321 | F117: 19195 | G117: 36375 | H117: 40184
B119: Check | C119: =SUM(C115:C117,C112:C113,C109:C110)-C106 -> 0 | D119: =SUM(D115:D117,D112:D113,D109:D110)-D106 -> 0 | E119: =SUM(E115:E117,E112:E113,E109:E110)-E106 -> 0 | F119: =SUM(F115:F117,F112:F113,F109:F110)-F106 -> 0 | G119: =SUM(G115:G117,G112:G113,G109:G110)-G106 -> 0 | H119: =SUM(H115:H117,H112:H113,H109:H110)-H106 -> 0
B123: Net other operating income | C123: 720026 | D123: 11373098 | E123: 6081876 | F123: 7770754 | G123: 10002216 | H123: -3771999 | I123: =FS!P15/9*12 -> 25159709 | J123: =I123*1.05 -> 26417695 | K123: =J123*1.05 -> 27738580 | L123: =K123*1.05 -> 29125509 | P123: 17086020 | Q123: -12524129 | R123: =P123*2 -> 34172040
B125: Gains/(losses) on sale of property, plant and equipment | C125: -18774 | D125: 9311 | E125: 19731 | F125: 5820 | G125: 4054 | H125: 20118
B126: Gains on revaluation of foreign exchange | C126: 489824 | D126: 11185438 | E126: 5783595 | F126: 7395513 | G126: 8832749 | H126: -5133408
B127: Recoveries o/a loans written off | C127: 32820 | D127: 21288 | E127: 20360 | F127: 157103 | G127: 316277 | H127: 449028
B128: Dividend income from subsidiaries | C128: 0 | D128: 0 | E128: 0 | F128: 0 | G128: =-4111+4111 -> 0 | H128: 0
B129: Dividend income from other equity securities | C129: =37938+4111-4111 -> 37938 | D129: 34119 | E129: 40076 | F129: 28739 | G129: 48638 | H129: 54571
B130: Profit due to change in ownership | C130: 5262 | D130: 3344 | E130: 14498 | F130: 0
B131: Rental and other income | C131: 178218 | D131: 122942 | E131: 218114 | F131: 183579 | G131: 795214 | H131: 829742
B132: Less: Profit due to change in ownership | C132: -5262 | D132: -3344 | E132: -14498 | F132: 0 | G132: 5284 | H132: 7950
B134: Check | C134: =SUM(C125:C131)+C132-C123 -> 0 | D134: =SUM(D125:D131)+D132-D123 -> 0 | E134: =SUM(E125:E131)+E132-E123 -> 0 | F134: =SUM(F125:F131)+F132-F123 -> 0 | G134: =SUM(G125:G131)+G132-G123 -> 0 | H134: =SUM(H125:H131)+H132-H123 -> 0
B138: Impairment charges and other losses | C138: 989315 | D138: 8833362 | E138: 11331523 | F138: 21419532 | G138: 25139926 | H138: 71924260 | I138: =I151*I305 -> 35328926 | J138: =J151*J305 -> 30095011 | K138: =K151*K305 -> 34609262 | L138: =L151*L305 -> 39800652 | N138: =FS!P17/9*12 -> 34376147 | P138: 13210963 | Q138: 35218619 | R138: =P138*2 -> 26421926
B140: Loans and advances to other customers | C140: 988639 | D140: 8379540 | E140: 10309857 | F140: 18124673 | G140: 14947268 | H140: 22296719
B141: Individual impairment | C141: -22317 | D141: -1002000 | E141: 1938437 | F141: 3983706
B142: Collective impairment | C142: 1211813 | D142: 9381540 | E142: 8371420 | F142: 14140967
B144: Other financial assets and off-balance sheet credit exposures | C144: 0 | D144: 452856 | E144: 1020414 | F144: 3291313 | G144: =6948387+3242610 -> 10190997 | H144: =47281554+2196056 -> 49477610
B145: Total impairment charges | C145: 988639 | D145: 8832396 | E145: 11330271 | F145: 21415986 | G145: 25138265 | H145: 71774329
...

Sheet Ratios
C2: =FS!C4 -> 2017 | D2: =FS!D4 -> 2018 | E2: =FS!E4 -> 2019 | F2: =FS!G4 -> 2020 | G2: =FS!H4 -> 2021 | H2: =FS!I4 -> 2022 | I2: =FS!J4 -> 2023F | J2: =FS!K4 -> 2024F | K2: =FS!L4 -> 2025F | L2: =FS!M4 -> 2026F
B3: Avg. yield on interest earning assets | C3: =FS!C7/(FS!C49+FS!C50+FS!C51+FS!C52+FS!C53+FS!C54) -> 0.10172748 | D3: =FS!D7/(FS!D49+FS!D50+FS!D51+FS!D52+FS!D53+FS!D54) -> 0.10328201 | E3: =FS!E7/(FS!E49+FS!E50+FS!E51+FS!E52+FS!E53+FS!E54) -> 0.1057257 | F3: =FS!G7/(FS!G49+FS!G50+FS!G51+FS!G52+FS!G53+FS!G54) -> 0.081144905 | G3: =FS!H7/(FS!H49+FS!H50+FS!H51+FS!H52+FS!H53+FS!H54) -> 0.074717288 | H3: =FS!I7/(FS!I49+FS!I50+FS!I51+FS!I52+FS!I53+FS!I54) -> 0.10748751 | I3: =FS!J7/(FS!J49+FS!J50+FS!J51+FS!J52+FS!J53+FS!J54) -> 0.13149674 | J3: =FS!K7/(FS!K49+FS!K50+FS!K51+FS!K52+FS!K53+FS!K54) -> 0.1142421 | K3: =FS!L7/(FS!L49+FS!L50+FS!L51+FS!L52+FS!L53+FS!L54) -> 0.11545382 | L3: =FS!M7/(FS!M49+FS!M50+FS!M51+FS!M52+FS!M53+FS!M54) -> 0.11603704
B4: Avg. cost on interest bearing funds | C4: =FS!C8/(FS!C64+FS!C65+FS!C66+FS!C67+FS!C68) -> 0.064837643 | D4: =FS!D8/(FS!D64+FS!D65+FS!D66+FS!D67+FS!D68) -> 0.064595781 | E4: =FS!E8/(FS!E64+FS!E65+FS!E66+FS!E67+FS!E68) -> 0.067518664 | F4: =FS!G8/(FS!G64+FS!G65+FS!G66+FS!G67+FS!G68) -> 0.048096509 | G4: =FS!H8/(FS!H64+FS!H65+FS!H66+FS!H67+FS!H68) -> 0.038326172 | H4: =FS!I8/(FS!I64+FS!I65+FS!I66+FS!I67+FS!I68) -> 0.063778484 | I4: =FS!J8/(FS!J64+FS!J65+FS!J66+FS!J67+FS!J68) -> 0.095531498 | J4: =FS!K8/(FS!K64+FS!K65+FS!K66+FS!K67+FS!K68) -> 0.090014943 | K4: =FS!L8/(FS!L64+FS!L65+FS!L66+FS!L67+FS!L68) -> 0.090526292 | L4: =FS!M8/(FS!M64+FS!M65+FS!M66+FS!M67+FS!M68) -> 0.091290321
B5: Net interest margin | C5: =FS!C9/(FS!C49+FS!C50+FS!C51+FS!C52+FS!C53+FS!C54) -> 0.038684441 | D5: =FS!D9/(FS!D49+FS!D50+FS!D51+FS!D52+FS!D53+FS!D54) -> 0.039742648 | E5: =FS!E9/(FS!E49+FS!E50+FS!E51+FS!E52+FS!E53+FS!E54) -> 0.039543682 | F5: =FS!G9/(FS!G49+FS!G50+FS!G51+FS!G52+FS!G53+FS!G54) -> 0.033264729 | G5: =FS!H9/(FS!H49+FS!H50+FS!H51+FS!H52+FS!H53+FS!H54) -> 0.037362719 | H5: =FS!I9/(FS!I49+FS!I50+FS!I51+FS!I52+FS!I53+FS!I54) -> 0.040920576 | I5: =FS!J9/(FS!J49+FS!J50+FS!J51+FS!J52+FS!J53+FS!J54) -> 0.035753876 | J5: =FS!K9/(FS!K49+FS!K50+FS!K51+FS!K52+FS!K53+FS!K54) -> 0.024431959 | K5: =FS!L9/(FS!L49+FS!L50+FS!L51+FS!L52+FS!L53+FS!L54) -> 0.024499099 | L5: =FS!M9/(FS!M49+FS!M50+FS!M51+FS!M52+FS!M53+FS!M54) -> 0.024604392
B6: Interest rate spread | C6: =C3-C4 -> 0.036889834 | D6: =D3-D4 -> 0.038686225 | E6: =E3-E4 -> 0.038207039 | F6: =F3-F4 -> 0.033048396 | G6: =G3-G4 -> 0.036391117 | H6: =H3-H4 -> 0.043709029 | I6: =I3-I4 -> 0.035965245 | J6: =J3-J4 -> 0.024227159 | ... L6: =L3-L4 -> 0.024746718
B7: Cost to income (operating) | C7: =FS!C23/FS!C16 -> 0.4112972 | D7: =FS!D23/FS!D16 -> 0.36825623 | E7: =FS!E23/FS!E16 -> 0.38597706 | F7: =FS!G23/FS!G16 -> 0.34227536 | G7: =FS!H23/FS!H16 -> 0.31686186 | H7: =FS!I23/FS!I16 -> 0.26553814 | I7: =FS!J23/FS!J16 -> 0.36014337 | J7: =FS!K23/FS!K16 -> 0.3938361 | K7: =FS!L23/FS!L16 -> 0.40024182 | L7: =FS!M23/FS!M16 -> 0.40865195
B8: Cost to income (with impairments) | C8: =(FS!C23+FS!C17)/FS!C6 -> 0.1847993 | D8: =(FS!D23+FS!D17)/FS!D6 -> 0.23428872 | E8: =(FS!E23+FS!E17)/FS!E6 -> 0.24848571 | F8: =(FS!G23+FS!G17)/FS!G6 -> 0.31376765 | G8: =(FS!H23+FS!H17)/FS!H6 -> 0.33479493 | H8: =(FS!I23+FS!I17)/FS!I6 -> 0.38591847 | I8: =(FS!J23/FS!J6) -> 0.12230364 | J8: =(FS!K23/FS!K6) -> 0.13311063 | K8: =(FS!L23/FS!L6) -> 0.13292398 | L8: =(FS!M23/FS!M6) -> 0.13444637
B9: Impairments/ Gross loans | C9: =Drivers!C315/Drivers!C311 -> 0.023682969 | D9: =Drivers!D315/Drivers!D311 -> 0.033792109 | E9: =Drivers!E315/Drivers!E311 -> 0.039557968 | F9: =Drivers!F315/Drivers!F311 -> 0.054093105 | G9: =Drivers!G315/Drivers!G311 -> 0.059681216 | H9: =Drivers!H315/Drivers!H311 -> 0.07276509 | I9: =Drivers!I315/Drivers!I311 -> 0.07148 | J9: =Drivers!J315/Drivers!J311 -> 0.0521 | ... L9: =Drivers!L315/Drivers!L311 -> 0.0412
B10: Net margin | C10: =FS!C30/FS!C6 -> 0.1438215 | D10: =FS!D30/FS!D6 -> 0.12790484 | E10: =FS!E30/FS!E6 -> 0.11556498 | F10: =FS!G30/FS!G6 -> 0.11243798 | G10: =FS!H30/FS!H6 -> 0.14840533 | H10: =FS!I30/FS!I6 -> 0.087020714 | I10: =FS!J30/FS!J6 -> 0.059137383 | J10: =FS!K30/FS!K6 -> 0.073978971 | K10: =FS!L30/FS!L6 -> 0.069279017 | L10: =FS!M30/FS!M6 -> 0.064732691
B11: ROE | C11: =FS!C30/FS!C82 -> 0.15272352 | D11: =FS!D30/FS!D82 -> 0.14812024 | E11: =FS!E30/FS!E82 -> 0.12807845 | F11: =FS!G30/FS!G82 -> 0.106163 | G11: =FS!H30/FS!H82 -> 0.14326114 | H11: =FS!I30/FS!I82 -> 0.11456626 | I11: =FS!J30/FS!J82 -> 0.087940259 | J11: =FS!K30/FS!K82 -> 0.10323137 | K11: =FS!L30/FS!L82 -> 0.1004223 | L11: =FS!M30/FS!M82 -> 0.096883779
B12: ROA | C12: =FS!C30/FS!C62 -> 0.014385023 | D12: =FS!D30/FS!D62 -> 0.013533348 | E12: =FS!E30/FS!E62 -> 0.012364174 | F12: =FS!G30/FS!G62 -> 0.0096946578 | G12: =FS!H30/FS!H62 -> 0.01224623 | H12: =FS!I30/FS!I62 -> 0.0097615306 | I12: =FS!J30/FS!J62 -> 0.0077457677 | J12: =FS!K30/FS!K62 -> 0.009090326 | K12: =FS!L30/FS!L62 -> 0.0084873126 | L12: =FS!M30/FS!M62 -> 0.0079878194
B13: Equity/ total assets | C13: =FS!C82/FS!C62 -> 0.094189964 | D13: =FS!D82/FS!D62 -> 0.09136731 | E13: =FS!E82/FS!E62 -> 0.096535943 | F13: =FS!G82/FS!G62 -> 0.091318616 | G13: =FS!H82/FS!H62 -> 0.085481868 | H13: =FS!I82/FS!I62 -> 0.085204233 | I13: =FS!J82/FS!J62 -> 0.088079883 | J13: =FS!K82/FS!K62 -> 0.088057786 | K13: =FS!L82/FS!L62 -> 0.084516214 | L13: =FS!M82/FS!M62 -> 0.082447439
B14: Deposits / total assets | C14: =FS!C67/FS!C62 -> 0.7416981 | D14: =FS!D67/FS!D62 -> 0.75336136 | E14: =FS!E67/FS!E62 -> 0.75871332 | F14: =FS!G67/FS!G62 -> 0.72999671 | G14: =FS!H67/FS!H62 -> 0.74244872 | H14: =FS!I67/FS!I62 -> 0.79123865 | I14: =FS!J67/FS!J62 -> 0.81094232 | J14: =FS!K67/FS!K62 -> 0.80000087 | K14: =FS!L67/FS!L62 -> 0.79616944 | L14: =FS!M67/FS!M62 -> 0.79274167
B15: Cash / total assets | C15: =FS!C45/FS!C62 -> 0.029998966 | D15: =FS!D45/FS!D62 -> 0.033605236 | E15: =FS!E45/FS!E62 -> 0.038100321 | F15: =FS!G45/FS!G62 -> 0.029080932 | G15: =FS!H45/FS!H62 -> 0.034956233 | H15: =FS!I45/FS!I62 -> 0.060454583 | I15: =FS!J45/FS!J62 -> 0.039783431 | J15: =FS!K45/FS!K62 -> 0.037144427 | K15: =FS!L45/FS!L62 -> 0.047221241 | L15: =FS!M45/FS!M62 -> 0.044651353
B16: Gross income per employee | C16: =FS!C6/FS!C87 -> 23204.568 | D16: =FS!D6/FS!D87 -> 27781.419 | E16: =FS!E6/FS!E87 -> 29778.967 | F16: =FS!G6/FS!G87 -> 30050.705 | G16: =FS!H6/FS!H87 -> 32270.369 | H16: =FS!I6/FS!I87 -> 54752.381 | I16: =FS!J6/FS!J87 -> 67419.707 | J16: =FS!K6/FS!K87 -> 69462.011 | K16: =FS!L6/FS!L87 -> 78223.659 | L16: =FS!M6/FS!M87 -> 87193.49
B17: Dividend payout | F17: =FS!G36/FS!G34 -> 0.41401274 | G17: =FS!H36/FS!H34 -> 0.38639876 | H17: =FS!I36/FS!I34 -> 0.23425299 | I17: =FS!J36/FS!J34 -> #REF! | J17: =FS!K36/FS!K34 -> 0.35 | K17: =FS!L36/FS!L34 -> 0.35 | L17: =FS!M36/FS!M34 -> 0.35
B20: Gross income per service centre | C20: =FS!C6/FS!C88 -> 412875.56 | D20: =FS!D6/FS!D88 -> 490025.25 | E20: =FS!E6/FS!E88 -> 525230.41 | F20: =FS!G6/FS!G88 -> 529499.7 | G20: =FS!H6/FS!H88 -> 570297.25 | H20: =FS!I6/FS!I88 -> 970197.04 | I20: =FS!J6/FS!J88 -> 1200602.1 | J20: =FS!K6/FS!K88 -> 1243125.3 | K20: =FS!L6/FS!L88 -> 1406892.8 | L20: =FS!M6/FS!M88 -> 1576021.9
B22: Net interest spread | F22: =F3-F4 -> 0.033048396 | G22: =G3-G4 -> 0.036391117 | H22: =H3-H4 -> 0.043709029 | I22: =I3-I4 -> 0.035965245 | J22: =J3-J4 -> 0.024227159 | K22: =K3-K4 -> 0.024927528 | L22: =L3-L4 -> 0.024746718

Sheet Quarterly
C1: For the quarter ended
C2: 45192 | D2: 45078 | E2: 44986 | F2: 44896 | G2: 44805 | H2: 44713 | I2: 44621 | J2: 44531
B3: Gross income | C3: 88294597 | D3: 83519041 | E3: 84149226 | F3: 84813856 | G3: 76055638 | H3: 64944217 | I3: 54573233 | J3: 43625180 | K3: =E3+D3+C3+C3 -> 344257461
B4: Interest income | C4: 73758370 | D4: 74872632 | E4: 75939012 | F4: 72136429 | G4: 62139977 | H4: 50269825 | I4: 37846848 | J4: 36591673 | K4: =E4+D4+C4+C4 -> 298328384
B5: Less : Interest expense | C5: 50326278 | D5: 56398189 | E5: 56963785 | F5: 50285038 | G5: 40038742 | H5: 28380265 | I5: 19023823 | J5: 17708621 | K5: =E5+D5+C5+C5 -> 214014530
B6: Net interest income | C6: 23432092 | D6: 18474443 | E6: 18975227 | F6: 21851391 | G6: 22101235 | H6: 21889560 | I6: 18823025 | J6: 18883052 | K6: =E6+D6+C6+C6 -> 84313854
B7: Fee and commission income | C7: 7657034 | D7: 7076778 | E7: 7300668 | F7: 7985635 | G7: 6447150 | H7: 6365740 | I7: 5393005 | J7: 4915199 | K7: =E7+D7+C7+C7 -> 29691514
B8: Less: Fee and commission expense | C8: 2038079 | D8: 1887996 | E8: 1898492 | F8: 1729591 | G8: 1411595 | H8: 1575925 | I8: 1305318 | J8: 1269724
B9: Net fee and commission income | C9: 5618955 | D9: 5188782 | E9: 5402176 | F9: 6256044 | G9: 5035555 | H9: 4789815 | I9: 4087687 | J9: 3645475
B10: Net gains/(losses) from trading | C10: 3381671 | D10: -6555889 | E10: -8975464 | F10: 1173354 | G10: 2022197 | H10: 8560357 | I10: 23541542 | J10: -101050
B11: Net gains/(losses) from derecognition of financial assets | C11: 1713760 | D11: 587244 | E11: 337266 | F11: 105790 | G11: 106832 | H11: 49119 | I11: 15143 | J11: 25076
B12: Net other operating income | C12: 1783762 | D12: 7538276 | E12: 9547744 | F12: 3412648 | G12: 5339482 | H12: -300824 | I12: -12223305 | J12: 2194282
B13: Total operating income | C13: 35930240 | D13: 25232856 | E13: 25286949 | F13: 32799227 | G13: 34605301 | H13: 34988027 | I13: 34244092 | J13: 24646835
B14: Less : Impairment charges and other losses | C14: 12571147 | D14: 6413788 | E14: 6797175 | F14: 19652653 | G14: 17052988 | H14: 29258063 | I14: 5960556 | J14: 7142508
B15: Net operating income | C15: 23359093 | D15: 18819068 | E15: 18489774 | F15: 13146574 | G15: 17552313 | H15: 5729964 | I15: 28283536 | J15: 17504327
B16: Less: Expenses | C16: 10691452 | D16: 10607104 | E16: 10677690 | F16: 10265566 | G16: 7985228 | H16: 9310867 | I16: 8720580 | J16: 8378026
B17: Personnel expenses | C17: 5512768 | D17: 5684029 | E17: 5612486 | F17: 5148402 | G17: 5055534 | H17: 4972094 | I17: 4612253 | J17: 4639350
B18: Depreciation and amortisation | C18: 995181 | D18: 1020578 | E18: 1063760 | F18: 968895 | G18: 905454 | H18: 906117 | I18: 817905 | J18: 798333
B19: Other operating expenses | C19: 4183503 | D19: 3902497 | E19: 4001444 | F19: 4148269 | G19: 2024240 | H19: 3432656 | I19: 3290422 | J19: 2940343
... B26: Profit for the period | C26: 6473131 | D26: 3931444 | E26: 4359030 | F26: 8939067 | G26: 6282655 | H26: -2596954 | I26: 11774704 | J26: 5272945
B27: Profit attributable to:
B28: Equity holders of the Bank | C28: 6233402 | D28: 3750123 | E28: 4216403 | F28: 8775188 | G28: 6095730 | H28: -2743585 | I28: 11684581 | J28: 5217687
B29: Non-controlling interest | C29: 239729 | D29: 181321 | E29: 142627 | F29: 163879 | G29: 186925 | H29: 146631 | I29: 90123 | J29: 55258
B30: Profit for the period | C30: 6473131 | D30: 3931444 | E30: 4359030 | F30: 8939067 | G30: 6282655 | H30: -2596954 | I30: 11774704 | J30: 5272945
B32: Earnings per share | C32: 4.75 | D32: 2.86 | E32: 3.21 | F32: 7.08 | G32: 4.92 | H32: -2.21 | I32: 9.42 | J32: 4.37

Sheet Sheet1
B3: For the year ended December 31,
B4: (LKR '000 except per share data) | C4: 2017 | D4: 2018 | E4: 2019
B5: INCOME STATEMENT
B6: Gross income | C6: - | D6: - | E6: 150741129
B7: Interest income | C7: - | D7: - | E7: 129287743
B8: Less: Interest expense | C8: - | D8: - | E8: 80931352
B9: Net interest income | C9: - | D9: - | E9: 48356391
B10: Fee and commission income | C10: - | D10: - | E10: 12874966
B11: Less: Fee and commission expense | C11: - | D11: - | E11: 2123128
B12: Net fee and commission income | C12: - | D12: - | E12: 10751838
B13: Net gains/(losses) from trading | C13: - | D13: - | E13: 1360833
B14: Net gains/(losses) from derecognition of financial assets | C14: - | D14: - | E14: 1135711
B15: Net other operating income | C15: - | D15: - | E15: 6081876
B16: Total operating income | C16: - | D16: - | E16: 67686649
B17: Less: Impairment charges and other losses | C17: - | D17: - | E17: 11331525
B18: Net operating income | C18: - | D18: - | E18: 56355126
B19: Less: Expenses
B20: Personnel expenses | C20: - | D20: - | E20: 14408914
B21: Depreciation and amortisation | C21: - | D21: - | E21: 2841264
B22: Other operating expenses | C22: - | D22: - | E22: 8875316
B23: Total operating expenses | C23: - | D23: - | E23: 26125494
B24: Operating profit before taxes on financial services | C24: - | D24: - | E24: 30229632
B25: Less: Taxes on financial services | C25: - | D25: - | E25: 7255728
B26: Operating profit after taxes on financial services | C26: - | D26: - | E26: 22973904
B27: Share of profit/(loss) of associate, net of tax | C27: - | D27: - | E27: 9992
B28: Profit before tax | C28: - | D28: - | E28: 22983896
B29: Less: Income tax expense/(reversal) | C29: - | D29: - | E29: 5563500
B30: Profit for the year | C30: - | D30: - | E30: 17420396
B31: Profit attributable to: Equity holders of the Bank | C31: - | D31: - | E31: 17263259
... B36: Diviend per share | C36: - | D36: - | E36: 5
B38: OCI
B39: Transfer of FV losses reclassification of debt from FVTOCI to AC | C39: - | D39: - | E39: -
B41: IS check | C41: =IF(C18-C23-C25+C27-C29-C30+C31+C32-C33=0,"OK","FLAG") -> #VALUE! | D41: =IF(D18-D23-D25+D27-D29-D30+D31+D32-D33=0,"OK","FLAG") -> #VALUE! | E41: =IF(E18-E23-E25+E27-E29-E30+E31+E32-E33=0,"OK","FLAG") -> FLAG
B43: BALANCE SHEET
B44: Assets
B45: Cash and cash equivalents | C45: - | D45: - | E45: 53681118
B46: Balances with Central Banks | C46: - | D46: - | E46: 46101232
B47: Placements with banks | C47: - | D47: - | E47: 24903809
B48: Securities purchased under resale agreements | C48: - | D48: - | E48: 13147534
B49: Derivative financial assets | C49: - | D49: - | E49: 1830927
B50: Financial assets recognised through profit or loss – measured at fair value | C50: - | D50: - | E50: 21468033
B51: Financial assets at amortised cost – loans and advances to banks | C51: - | D51: - | E51: 884646
B52: Financial assets at amortised cost – loans and advances to other customers | C52: - | D52: - | E52: 893919311
B53: Financial assets at amortised cost – debt and other financial instruments | C53: - | D53: - | E53: 107059021
B54: Financial assets measured at fair value through other comprehensive income | C54: - | D54: - | E54: 197825017
B55: Investments in subsidiaries | C55: - | D55: - | E55: 5011284
B56: Investment in associate | C56: - | D56: - | E56: 56821
... B62: Total assets | C62: - | D62: - | E62: 1408941366
B63: Liabilities
B64: Due to banks | C64: - | D64: - | E64: 53807425
B65: Derivative financial liabilities | C65: - | D65: - | E65: 1495317
B66: Securities sold under repurchase agreements | C66: - | D66: - | E66: 51117342
B67: Financial liabilities at amortised cost – due to depositors | C67: - | D67: - | E67: 1068982587
B68: Financial liabilities at amortised cost – other borrowings | C68: - | D68: - | E68: 23248893
B69: Current tax liabilities | C69: - | D69: - | E69: 5197188
B70: Deferred tax liabilities | C70: - | D70: - | E70: 416458
B71: Other liabilities | C71: - | D71: - | E71: 30775884
B72: Due to subsidiaries | C72: - | D72: - | E72: 54292
B73: Subordinated liabilities | C73: - | D73: - | E73: 37886789
B74: Total liabilities | C74: - | D74: - | E74: 1272927883
B75: Equity
B76: Stated capital | C76: - | D76: - | E76: 40916958
B77: Statutory reserves | C77: - | D77: - | E77: 8387701
B78: Retained earnings | C78: - | D78: - | E78: 5182185
B79: Other reserves | C79: - | D79: - | E79: 79937405
B80: Total equity attributable to equity holders of the Bank | C80: - | D80: - | E80: 134424249
B81: Non-controlling interest | C81: - | D81: - | E81: 1589234
B82: Total equity | C82: - | D82: - | E82: 136013483
B83: Total liabilities and equity | C83: - | D83: - | E83: 1408941366
B84: Contingent liabilities and commitments | C84: - | D84: - | E84: 580961807
B85: Net assets value per ordinary share (Rs.) | C85: - | D85: - | E85: 130.83
B86: Memorandum information
B87: Number of employees | C87: - | D87: - | E87: 5062
B88: Number of customer service centres | C88: - | D88: - | E88: 287
B90: BS check | C90: =SUM(C45:C61)-SUM(C64:C73)-SUM(C76:C79)-C81 -> #VALUE! | D90: =SUM(D45:D61)-SUM(D64:D73)-SUM(D76:D79)-D81 -> #VALUE! | E90: =SUM(E45:E61)-SUM(E64:E73)-SUM(E76:E79)-E81 -> 4982239
B92: Cash / total assets | C92: - | D92: - | E92: 1408941366
B94: CASH FLOW STATEMENT
B96: Cash flows from operating activities Profit before income tax | C96: - | D96: - | E96: 22339105
B97: Adjustments for:
B98: Non-cash items included in profit before tax | C98: - | D98: - | E98: 13702213
B99: Change in operating assets | C99: - | D99: - | E99: -74749286
B100: Change in operating liabilities | C100: - | D100: - | E100: 65515273
B101: (Gains)/losses on sale of property, plant and equipment | C101: - | D101: - | E101: -7958
B102: Share of (profit)/loss of associate, net of tax | C102: - | D102: - | E102: -
B103: Dividends received from investments in associate and subsidiaries | C103: - | D103: - | E103: 85397
B104: Interest expense on subordinated liabilities | C104: - | D104: - | E104: 3848979
B105: Net unrealised gains/(losses) arising from translating the Financial Statements of foreign operations | C105: - | D105: - | E105: -399787
B106: Benefits paid on defined benefit plans | C106: - | D106: - | E106: -194728
B107: Income tax paid | C107: - | D107: - | E107: -8087930
B108: Surcharge tax paid | C108: - | D108: - | E108: -
B109: Net cash from/(used in) operating activities | C109: - | D109: - | E109: 21865986
B110: Cash flows from investing activities
B111: Purchase of property, plant and equipment | C111: - | D111: - | E111: -1307244
B112: Proceeds from sale of property, plant and equipment | C112: - | D112: - | E112: 11025
B113: Purchase of financial investments | C113: - | D113: - | E113: -95031
B114: Proceeds from sale and maturity of financial investments | C114: - | D114: - | E114: 3428080
B115: Purchase of intangible assets | C115: - | D115: - | E115: -387432
B116: Dividends received from investments in associate and subsidiaries | C116: - | D116: - | E116: 85397
B117: Other items | C117: - | D117: - | E117: 21503
B118: Net cash from/(used in) investing activities | C118: - | D118: - | E118: 1001641
...
