Workbook

Sheet FS (2)
B3: For the year ended December 31,
B4: (LKR '000 except per share data) | C4: 2017 | D4: 2018 | E4: 2019 | F4: 2020 | G4: 2021 | H4: 2022 | I4: 2023F | J4: 2024F | K4: 2025F | L4: 2026F
B5: INCOME STATEMENT
B6: Gross income | C6: 115605156 | D6: 139657195 | E6: 150741129 | F6: 151966413 | G6: 163675312 | H6: 280386944 | I6: =I7+I10+I13+I14+I15 -> 0 | J6: =J7+J10+J13+J14+J15 -> 0 | K6: =K7+K10+K13+K14+K15 -> 0 | L6: =L7+L10+L13+L14+L15 -> 0
B7: Interest income | C7: 104049102 | D7: 118551239 | E7: 129287743 | F7: 124087713 | G7: 132818178 | H7: 222393079
B8: Less: Interest expense | C8: 64481804 | D8: 72933030 | E8: 80931352 | F8: 73218911 | G8: 66401846 | H8: 137727868
B9: Net interest income | C9: 39567298 | D9: 45618209 | E9: 48356391 | F9: 50868802 | G9: 66416332 | H9: 84665211 | I9: =I7-I8 -> 0 | J9: =J7-J8 -> 0 | K9: =K7-K8 -> 0 | L9: =L7-L8 -> 0
B10: Fee and commission income | C10: 10510800 | D10: 12494090 | E10: 12874966 | F10: 11839689 | G10: 15917337 | H10: 26191530
B11: Less: Fee and commission expense | C11: 1586334 | D11: 1859698 | E11: 2123128 | F11: 2018014 | G11: 3675143 | H11: 6022429
B12: Net fee and commission income | C12: 8924466 | D12: 10634392 | E12: 10751838 | F12: 9821675 | G12: 12242194 | H12: 20169101 | I12: =I10-I11 -> 0 | J12: =J10-J11 -> 0 | K12: =K10-K11 -> 0 | L12: =L10-L11 -> 0
B13: Net gains/(losses) from trading | C13: 233956 | D13: -3033236 | E13: 1360833 | F13: 1878060 | G13: 1936007 | H13: 35297450
B14: Net gains/(losses) from derecognition of financial assets | C14: 91272 | D14: 272004 | E14: 1135711 | F14: 6390197 | G14: 3001574 | H14: 276884
B15: Net other operating income | C15: 720026 | D15: 11373098 | E15: 6081876 | F15: 7770754 | G15: 10002216 | H15: -3771999
B16: Total operating income | C16: 49537018 | D16: 64864467 | E16: 67686649 | F16: 76729488 | G16: 93598323 | H16: 136636647 | I16: =I9+I12+I13+I14+I15 -> 0 | J16: =J9+J12+J13+J14+J15 -> 0 | K16: =K9+K12+K13+K14+K15 -> 0 | L16: =L9+L12+L13+L14+L15 -> 0
B17: Less: Impairment charges and other losses | C17: 989315 | D17: 8833362 | E17: 11331523 | F17: 21419532 | G17: 25139926 | H17: 71924260
B18: Net operating income | C18: 48547703 | D18: 56031105 | E18: 56355126 | F18: 55309956 | G18: 68458397 | H18: 64712387 | I18: =I16-I17 -> 0 | J18: =J16-J17 -> 0 | K18: =K16-K17 -> 0 | L18: =L16-L17 -> 0
B19: Less: Expenses
B20: Personnel expenses | C20: 11338517 | D20: 13289668 | E20: 14408914 | F20: 14992748 | G20: 16799212 | H20: 19788283
B21: Depreciation and amortisation | C21: 1416927 | D21: 1603118 | E21: 2841264 | F21: 3102695 | G21: 3220066 | H21: 3598371
B22: Other operating expenses | C22: 7618993 | D22: 8993958 | E22: 8875316 | F22: 8167170 | G22: 9638461 | H22: 12895587
B23: Total operating expenses | C23: 20374437 | D23: 23886744 | E23: 26125494 | F23: 26262613 | G23: 29657739 | H23: 36282241 | I23: =I20+I21+I22 -> 0 | J23: =J20+J21+J22 -> 0 | K23: =K20+K21+K22 -> 0 | L23: =L20+L21+L22 -> 0
B24: Operating profit before taxes on financial services | C24: 28173266 | D24: 32144361 | E24: 30229632 | F24: 29047343 | G24: 38800658 | H24: 28430146 | I24: =I18-I23 -> 0
B25: Less: Taxes on financial services | C25: 4896620 | D25: 6051861 | E25: 7255728 | F25: 4531381 | G25: 5845230 | H25: 3921381
B26: Operating profit after taxes on financial services | C26: 23276646 | D26: 26092500 | E26: 22973904 | F26: 24515962 | G26: 32955428 | H26: 24508765 | I26: =I24-I25 -> 0 | J26: =J24-J25 -> 0 | K26: =K24-K25 -> 0 | L26: =L24-L25 -> 0
B27: Share of profit/(loss) of associate, net of tax | C27: 3678 | D27: 6048 | E27: 9992 | F27: 3898 | G27: 1896 | H27: -3727
B28: Profit before tax | C28: 23280324 | D28: 26098548 | E28: 22983896 | F28: 24519860 | G28: 32957324 | H28: 24505038 | I28: =I26+I27 -> 0 | J28: =J26+J27 -> 0 | K28: =K26+K27 -> 0 | L28: =L26+L27 -> 0
B29: Less: Income tax expense/(reversal) | C29: 6653817 | D29: 8235717 | E29: 5563500 | F29: 7433063 | G29: 8667036 | H29: 105566
B30: Profit for the year | C30: 16626507 | D30: 17862831 | E30: 17420396 | F30: 17086797 | G30: 24290288 | H30: 24399472 | I30: =I28-I29 -> 0 | J30: =J28-J29 -> 0 | K30: =K28-K29 -> 0 | L30: =L28-L29 -> 0
B31: Profit attributable to: Equity holders of the Bank | C31: 16605963 | D31: 17734706 | E31: 17263259 | F31: 16939950 | G31: 24062469 | H31: 23811914
B32: Non-controlling interest | C32: 20544 | D32: 128125 | E32: 157137 | F32: 146847 | G32: 227819 | H32: 587558
B33: Profit for the year | C33: 16626507 | D33: 17862831 | E33: 17420396 | F33: 17086797 | G33: 24290288 | H33: 24399472 | I33: =I30 -> 0 | J33: =J30 -> 0 | K33: =K30 -> 0 | L33: =L30 -> 0
B34: Earnings per share Basic earnings per ordinary share (Rs.) | C34: 17.05 | D34: 17.55 | E34: 16.41 | F34: 15.7 | G34: 19.41 | H34: 19.21
B35: Diluted earnings per ordinary share (Rs.) | C35: 17.03 | D35: 17.55 | E35: 16.41 | F35: 15.7 | G35: 19.41 | H35: 19.21
B37: OCI
B38: Transfer of FV losses reclassification of debt from FVTOCI to AC | G38: 0 | H38: 26481256
B40: IS check | C40: =IF(C18-C23-C25+C27-C29-C30=0,"OK","FLAG") -> OK | D40: =IF(D18-D23-D25+D27-D29-D30=0,"OK","FLAG") -> OK | E40: =IF(E18-E23-E25+E27-E29-E30=0,"OK","FLAG") -> OK | F40: =IF(F18-F23-F25+F27-F29-F30=0,"OK","FLAG") -> OK | G40: =IF(G18-G23-G25+G27-G29-G30=0,"OK","FLAG") -> OK | H40: =IF(H18-H23-H25+H27-H29-H30=0,"OK","FLAG") -> OK
B42: BALANCE SHEET
B43: Assets
B44: Cash and cash equivalents | C44: 34673424 | D44: 44355962 | E44: 53681118 | F44: 51255030 | G44: 69335379 | H44: 151109490
B45: Balances with Central Banks | C45: 45546349 | D45: 55406535 | E45: 46101232 | F45: 115358732 | G45: 56777465 | H45: 78597120
B46: Placements with banks | C46: 17633269 | D46: 19898515 | E46: 24903809 | F46: 16421867 | G46: 12498709 | H46: 96082937
B47: Securities purchased under resale agreements | C47: 0 | D47: 9513512 | E47: 13147534 | F47: 0 | G47: 3000490 | H47: 1517308
B48: Derivative financial assets | C48: 2334536 | D48: 7909962 | E48: 1830927 | F48: 2636717 | G48: 3245120 | H48: 8345091
B49: Financial assets recognised through profit or loss – measured at fair value | C49: 4410913 | D49: 5520167 | E49: 21468033 | F49: 35189471 | G49: 23436123 | H49: 24873057
B50: Financial assets at amortised cost – loans and advances to banks | C50: 640512 | D50: 763074 | E50: 757787 | F50: 779705
B51: Financial assets at amortised cost – loans and advances to other customers | C51: 742444130 | D51: 867611976 | E51: 893919311 | F51: 909829172 | G51: 1029584075 | H51: 1155492527
B52: Financial assets at amortised cost – debt and other financial instruments | C52: 118078273 | D52: 89274413 | E52: 107059021 | F52: 302059529 | G52: 385390598 | H52: 761650234
B53: Financial assets measured at fair value through other comprehensive income | C53: 154913643 | D53: 176760611 | E53: 197825017 | F53: 278716794 | G53: 335953802 | H53: 118652257
B54: Investments in subsidiaries | C54: 0 | D54: 0 | E54: 0 | F54: 0 | G54: 0 | H54: 0
B55: Investment in associate | C55: 109844 | D55: 105320 | E55: 56821 | F55: 64155 | G55: 60428 | H55: 55302
B56: Property, plant and equipment and right-of-use assets | C56: 16317044 | D56: 17015236 | E56: 22524658 | F56: 25386630 | G56: 24744634 | H56: 27446607
B57: Investment properties | C57: 104516 | D57: 103064 | E57: 46350 | F57: 67116 | G57: 72400 | H57: 80350
B58: Intangible assets | C58: 1251226 | D58: 1433931 | E58: 1645714 | F58: 1800516 | G58: 2272639 | H58: 4113200
B59: Deferred tax assets | C59: 0 | D59: 188487 | E59: 530165 | F59: 2735566 | G59: 10036105 | H59: 30727213
B60: Other assets | C60: 17362977 | D60: 24051472 | E60: 23443869 | F60: 20195153 | G60: 27083177 | H60: 40811211
B61: Total assets | C61: 1155820656 | D61: 1319912237 | E61: 1408941366 | F61: 1762496153 | G61: 1983491144 | H61: 2499553904
B62: Liabilities
B63: Due to banks | C63: 60244892 | D63: 52362052 | E63: 53807425 | F63: 88248056 | G63: 73801195 | H63: 64971170
B64: Derivative financial liabilities | C64: 3678494 | D64: 8021783 | E64: 1495317 | F64: 1501262 | G64: 2092198 | H64: 2880667
B65: Securities sold under repurchase agreements | C65: 49532385 | D65: 48951394 | E65: 51117342 | F65: 91411522 | G65: 151424854 | H65: 97726435
B66: Financial liabilities at amortised cost – due to depositors | C66: 857269981 | D66: 994370875 | E66: 1068982587 | F66: 1286616399 | G66: 1472640456 | H66: 1977743661
B67: Financial liabilities at amortised cost – other borrowings | C67: 23786094 | D67: 25361912 | E67: 23248893 | F67: 54555933 | G67: 32587051 | H67: 16150356
B68: Current tax liabilities | C68: 4202850 | D68: 6735997 | E68: 5197188 | F68: 6991005 | G68: 9486772 | H68: 24916074
B69: Deferred tax liabilities | C69: 3565215 | D69: 971424 | E69: 416458 | F69: 403846 | G69: 349106 | H69: 437123
B70: Other liabilities | C70: 19508115 | D70: 24547513 | E70: 30775884 | F70: 33572283 | G70: 33253518 | H70: 40354877
B71: Due to subsidiaries | C71: 0 | D71: 0 | E71: 0 | F71: 0 | G71: 0 | H71: 0
B72: Subordinated liabilities | C72: 25165924 | D72: 37992457 | E72: 37886789 | F72: 38247138 | G72: 38303466 | H72: 61400967
B73: Total liabilities | C73: 1046953950 | D73: 1199315407 | E73: 1272927883 | F73: 1601547444 | G73: 1813938616 | H73: 2286581330
B74: Equity
B75: Stated capital | C75: 37143541 | D75: 39147882 | E75: 40916958 | F75: 52187747 | G75: 54566957 | H75: 58149621
B76: Statutory reserves | C76: 6492552 | D76: 7444178 | E76: 8387701 | F76: 9285233 | G76: 10590338 | H76: 12079670
B77: Retained earnings | C77: 5086609 | D77: 4949955 | E77: 5182185 | F77: 8124261 | G77: 9890762 | H77: 6790304
B78: Other reserves | C78: 59272098 | D78: 67855834 | E78: 79937405 | F78: 89595571 | G78: 92426660 | H78: 131845571
B79: Total equity attributable to equity holders of the Bank | C79: 107994800 | D79: 119397849 | E79: 134424249 | F79: 159192812 | G79: 167474717 | H79: 208865166
B80: Non-controlling interest | C80: 871906 | D80: 1198981 | E80: 1589234 | F80: 1755897 | G80: 2077811 | H80: 4107408
B81: Total equity | C81: 108866706 | D81: 120596830 | E81: 136013483 | F81: 160948709 | G81: 169552528 | H81: 212972574
B82: Total liabilities and equity | C82: 1155820656 | D82: 1319912237 | E82: 1408941366 | F82: 1762496153 | G82: 1983491144 | H82: 2499553904
B83: Contingent liabilities and commitments | C83: 565277821 | D83: 658860264 | E83: 580961807 | F83: 730561685 | G83: 685379028 | H83: 555531537
B84: Net assets value per ordinary share (Rs.) | C84: 108.44 | D84: 118.13 | E84: 130.83 | F84: 136.42 | G84: 140.24 | H84: 168.47
B85: Memorandum information
B86: Number of employees | C86: 4982 | D86: 5027 | E86: 5062 | F86: 5057 | G86: 5072 | H86: 5121
B87: Number of customer service centres | C87: 280 | D87: 285 | E87: 287 | F87: 287 | G87: 287 | H87: 289
B89: BS check | C89: =SUM(C44:C60)-SUM(C63:C72)-SUM(C75:C78)-C80 -> 0 | D89: =SUM(D44:D60)-SUM(D63:D72)-SUM(D75:D78)-D80 -> 0 | E89: =SUM(E44:E60)-SUM(E63:E72)-SUM(E75:E78)-E80 -> 0 | F89: =SUM(F44:F60)-SUM(F63:F72)-SUM(F75:F78)-F80 -> 0 | G89: =SUM(G44:G60)-SUM(G63:G72)-SUM(G75:G78)-G80 -> 0 | H89: =SUM(H44:H60)-SUM(H63:H72)-SUM(H75:H78)-H80 -> 0
B91: CASH FLOW STATEMENT
B93: Cash flows from operating activities Profit before income tax | C93: 23280324 | D93: 26098548 | E93: 22983896 | F93: 24519860 | G93: 32957324 | H93: 24505038
B94: Adjustments for:
B95: Non-cash items included in profit before tax | C95: 1078540 | D95: 12380685 | E95: 14014272 | F95: 24764927 | G95: 30473593 | H95: 91299070
B96: Change in operating assets | C96: -125489870 | D96: -169379105 | E96: -84218375 | F96: -374761711 | G96: -230261220 | H96: -463345077
B97: Change in operating liabilities | C97: 100265879 | D97: 138876499 | E97: 69879669 | F97: 325708382 | G97: 208070200 | H97: 430778836
B98: (Gains)/losses on sale of property, plant and equipment | C98: 18774 | D98: -9311 | E98: -19731 | F98: -5820 | G98: -4054 | H98: -20118
B99: Share of (profit)/loss of associate, net of tax | C99: -3678 | D99: -6048 | E99: -9992 | F99: -3898 | G99: -1896 | H99: 3727
B100: Dividends received from investments in associate and subsidiaries | C100: 0 | D100: 0 | E100: 0 | F100: 0 | G100: 0 | H100: 0
B101: Interest expense on subordinated liabilities | C101: 2377694 | D101: 3105553 | E101: 3848979 | F101: 3756921 | G101: 3398554 | H101: 4843571
B102: Net unrealised gains/(losses) arising from translating the Financial Statements of foreign operations | C102: -503140 | D102: 3003952 | E102: -396201 | F102: 596723 | G102: 1278891 | H102: 18347815
B103: Benefits paid on defined benefit plans | C103: -184464 | D103: -382409 | E103: -198799 | F103: -673106 | G103: -1116195 | H103: -780828
B104: Income tax paid | C104: -3810701 | D104: -5971026 | E104: -8301839 | F104: -7748870 | G104: -8963620 | H104: -11143271
B105: Surcharge tax paid | C105: 0 | D105: 0 | E105: 0 | F105: 0 | G105: 0 | H105: -5216574
B106: Net cash from/(used in) operating activities | C106: -2970642 | D106: 7717338 | E106: 17581879 | F106: -3846592 | G106: 35831577 | H106: 89272189
B107: Cash flows from investing activities
B108: Purchase of property, plant and equipment | C108: -2163733 | D108: -2079875 | E108: -1372832 | F108: -1159712 | G108: -1034299 | H108: -3370339
...

Sheet Cover
B3: COMMERCIAL BANK OF CEYLON PLC
B4: COMB N
B5: COMB X

Sheet FS
V1: correct
V2: wrong
B3: For the year ended December 31, | V3: not in report
B4: (LKR '000 except per share data) | C4: 2017 | D4: 2018 | E4: 2019 | F4: 2020 | G4: 2021 | I4: 2022 | J4: 2023F | K4: 2024F | L4: 2025F | M4: 2026F | O4: Annualised | P4: 9M Sep23 | Q4: 1H2023 | R4: 1H2022
B5: INCOME STATEMENT
B6: Gross income | C6: 115605156 | D6: 139657195 | E6: 150741129 | F6: 151966413 | G6: 163675312 | I6: 280386944 | J6: =J7+J10+J13+J14+J15 -> 3.4870888e+08 | K6: =K7+K10+K13+K14+K15 -> 3.6286483e+08 | L6: =L7+L10+L13+L14+L15 -> 4.1272143e+08 | M6: =M7+M10+M13+M14+M15 -> 4.6464828e+08 | O6: =P6/9*12 -> 3.4128382e+08 | P6: 255962864 | Q6: 167668267 | R6: 119517450 | S6: =Q6*2 -> 335336534
B7: Interest income | C7: 104049102 | D7: 118551239 | E7: 129287743 | F7: 124087713 | G7: 132818178 | I7: 222393079 | J7: =Drivers!I7 -> 3.0585734e+08 | K7: =Drivers!J7 -> 2.9513936e+08 | L7: =Drivers!K7 -> 3.3784948e+08 | M7: =Drivers!L7 -> 3.8175485e+08 | O7: =P7/9*12 -> 2.9942669e+08 | P7: 224570014 | Q7: 150811644 | R7: 88116673 | S7: =Q7*2 -> 301623288
B8: Less: Interest expense | C8: 64481804 | D8: 72933030 | E8: 80931352 | F8: 73218911 | G8: 66401846 | I8: 137727868 | J8: =Drivers!I58 -> 2.2269493e+08 | K8: =Drivers!J58 -> 2.3202049e+08 | L8: =Drivers!K58 -> 2.6615841e+08 | M8: =Drivers!L58 -> 3.0080788e+08 | O8: =P8/9*12 -> 2.18251e+08 | P8: 163688252 | Q8: 113361974 | R8: 47404088 | S8: =Q8*2 -> 226723948
B9: Net interest income | C9: 39567298 | D9: 45618209 | E9: 48356391 | F9: 50868802 | G9: 66416332 | I9: 84665211 | J9: =J7-J8 -> 83162406 | K9: =K7-K8 -> 63118873 | L9: =L7-L8 -> 71691068 | M9: =M7-M8 -> 80946963 | O9: =P9/9*12 -> 81175683 | P9: 60881762 | Q9: 37449670 | R9: 40712585 | S9: =Q9*2 -> 74899340
B10: Fee and commission income | C10: 10510800 | D10: 12494090 | E10: 12874966 | F10: 11839689 | G10: 15917337 | I10: 26191530 | J10: =Drivers!I78 -> 30373717 | K10: =Drivers!J78 -> 35658826 | L10: =Drivers!K78 -> 41280198 | M10: =Drivers!L78 -> 47701081 | O10: =P10/9*12 -> 29379307 | P10: 22034480 | Q10: 14377446 | R10: 11758745 | S10: =Q10*2 -> 28754892
B11: Less: Fee and commission expense | C11: 1586334 | D11: 1859698 | E11: 2123128 | F11: 2018014 | G11: 3675143 | I11: 6022429 | J11: =Drivers!I93 -> 7593429.2 | K11: =Drivers!J93 -> 8201529.9 | L11: =Drivers!K93 -> 9494445.4 | M11: =Drivers!L93 -> 10971249 | O11: =P11/9*12 -> 7766089.3 | P11: 5824567 | Q11: 3786488 | R11: 2881243 | S11: =Q11*2 -> 7572976
B12: Net fee and commission income | C12: 8924466 | D12: 10634392 | E12: 10751838 | F12: 9821675 | G12: 12242194 | I12: 20169101 | J12: =J10-J11 -> 22780287 | K12: =K10-K11 -> 27457296 | L12: =L10-L11 -> 31785752 | M12: =M10-M11 -> 36729832 | O12: =P12/9*12 -> 21613217 | P12: 16209913 | Q12: 10590958 | R12: 8877502 | S12: =Q12*2 -> 21181916
B13: Net gains/(losses) from trading | C13: 233956 | D13: -3033236 | E13: 1360833 | F13: 1878060 | G13: 1936007 | I13: 35297450 | J13: =Drivers!I106 -> -16199576 | K13: =Drivers!J106 -> 1955367.1 | L13: =Drivers!K106 -> 1974920.7 | M13: =Drivers!L106 -> 1994669.9 | O13: =P13/9*12 -> -16199576 | P13: -12149682 | Q13: -15531353 | R13: 32101899 | S13: =Q13*2 -> -31062706
B14: Net gains/(losses) from derecognition of financial assets | C14: 91272 | D14: 272004 | E14: 1135711 | F14: 6390197 | G14: 3001574 | I14: 276884 | J14: =P14/9*12 -> 3517693.3 | K14: =J14*1.05 -> 3693578 | L14: =K14*1.05 -> 3878256.9 | M14: =L14*1.05 -> 4072169.7 | O14: =P14/9*12 -> 3517693.3 | P14: 2638270 | Q14: 924510 | R14: 64262 | S14: =Q14*2 -> 1849020
B15: Net other operating income | C15: 720026 | D15: 11373098 | E15: 6081876 | F15: 7770754 | G15: 10002216 | I15: -3771999 | J15: =Drivers!I123 -> 25159709 | K15: =Drivers!J123 -> 26417695 | L15: =Drivers!K123 -> 27738580 | M15: =Drivers!L123 -> 29125509 | O15: =P15/9*12 -> 25159709 | P15: 18869782 | Q15: 17086020 | R15: -12524129 | S15: =Q15*2 -> 34172040
B16: Total operating income | C16: 49537018 | D16: 64864467 | E16: 67686649 | F16: 76729488 | G16: 93598323 | I16: 136636647 | J16: =J9+J12+J13+J14+J15 -> 1.1842052e+08 | K16: =K9+K12+K13+K14+K15 -> 1.2264281e+08 | L16: =L9+L12+L13+L14+L15 -> 1.3706858e+08 | M16: =M9+M12+M13+M14+M15 -> 1.5286914e+08 | O16: =P16/9*12 -> 1.1526673e+08 | P16: 86450045 | Q16: 50519805 | R16: 69232119 | S16: =Q16*2 -> 101039610
B17: Less: Impairment charges and other losses | C17: 989315 | D17: 8833362 | E17: 11331523 | F17: 21419532 | G17: 25139926 | I17: 71924260 | J17: =Drivers!I138 -> 35328926 | K17: =Drivers!J138 -> 30095011 | L17: =Drivers!K138 -> 34609262 | M17: =Drivers!L138 -> 39800652 | O17: =P17/9*12 -> 34376147 | P17: 25782110 | Q17: 13210963 | R17: 35218619 | S17: =Q17*2 -> 26421926
B18: Net operating income | C18: 48547703 | D18: 56031105 | E18: 56355126 | F18: 55309956 | G18: 68458397 | I18: 64712387 | J18: =J16-J17 -> 83091594 | K18: =K16-K17 -> 92547798 | L18: =L16-L17 -> 1.0245931e+08 | M18: =M16-M17 -> 1.1306849e+08 | O18: =P18/9*12 -> 80890580 | P18: 60667935 | Q18: 37308842 | R18: 34013500 | S18: =Q18*2 -> 74617684
B19: Less: Expenses | O19: =P19/9*12 -> 0 | S19: =Q19*2 -> 0
B20: Personnel expenses | C20: 11338517 | D20: 13289668 | E20: 14408914 | F20: 14992748 | G20: 16799212 | I20: 19788283 | J20: =Drivers!I155 -> 21767111 | K20: =Drivers!J155 -> 23943822 | L20: =Drivers!K155 -> 26338205 | M20: =Drivers!L155 -> 28972025 | O20: =P20/9*12 -> 22412377 | P20: 16809283 | Q20: 11296515 | R20: 9584347 | S20: =Q20*2 -> 22593030
B21: Depreciation and amortisation | C21: 1416927 | D21: 1603118 | E21: 2841264 | F21: 3102695 | G21: 3220066 | I21: 3598371 | J21: =Drivers!I172 -> 4116991 | K21: =Drivers!J172 -> 4240227.2 | L21: =Drivers!K172 -> 4381833.5 | M21: =Drivers!L172 -> 4529601.5 | O21: =P21/9*12 -> 4106025.3 | P21: 3079519 | Q21: 2084338 | R21: 1724022 | S21: =Q21*2 -> 4168676
B22: Other operating expenses | C22: 7618993 | D22: 8993958 | E22: 8875316 | F22: 8167170 | G22: 9638461 | I22: 12895587 | J22: =Drivers!I184 -> 16764263 | K22: =Drivers!J184 -> 20117116 | L22: =Drivers!K184 -> 24140539 | M22: =Drivers!L184 -> 28968647 | O22: =P22/9*12 -> 16116592 | P22: 12087444 | Q22: 7903941 | R22: 6723078 | S22: =Q22*2 -> 15807882
B23: Total operating expenses | C23: 20374437 | D23: 23886744 | E23: 26125494 | F23: 26262613 | G23: 29657739 | I23: 36282241 | J23: =J20+J21+J22 -> 42648365 | K23: =K20+K21+K22 -> 48301165 | L23: =L20+L21+L22 -> 54860577 | M23: =M20+M21+M22 -> 62470273 | O23: =P23/9*12 -> 42634995 | P23: 31976246 | Q23: 21284794 | R23: 18031447 | S23: =Q23*2 -> 42569588
B24: Operating profit before taxes on financial services | C24: 28173266 | D24: 32144361 | E24: 30229632 | F24: 29047343 | G24: 38800658 | I24: 28430146 | J24: =J18-J23 -> 40443229 | K24: =K18-K23 -> 44246633 | L24: =L18-L23 -> 47598738 | M24: =M18-M23 -> 50598219 | O24: =P24/9*12 -> 38255585 | P24: 28691689 | Q24: 16024048 | R24: 15982053 | S24: =Q24*2 -> 32048096
B25: Less: Taxes on financial services | C25: 4896620 | D25: 6051861 | E25: 7255728 | F25: 4531381 | G25: 5845230 | I25: 3921381 | J25: =Drivers!I196 -> 4893717.4 | K25: =Drivers!J196 -> 5902787.2 | L25: =Drivers!K196 -> 6756989.5 | M25: =Drivers!L196 -> 7635097 | O25: =P25/9*12 -> 4886169.3 | P25: 3664627 | Q25: 1933968 | R25: 2602781 | S25: =Q25*2 -> 3867936
B26: Operating profit after taxes on financial services | C26: 23276646 | D26: 26092500 | E26: 22973904 | F26: 24515962 | G26: 32955428 | I26: 24508765 | J26: =J24-J25 -> 35549511 | K26: =K24-K25 -> 38343846 | L26: =L24-L25 -> 40841748 | M26: =M24-M25 -> 42963122 | O26: =P26/9*12 -> 33369416 | P26: 25027062 | Q26: 14090080 | R26: 13379272 | S26: =Q26*2 -> 28180160
B27: Share of profit/(loss) of associate, net of tax | C27: 3678 | D27: 6048 | E27: 9992 | F27: 3898 | G27: 1896 | I27: -3727 | J27: =P27/9*12 -> 5197.3333 | K27: =J27*1.01 -> 5249.3067 | L27: =K27*1.01 -> 5301.7997 | M27: =L27*1.01 -> 5354.8177 | O27: =P27/9*12 -> 5197.3333 | P27: 3898 | Q27: 2352 | R27: -3476 | S27: =Q27*2 -> 4704
B28: Profit before tax | C28: 23280324 | D28: 26098548 | E28: 22983896 | F28: 24519860 | G28: 32957324 | I28: 24505038 | J28: =J26+J27 -> 35554709 | K28: =K26+K27 -> 38349095 | L28: =L26+L27 -> 40847050 | M28: =M26+M27 -> 42968476 | O28: =P28/9*12 -> 33374613 | P28: 25030960 | Q28: 14092432 | R28: 13375796 | S28: =Q28*2 -> 28184864
B29: Less: Income tax expense/(reversal) | C29: 6653817 | D29: 8235717 | E29: 5563500 | F29: 7433063 | G29: 8667036 | I29: 105566 | J29: =Drivers!I206 -> 14932978 | K29: =Drivers!J206 -> 11504728 | L29: =Drivers!K206 -> 12254115 | M29: =Drivers!L206 -> 12890543 | O29: =P29/9*12 -> 13689807 | P29: 10267355 | Q29: 5801958 | R29: 4198046 | S29: =Q29*2 -> 11603916
B30: Profit for the year | C30: 16626507 | D30: 17862831 | E30: 17420396 | F30: 17086797 | G30: 24290288 | I30: 24399472 | J30: =J28-J29 -> 20621731 | K30: =K28-K29 -> 26844366 | L30: =L28-L29 -> 28592935 | M30: =M28-M29 -> 30077933 | O30: =P30/9*12 -> 19684807 | P30: 14763605 | Q30: 8290474 | R30: 9177750 | S30: =Q30*2 -> 16580948
B31: Profit attributable to: Equity holders of the Bank | C31: 16605963 | D31: 17734706 | E31: 17263259 | F31: 16939950 | G31: 24062469 | I31: 23811914 | J31: =J30*0.96 -> 19796862 | K31: =K30*0.96 -> 25770592 | L31: =L30*0.96 -> 27449218 | M31: =M30*0.96 -> 28874816 | O31: =P31/9*12 -> 18933237 | P31: 14199928 | Q31: 7966526 | R31: 8940996
B32: Non-controlling interest | C32: 20544 | D32: 128125 | E32: 157137 | F32: 146847 | G32: 227819 | I32: 587558 | J32: =J30*0.04 -> 824869.24 | K32: =K30*0.04 -> 1073774.7 | L32: =L30*0.04 -> 1143717.4 | M32: =M30*0.04 -> 1203117.3 | O32: =P32/9*12 -> 751569.33 | P32: 563677 | Q32: 323948 | R32: 236754
B33: Profit for the year | C33: 16626507 | D33: 17862831 | E33: 17420396 | F33: 17086797 | G33: 24290288 | I33: 24399472 | J33: =J30 -> 20621731 | K33: =K30 -> 26844366 | L33: =L30 -> 28592935 | M33: =M30 -> 30077933 | O33: =P33/9*12 -> 19684807 | P33: =P30 -> 14763605 | Q33: =Q30 -> 8290474 | R33: =R30 -> 9177750
B34: Earnings per share Basic earnings per ordinary share (Rs.) | C34: 17.05 | D34: 17.55 | E34: 16.41 | F34: 15.7 | G34: 19.41 | I34: 19.21 | J34: =J31*1000/Drivers!I586 -> 15.064716 | K34: =K31*1000/Drivers!J586 -> 19.610515 | L34: =L31*1000/Drivers!K586 -> 20.88789 | M34: =M31*1000/Drivers!L586 -> 21.97272 | P34: 10.81 | Q34: 6.07 | R34: 7.21
B35: Diluted earnings per ordinary share (Rs.) | C35: 17.03 | D35: 17.55 | E35: 16.41 | F35: 15.7 | G35: 19.41 | I35: 19.21 | P35: 10.81 | Q35: 6.07 | R35: 7.21
B36: Diviend per share | D36: 6.5 | E36: 6.5 | F36: 6.5 | G36: 7.5 | I36: 4.5 | J36: ='charts 1'!N23 -> 4.5 | K36: =-Drivers!J619*1000/Drivers!J586 -> 6.8636802 | L36: =-Drivers!K619*1000/Drivers!K586 -> 7.3107615 | M36: =-Drivers!L619*1000/Drivers!L586 -> 7.6904522
B38: OCI
B39: Transfer of FV losses reclassification of debt from FVTOCI to AC | G39: 0 | I39: 26481256
B41: IS check | C41: =IF(C18-C23-C25+C27-C29-C30+C31+C32-C33=0,"OK","FLAG") -> OK | D41: =IF(D18-D23-D25+D27-D29-D30+D31+D32-D33=0,"OK","FLAG") -> OK | E41: =IF(E18-E23-E25+E27-E29-E30+E31+E32-E33=0,"OK","FLAG") -> OK | F41: =IF(F18-F23-F25+F27-F29-F30+F31+F32-F33=0,"OK","FLAG") -> OK | G41: =IF(G18-G23-G25+G27-G29-G30+G31+G32-G33=0,"OK","FLAG") -> OK | I41: =IF(I18-I23-I25+I27-I29-I30+I31+I32-I33=0,"OK","FLAG") -> OK | J41: =J18-J23-J25+J27-J29-J30+J31+J32-J33 -> 0 | K41: =K18-K23-K25+K27-K29-K30+K31+K32-K33 -> 0 | L41: =L18-L23-L25+L27-L29-L30+L31+L32-L33 -> 0 | M41: =M18-M23-M25+M27-M29-M30+M31+M32-M33 -> 0 | Q41: =IF(Q18-Q23-Q25+Q27-Q29-Q30=0,"OK","FLAG") -> OK | R41: =IF(R18-R23-R25+R27-R29-R30=0,"OK","FLAG") -> OK
B43: BALANCE SHEET
B44: Assets
B45: Cash and cash equivalents | C45: 34673424 | D45: 44355962 | E45: 53681118 | F45: 51255030 | G45: 69335379 | I45: 151109490 | J45: =J62-SUM(J46:J61) -> 1.0591632e+08 | K45: =K62-SUM(K46:K61) -> 1.0969008e+08 | L45: =L62-SUM(L46:L61) -> 1.5908379e+08 | M45: =M62-SUM(M46:M61) -> 1.6813355e+08 | P45: 114518140 | Q45: 112544293 | R45: 151109490
B46: Balances with Central Banks | C46: 45546349 | D46: 55406535 | E46: 46101232 | F46: 115358732 | G46: 56777465 | I46: 78597120 | J46: =Drivers!I234 -> 52339149 | K46: =Drivers!J234 -> 94799284 | L46: =Drivers!K234 -> 1.0901918e+08 | M46: =Drivers!L234 -> 1.2537205e+08 | P46: 37516912 | Q46: 61871953 | R46: 78597120
B47: Placements with banks | C47: 17633269 | D47: 19898515 | E47: 24903809 | F47: 16421867 | G47: 12498709 | I47: 96082937 | J47: =Drivers!I252 -> 76866350 | K47: =Drivers!J252 -> 80709667 | L47: =Drivers!K252 -> 84745150 | M47: =Drivers!L252 -> 88982408 | P47: 66538167 | Q47: 53920816 | R47: 96082937
B48: Securities purchased under resale agreements | C48: 0 | D48: 9513512 | E48: 13147534 | F48: 0 | G48: 3000490 | I48: 1517308 | J48: =Drivers!I264 -> 606923.2 | K48: =Drivers!J264 -> 637269.36 | L48: =Drivers!K264 -> 669132.83 | M48: =Drivers!L264 -> 702589.47 | P48: 549770 | Q48: 3378561 | R48: 1517308
B49: Derivative financial assets | C49: 2334536 | D49: 7909962 | E49: 1830927 | F49: 2636717 | G49: 3245120 | I49: 8345091 | J49: =Drivers!I266 -> 5841563.7 | K49: =Drivers!J266 -> 6133641.9 | L49: =Drivers!K266 -> 6440324 | M49: =Drivers!L266 -> 6762340.2 | P49: 6091290 | Q49: 7032972 | R49: 8345091
B50: Financial assets recognised through profit or loss – measured at fair value | C50: 4410913 | D50: 5520167 | E50: 21468033 | F50: 35189471 | G50: 23436123 | I50: 24873057 | J50: =Drivers!I271 -> 98932873 | K50: =Drivers!J271 -> 1.5596006e+08 | L50: =Drivers!K271 -> 1.7155607e+08 | M50: =Drivers!L271 -> 1.8871168e+08 | P50: 98042540 | Q50: 50791983 | R50: 24873057
B51: Financial assets at amortised cost – loans and advances to banks | C51: 640512 | D51: 763074 | E51: 757787 | F51: 779705 | G51: 0 | I51: 0
B52: Financial assets at amortised cost – loans and advances to other customers | C52: 742444130 | D52: 867611976 | E52: 893919311 | F52: 909829172 | G52: 1029584075 | I52: 1155492527 | J52: =Drivers!I289 -> 1.2149487e+09 | K52: =Drivers!J289 -> 1.426353e+09 | L52: =Drivers!K289 -> 1.6512079e+09 | M52: =Drivers!L289 -> 1.9080432e+09 | P52: 1148276787 | Q52: 1096826774 | R52: 1155492527
B53: Financial assets at amortised cost – debt and other financial instruments | C53: 118078273 | D53: 89274413 | E53: 107059021 | F53: 302059529 | G53: 385390598 | I53: 761650234 | J53: =Drivers!I341 -> 7.0929112e+08 | K53: =Drivers!J341 -> 6.6835832e+08 | L53: =Drivers!K341 -> 7.3775418e+08 | M53: =Drivers!L341 -> 7.9117557e+08 | P53: 706747778 | Q53: 740197253 | R53: 761650234
B54: Financial assets measured at fair value through other comprehensive income | C54: 154913643 | D54: 176760611 | E54: 197825017 | F54: 278716794 | G54: 335953802 | I54: 118652257 | J54: =Drivers!I384 -> 296954728 | K54: =Drivers!J384 -> 3.266502e+08 | L54: =Drivers!K384 -> 3.5931522e+08 | M54: =Drivers!L384 -> 3.9524674e+08 | P54: 246477855 | Q54: 230826265 | R54: 118652257
B55: Investments in subsidiaries | C55: 0 | D55: 0 | E55: 0 | F55: 0 | G55: 0 | I55: 0 | J55: =I55 -> 0 | K55: =J55 -> 0 | L55: =K55 -> 0 | M55: =L55 -> 0 | P55: 0
B56: Investment in associate | C56: 109844 | D56: 105320 | E56: 56821 | F56: 64155 | G56: 60428 | I56: 55302 | J56: =Drivers!I396 -> 55302 | K56: =Drivers!J396 -> 55302 | L56: =Drivers!K396 -> 55302 | M56: =Drivers!L396 -> 55302 | P56: 59475 | Q56: 57856 | R56: 55302
B57: Property, plant and equipment and right-of-use assets | C57: 16317044 | D57: 17015236 | E57: 22524658 | F57: 25386630 | G57: 24744634 | I57: 27446607 | J57: =Drivers!I401 -> 28268182 | K57: =Drivers!J401 -> 29212223 | L57: =Drivers!K401 -> 30197343 | M57: =Drivers!L401 -> 31229666 | P57: 26538514 | Q57: 26649043 | R57: 27446607
B58: Investment properties | C58: 104516 | D58: 103064 | E58: 46350 | F58: 67116 | G58: 72400 | I58: 80350 | J58: =Drivers!I430 -> 642800 | K58: =Drivers!J430 -> 707080 | L58: =Drivers!K430 -> 777788 | M58: =Drivers!L430 -> 855566.8 | P58: 545850 | Q58: 424550 | R58: 80350
B59: Intangible assets | C59: 1251226 | D59: 1433931 | E59: 1645714 | F59: 1800516 | G59: 2272639 | I59: 4113200 | J59: =Drivers!I435 -> 4090774.5 | K59: =Drivers!J435 -> 4409448.7 | L59: =Drivers!K435 -> 7206711.9 | M59: =Drivers!L435 -> 7793697.9 | P59: 4061409 | Q59: 4042878 | R59: 4113200
B60: Deferred tax assets | C60: 0 | D60: 188487 | E60: 530165 | F60: 2735566 | G60: 10036105 | I60: 30727213 | J60: =Drivers!I462 -> 32878118 | K60: =Drivers!J462 -> 16439059 | L60: =Drivers!K462 -> 17261012 | M60: =Drivers!L462 -> 18124062 | P60: 32664942 | Q60: 30251431 | R60: 30727213
B61: Other assets | C61: 17362977 | D61: 24051472 | E61: 23443869 | F61: 20195153 | G61: 27083177 | I61: 40811211 | J61: =Drivers!I468 -> 34689529 | K61: =Drivers!J468 -> 32955053 | L61: =Drivers!K468 -> 33614154 | M61: =Drivers!L468 -> 34286437 | P61: 36882221 | Q61: 43351569 | R61: 40811211
B62: Total assets | C62: 1155820656 | D62: 1319912237 | E62: 1408941366 | F62: 1762496153 | G62: 1983491144 | I62: 2499553904 | J62: =J83 -> 2.6623224e+09 | K62: =K83 -> 2.9530697e+09 | L62: =L83 -> 3.3689033e+09 | M62: =M83 -> 3.7654749e+09 | P62: 2525511650 | Q62: 2462168197 | R62: 2499553904
B63: Liabilities
B64: Due to banks | C64: 60244892 | D64: 52362052 | E64: 53807425 | F64: 88248056 | G64: 73801195 | I64: 64971170 | J64: =Drivers!I475 -> 39254362 | K64: =Drivers!J475 -> 60190021 | L64: =Drivers!K475 -> 69218525 | M64: =Drivers!L475 -> 79601303 | P64: 48268948 | Q64: 50020369 | R64: 64971170
B65: Derivative financial liabilities | C65: 3678494 | D65: 8021783 | E65: 1495317 | F65: 1501262 | G65: 2092198 | I65: 2880667 | J65: =Drivers!I488 -> 1440333.5 | K65: =Drivers!J488 -> 1584366.9 | L65: =Drivers!K488 -> 1742803.5 | M65: =Drivers!L488 -> 1917083.9 | P65: 1560980 | Q65: 5309026 | R65: 2880667
B66: Securities sold under repurchase agreements | C66: 49532385 | D66: 48951394 | E66: 51117342 | F66: 91411522 | G66: 151424854 | I66: 97726435 | J66: =Drivers!I494 -> 1.0794949e+08 | K66: =Drivers!J494 -> 1.1812292e+08 | L66: =Drivers!K494 -> 1.3411089e+08 | M66: =Drivers!L494 -> 1.4925244e+08 | P66: 117895187 | Q66: 133588179 | R66: 97726435
B67: Financial liabilities at amortised cost – due to depositors | C67: 857269981 | D67: 994370875 | E67: 1068982587 | F67: 1286616399 | G67: 1472640456 | I67: 1977743661 | J67: =Drivers!I501 -> 2.1589899e+09 | K67: =Drivers!J501 -> 2.3624583e+09 | L67: =Drivers!K501 -> 2.6822178e+09 | M67: =Drivers!L501 -> 2.9850489e+09 | P67: 2038498641 | Q67: 1958690813 | R67: 1977743661
B68: Financial liabilities at amortised cost – other borrowings | C68: 23786094 | D68: 25361912 | E68: 23248893 | F68: 54555933 | G68: 32587051 | I68: 16150356 | J68: =Drivers!I534 -> 23481198 | K68: =Drivers!J534 -> 35221797 | L68: =Drivers!K534 -> 52832696 | M68: =Drivers!L534 -> 79249043 | P68: 13243625 | Q68: 11481198 | R68: 16150356
B69: Current tax liabilities | C69: 4202850 | D69: 6735997 | E69: 5197188 | F69: 6991005 | G69: 9486772 | I69: 24916074 | J69: =Drivers!I546 -> 9913347.5 | K69: =Drivers!J546 -> 8703757.9 | L69: =Drivers!K546 -> 9505552.3 | M69: =Drivers!L546 -> 10262820 | P69: 14420344 | Q69: 23513300 | R69: 24916074
B70: Deferred tax liabilities | C70: 3565215 | D70: 971424 | E70: 416458 | F70: 403846 | G70: 349106 | I70: 437123 | J70: =Drivers!I547 -> 437123 | K70: =Drivers!J547 -> 437123 | L70: =Drivers!K547 -> 437123 | M70: =Drivers!L547 -> 437123 | P70: 431708 | Q70: 433316 | R70: 437123
B71: Other liabilities | C71: 19508115 | D71: 24547513 | E71: 30775884 | F71: 33572283 | G71: 33253518 | I71: 40354877 | J71: =Drivers!I553 -> 53974747 | K71: =Drivers!J553 -> 59061458 | L71: =Drivers!K553 -> 67055446 | M71: =Drivers!L553 -> 74626222 | P71: 48296812 | Q71: 36253554 | R71: 40354877
B72: Due to subsidiaries | C72: 0 | D72: 0 | E72: 0 | F72: 0 | G72: 0 | I72: 0 | P72: 0
B73: Subordinated liabilities | C73: 25165924 | D73: 37992457 | E73: 37886789 | F73: 38247138 | G73: 38303466 | I73: 61400967 | J73: =Drivers!I559 -> 32384848 | K73: =Drivers!J559 -> 47249167 | L73: =Drivers!K559 -> 67055446 | M73: =Drivers!L559 -> 74626222 | P73: 24869883 | Q73: 33262957 | R73: 61400967
B74: Total liabilities | C74: 1046953950 | D74: 1199315407 | E74: 1272927883 | F74: 1601547444 | G74: 1813938616 | I74: 2286581330 | J74: =SUM(J64:J73) -> 2.4278254e+09 | K74: =SUM(K64:K73) -> 2.6930289e+09 | L74: =SUM(L64:L73) -> 3.0841763e+09 | M74: =SUM(M64:M73) -> 3.4550211e+09 | P74: 2307486128 | Q74: 2252552712 | R74: 2286581330
B75: Equity
B76: Stated capital | C76: 37143541 | D76: 39147882 | E76: 40916958 | F76: 52187747 | G76: 54566957 | I76: 58149621 | J76: =Drivers!I599 -> 62948003 | K76: =Drivers!J599 -> 69242803 | L76: =Drivers!K599 -> 72704943 | M76: =Drivers!L599 -> 76340191 | P76: 62948003 | Q76: 62891772 | R76: 58149621
B77: Statutory reserves | C77: 6492552 | D77: 7444178 | E77: 8387701 | F77: 9285233 | G77: 10590338 | I77: 12079670 | J77: =Drivers!I609 -> 15112929 | K77: =Drivers!J609 -> 16537208 | L77: =Drivers!K609 -> 18775525 | M77: =Drivers!L609 -> 20895342 | P77: 12079670 | Q77: 12079670 | R77: 12079670
B78: Retained earnings | C78: 5086609 | D78: 4949955 | E78: 5182185 | F78: 8124261 | G78: 9890762 | I78: 6790304 | J78: =Drivers!I615 -> 15698892 | K78: =Drivers!J615 -> 26007129 | L78: =Drivers!K615 -> 35614355 | M78: =Drivers!L615 -> 45720540 | P78: 15470462 | Q78: 9216216 | R78: 6790304
B79: Other reserves | C79: 59272098 | D79: 67855834 | E79: 79937405 | F79: 89595571 | G79: 92426660 | I79: 131845571 | J79: =Drivers!I631 -> 1.3580494e+08 | K79: =Drivers!J631 -> 1.4224759e+08 | L79: =Drivers!K631 -> 1.5048236e+08 | M79: =Drivers!L631 -> 1.591448e+08 | P79: 123309743 | Q79: 121617007 | R79: 131845571
B80: Total equity attributable to equity holders of the Bank | C80: 107994800 | D80: 119397849 | E80: 134424249 | F80: 159192812 | G80: 167474717 | I80: 208865166 | J80: =SUM(J76:J79) -> 2.2956477e+08 | K80: =SUM(K76:K79) -> 2.5403473e+08 | L80: =SUM(L76:L79) -> 2.7757718e+08 | M80: =SUM(M76:M79) -> 3.0210087e+08 | P80: 213807878 | Q80: 205804665 | R80: 208865166
B81: Non-controlling interest | C81: 871906 | D81: 1198981 | E81: 1589234 | F81: 1755897 | G81: 2077811 | I81: 4107408 | J81: =I81+J32 -> 4932277.2 | K81: =J81+K32 -> 6006051.9 | L81: =K81+L32 -> 7149769.3 | M81: =L81+M32 -> 8352886.6 | P81: 4217644 | Q81: 3810820 | R81: 4107408
B82: Total equity | C82: 108866706 | D82: 120596830 | E82: 136013483 | F82: 160948709 | G82: 169552528 | I82: 212972574 | J82: =J80+J81 -> 2.3449704e+08 | K82: =K80+K81 -> 2.6004078e+08 | L82: =L80+L81 -> 2.8472695e+08 | M82: =M80+M81 -> 3.1045376e+08 | P82: 218025522 | Q82: 209615485 | R82: 212972574
B83: Total liabilities and equity | C83: 1155820656 | D83: 1319912237 | E83: 1408941366 | F83: 1762496153 | G83: 1983491144 | I83: 2499553904 | J83: =J74+J82 -> 2.6623224e+09 | K83: =K74+K82 -> 2.9530697e+09 | L83: =L74+L82 -> 3.3689033e+09 | M83: =M74+M82 -> 3.7654749e+09 | P83: 2525511650 | Q83: 2462168197 | R83: 2499553904
B84: Contingent liabilities and commitments | C84: 565277821 | D84: 658860264 | E84: 580961807 | F84: 730561685 | G84: 685379028 | I84: 555531537 | Q84: 605333607 | R84: 555531537
B85: Net assets value per ordinary share (Rs.) | C85: 108.44 | D85: 118.13 | E85: 130.83 | F85: 136.42 | G85: 140.24 | I85: 168.47 | J85: =Drivers!I595 -> 174.69072 | K85: =Drivers!J595 -> 193.3115 | L85: =Drivers!K595 -> 211.22648 | M85: =Drivers!L595 -> 229.88815 | P85: 162.7 | Q85: 156.68 | R85: 168.47
B86: Memorandum information
B87: Number of employees | C87: 4982 | D87: 5027 | E87: 5062 | F87: 5057 | G87: 5072 | I87: 5121 | J87: =I87*1.01 -> 5172.21 | K87: =J87*1.01 -> 5223.9321 | L87: =K87*1.01 -> 5276.1714 | M87: =L87*1.01 -> 5328.9331
B88: Number of customer service centres | C88: 280 | D88: 285 | E88: 287 | F88: 287 | G88: 287 | I88: 289 | J88: =I88*1.005 -> 290.445 | K88: =J88*1.005 -> 291.89722 | L88: =K88*1.005 -> 293.35671 | M88: =L88*1.005 -> 294.82349
B90: BS check | C90: =SUM(C45:C61)-SUM(C64:C73)-SUM(C76:C79)-C81 -> 0 | D90: =SUM(D45:D61)-SUM(D64:D73)-SUM(D76:D79)-D81 -> 0 | E90: =SUM(E45:E61)-SUM(E64:E73)-SUM(E76:E79)-E81 -> 0 | F90: =SUM(F45:F61)-SUM(F64:F73)-SUM(F76:F79)-F81 -> 0 | G90: =SUM(G45:G61)-SUM(G64:G73)-SUM(G76:G79)-G81 -> 0 | I90: =SUM(I45:I61)-SUM(I64:I73)-SUM(I76:I79)-I81 -> 0 | Q90: =SUM(Q45:Q61)-SUM(Q64:Q73)-SUM(Q76:Q79)-Q81 -> 0 | R90: =SUM(R45:R61)-SUM(R64:R73)-SUM(R76:R79)-R81 -> 0
B92: Cash / total assets | C92: =C45/C62 -> 0.029998966 | D92: =D45/D62 -> 0.033605236 | E92: =E45/E62 -> 0.038100321 | F92: =F45/F62 -> 0.029080932 | G92: =G45/G62 -> 0.034956233 | I92: =I45/I62 -> 0.060454583 | J92: =J45/J62 -> 0.039783431 | K92: =K45/K62 -> 0.037144427 | L92: =L45/L62 -> 0.047221241 | M92: =M45/M62 -> 0.044651353 | P92: =P45/P62 -> 0.04534453
I93: =((I88/E88)^(1/3))-1 -> 0.0023175054
B94: CASH FLOW STATEMENT
B96: Cash flows from operating activities Profit before income tax | C96: 23280324 | D96: 26098548 | E96: 22983896 | F96: 24519860 | G96: 32957324 | I96: 24505038
B97: Adjustments for:
B98: Non-cash items included in profit before tax | C98: 1078540 | D98: 12380685 | E98: 14014272 | F98: 24764927 | G98: 30473593 | I98: 91299070
B99: Change in operating assets | C99: -125489870 | D99: -169379105 | E99: -84218375 | F99: -374761711 | G99: -230261220 | I99: -463345077
B100: Change in operating liabilities | C100: 100265879 | D100: 138876499 | E100: 69879669 | F100: 325708382 | G100: 208070200 | I100: 430778836
B101: (Gains)/losses on sale of property, plant and equipment | C101: 18774 | D101: -9311 | E101: -19731 | F101: -5820 | G101: -4054 | I101: -20118
B102: Share of (profit)/loss of associate, net of tax | C102: -3678 | D102: -6048 | E102: -9992 | F102: -3898 | G102: -1896 | I102: 3727
B103: Dividends received from investments in associate and subsidiaries | C103: 0 | D103: 0 | E103: 0 | F103: 0 | G103: 0 | I103: 0
B104: Interest expense on subordinated liabilities | C104: 2377694 | D104: 3105553 | E104: 3848979 | F104: 3756921 | G104: 3398554 | I104: 4843571
B105: Net unrealised gains/(losses) arising from translating the Financial Statements of foreign operations | C105: -503140 | D105: 3003952 | E105: -396201 | F105: 596723 | G105: 1278891 | I105: 18347815
B106: Benefits paid on defined benefit plans | C106: -184464 | D106: -382409 | E106: -198799 | F106: -673106 | G106: -1116195 | I106: -780828
...

Sheet Valuation
A1: All figures in LKR 000 | D1: 0 | E1: 1 | F1: 2
A2: Residual income | C2: =FS!J4 -> 2023F | D2: =FS!K4 -> 2024F | E2: =FS!L4 -> 2025F | F2: =FS!M4 -> 2026F
A3: Equity | C3: =FS!J80 -> 2.2956477e+08 | D3: =FS!K80 -> 2.5403473e+08 | E3: =FS!L80 -> 2.7757718e+08 | F3: =FS!M80 -> 3.0210087e+08
A4: ROE | C4: =FS!J30/FS!J82 -> 0.087940259 | D4: =FS!K30/FS!K82 -> 0.10323137 | E4: =FS!L30/FS!L82 -> 0.1004223 | F4: =FS!M30/FS!M82 -> 0.096883779
A5: Net income | C5: =FS!J31 -> 19796862 | D5: =FS!K31 -> 25770592 | E5: =FS!L31 -> 27449218 | F5: =FS!M31 -> 28874816
A6: Equity charge | C6: =C3*C4 -> 20187985 | D6: =D3*D4 -> 26224354 | E6: =E3*E4 -> 27874939 | F6: =F3*F4 -> 29268674
A7: Residual income | C7: =C5-C6 -> -391123.5 | D7: =D5-D6 -> -453761.69 | E7: =E5-E6 -> -425721.12 | F7: =F5-F6 -> -393858.12
A8: Terminal value | F8: =(F7*(1+B32))/(B26-B32) -> -1505842.1
A9: Discount factor | D9: =1/((1+$B$26)^D1) -> 1 | E9: =1/((1+$B$26)^E1) -> 0.76958596 | F9: =1/((1+$B$26)^F1) -> 0.59226255
A10: PV of RI + terminal value | D10: =D7*D9 -> -453761.69 | E10: =E7*E9 -> -327629 | F10: =(F7*F9)+(F8*F9) -> -1125121.3
A12: Residual Income (RI) Valuation | B12: (LKR '000)
A13: Present Value of Residual Income | B13: =SUM(E10:F10) -> -1452750.3
A14: No of shares ('000) | B14: =Drivers!I586/1000 -> 1314121.1
A15: Residual Income per share | B15: =(B13)/B14 -> -1.1054919
A16: Net Asset Value Per Share | B16: =FS!P85 -> 162.7
A17: Value per share | B17: =B15+B16 -> 161.59451
A22: Cost of equity
A23: Risk Free rate | B23: 0.12
A24: Equity Risk Premium | B24: 0.23
A25: Beta | B25: 0.78
A26: Cost of Equity | B26: =B23+(B24*B25) -> 0.2994
A28: g = b x ROE
A29: 1-payout
A30: ROE (2023E) | B30: =FS!J30/FS!J82 -> 0.087940259
A32: Estiamted g | B32: 0.03
A37: PBV based valuation
A45: Justified Price to Book Valuation
A46: ROE (2024 expected) | B46: =D4 -> 0.10323137
A47: Growth rate (g) | B47: =B32 -> 0.03
A48: Cost of equity (r) | B48: =B26 -> 0.2994
A49: Justified PBV = (ROE - g)/ (r - g) | B49: =(B46-B47)/(B48-B47) -> 0.27183137
A50: Net Asset Value Per Share (2024E) | B50: =Drivers!J591 -> 193.3115
A51: Value per share | B51: =B49*B50 -> 52.548131
A52: Peer PBV | B52: =AVERAGE(C71:C77) -> 0.44728571
A53: Curent NAVPS | B53: =FS!P85 -> 162.7
A57: Forward PE Valuation
A58: Peer average PE | B58: =AVERAGE(B71:B77) -> 3.6592857
A59: Expected forward PE | B59: 5
A60: EPS (2024E) | B60: =FS!K34 -> 19.610515
A61: Value per share | B61: =B59*B60 -> 98.052574
A62: FY24 EPS | B62: =(FS!J31*1000)/Drivers!I586 -> 15.064716
A63: TTM EPS | B63: 17.48
C64: 2022 | D64: 9M 2023 | E64: 9M 2022 | F64: TTM
A65: PAT to equity | C65: =FS!I31 -> 23811914 | D65: 14199928 | E65: 15036726 | F65: =C65+D65-E65 -> 22975116
A66: EPS | F66: =F65*1000/Drivers!I586 -> 17.483256
A68: comparison - forward PE
A70: Peer valuation multiples | B70: PE | C70: PBV
A71: HNB.N | B71: 4.183 | C71: 0.455
A72: SAMP.N | B72: 4.31 | C72: 0.542
A73: NTB.N | B73: 2.941 | C73: 0.487
A74: NDB.N | B74: 3.327 | C74: 0.341
A75: SEYB.N | B75: 4.103 | C75: 0.438
A76: DFCC.N | B76: 3.748 | C76: 0.481
A77: PABC.N | B77: 3.003 | C77: 0.387
A78: Peer average | B78: =AVERAGE(B71:B77) -> 3.6592857 | C78: =AVERAGE(C71:C77) -> 0.44728571
A80: Justified Trailng PE | B80: (1-b) (1+g) / (r - g)
A81: Dividend payout | B81: =FS!I36/FS!I35 -> 0.23425299
A82: b | B82: =1-B81 -> 0.76574701
A83: g
A84: r
A85: Justified PE | B85: =((1-B82)*(1+B47))/(B26-B32) -> 0.89562206
A87: Weighted average intrinsic value
A88: RI | B88: =B17 -> 161.59451
A89: Justified PBV | B89: =B51 -> 52.548131
A90: Forward PE | B90: =B61 -> 98.052574
A91: FY24 NAVPS | B91: =Drivers!J591 -> 193.3115
A92: Weighted average value per share - COMB.N | B92: =AVERAGE(B88:B91) -> 126.37668
A93: Weighted average value per share - COMB.X | B93: =B92*(1-B111) -> 107.60586
A95: Dividend - FY24 | B95: =FS!K36 -> 6.8636802
A97: Current price - voting | B97: 91
A98: Return - voting | B98: =(B92-B97)/B97 -> 0.38875472
A99: Divided yield - vorting | B99: =B95/B97 -> 0.075425057
A100: total return - voting | B100: =B98+B99 -> 0.46417977
A102: Current price - non voting | B102: 76.3
A103: Return - non voting | B103: =(B93-B102)/B102 -> 0.41029964
A104: Divided yield - non voting | B104: =B95/B102 -> 0.08995649
A105: total return - non voting | B105: =B103+B104 -> 0.50025613
A108: Discount to Non voting share
A109: Voting | B109: 95.5
A110: Non voting | B110: 80.4
A111: Discount to Non voting share | B111: =AVERAGE('Price volume'!AJ5:AJ1175) -> 0.1485307
A115: Net Asset Value Based Valuation
A116: Net Asset Value per share (Sep 2023) | B116: =B53 -> 162.7
A117: Net Asset Value per share (2024E) | B117: =B91 -> 193.3115
A120: 1-year T bill rate | B120: 0.1293
B121: =B120+5% -> 0.1793

Sheet Drivers
B3: For the year ended December 31, | N3: Annualised | P3: Period | Q3: Quarter
B4: (LKR '000 except per share data) | C4: 2017 | D4: 2018 | E4: 2019 | F4: 2020 | G4: 2021 | H4: 2022 | I4: 2023F | J4: 2024F | K4: 2025F | L4: 2026F | N4: 45192 | O4: 45100 | P4: 45078
B5: INCOME STATEMENT
B7: Interest income | C7: 104049102 | D7: 118551239 | E7: 129287743 | F7: 124087713 | G7: 132818178 | H7: 222393079 | I7: =I13+SUM(I14:I19) -> 3.0585734e+08 | J7: =J13+SUM(J14:J19) -> 2.9513936e+08 | K7: =K13+SUM(K14:K19) -> 3.3784948e+08 | L7: =L13+SUM(L14:L19) -> 3.8175485e+08 | N7: =FS!P7/9*12 -> 2.9942669e+08 | P7: 150811644 | Q7: 88116673 | R7: =P7*2 -> 301623288
B9: Cash and cash equivalents | C9: 362695 | D9: 411412 | E9: 1290697 | F9: 1053757 | G9: 447742 | H9: 945450 | I9: =FS!I45*Drivers!I55 -> 2055089.1 | J9: =FS!J45*Drivers!J55 -> 1440462 | K9: =FS!K45*Drivers!K55 -> 1491785.1 | L9: =FS!L45*Drivers!L55 -> 2163539.6
B10: Balances with Central Banks | C10: 4400 | D10: 26734 | E10: 62572 | F10: 1175509 | G10: 1299948 | H10: 815979
B11: Placements with Banks | C11: 215909 | D11: 529738 | E11: 931571 | F11: 777425 | G11: 778021 | H11: 1685996 | I11: =I252*I28 -> 1348796.8 | J11: =J252*J28 -> 1416236.6 | K11: =K252*K28 -> 1487048.5 | L11: =L252*L28 -> 1561400.9
B12: Securities purchased under resale agreements | C12: 139153 | D12: 508616 | E12: 1906902 | F12: 836773 | G12: 375398 | H12: 1133583 | I12: =I264*I29 -> 453433.2 | J12: =J264*J29 -> 476104.86 | K12: =K264*K29 -> 499910.1 | L12: =L264*L29 -> 524905.61
B13: Financial assets recognized through profit or loss | C13: 469012 | D13: 323335 | E13: 474478 | F13: 1831327 | G13: 1101385 | H13: 1516691 | I13: =SUM(I9:I12) -> 3857319.1 | J13: =SUM(J9:J12) -> 3332803.5 | K13: =SUM(K9:K12) -> 3478743.7 | L13: =SUM(L9:L12) -> 4249846.1
B14: Derivatives | C14: 24111 | D14: 56173 | E14: 67453 | F14: 34902 | G14: 167377 | H14: 237438 | I14: =I266*I31 -> 166206.6 | J14: =J266*J31 -> 174516.93 | K14: =K266*K31 -> 183242.78 | L14: =L266*L31 -> 192404.92
B15: Other financial instruments | C15: 444901 | D15: 267162 | E15: 407025 | F15: 1796425 | G15: 934008 | H15: 1279253 | I15: =I271*I32 -> 4946643.7 | J15: =J271*J32 -> 7798003.1 | K15: =K271*K32 -> 8577803.4 | L15: =L271*L32 -> 9435583.8
B16: Financial assets at amortized cost - loans and advances to other customers | C16: 78132371 | D16: 95081154 | E16: 100444369 | F16: 84257196 | G16: 79654575 | H16: 144253496 | I16: =I33*I305 -> 2.028142e+08 | J16: =J33*J305 -> 1.8785541e+08 | K16: =K33*K305 -> 2.1976882e+08 | L16: =L33*L305 -> 2.5273414e+08
B17: Financial assets at amortized cost - debt and other financial instruments | C17: 8512118 | D17: 6828671 | E17: 7819563 | F17: 13194851 | G17: 25951467 | H17: 51750895 | I17: =I50*I341 -> 48193316 | J17: =J50*J341 -> 45412106 | K17: =K50*K341 -> 50127260 | L17: =L50*L341 -> 53757016
B18: Financial assets measured at fair value through other comprehensive income | C18: 15349974 | D18: 14478042 | E18: 15091368 | F18: 18053545 | G18: 22034788 | H18: 18995711 | I18: =I52*I384 -> 44543209 | J18: =J52*J384 -> 48997530 | K18: =K52*K384 -> 53897283 | L18: =L52*L384 -> 59287011
B19: Interest accrued on impaired loans and advances to other customers | C19: 861057 | D19: 360876 | E19: 1258339 | F19: 2895955 | G19: 1174854 | H19: 1295278 | I19: =I53*I289 -> 1336443.5 | J19: =J53*J289 -> 1568988.3 | K19: =K53*K289 -> 1816328.7 | L19: =L53*L289 -> 2098847.6
C20: 2413 | D20: 2661 | E20: 7884 | F20: 11375 | G20: 0 | H20: 0
B22: Check | C22: =SUM(C9:C13)+C16+C17+C18+C19+C20-C7 -> 0 | D22: =SUM(D9:D13)+D16+D17+D18+D19+D20-D7 -> 0 | E22: =SUM(E9:E13)+E16+E17+E18+E19+E20-E7 -> 0 | F22: =SUM(F9:F13)+F16+F17+F18+F19+F20-F7 -> 0 | G22: =SUM(G9:G13)+G16+G17+G18+G19+G20-G7 -> 0 | H22: =SUM(H9:H13)+H16+H17+H18+H19+H20-H7 -> 0
B24: Interest rate
B26: Cash and cash equivalents | C26: =C9/FS!C45 -> 0.010460317 | D26: =D9/FS!D45 -> 0.0092752356 | E26: =E9/FS!E45 -> 0.02404378 | F26: =F9/FS!F45 -> 0.020559094 | G26: =G9/FS!G45 -> 0.0064576268 | H26: =H9/FS!I45 -> 0.0062567215 | I26: 0.0062567215 | J26: 0.0062567215 | K26: 0.0062567215 | L26: 0.0062567215
B27: Balances with Central Banks | C27: =C10/FS!C46 -> 9.6604889e-05 | D27: =D10/FS!D46 -> 0.00048250626 | E27: =E10/FS!E46 -> 0.0013572739 | F27: =F10/FS!F46 -> 0.010190031 | G27: =G10/FS!G46 -> 0.022895492 | H27: =H10/FS!I46 -> 0.010381793 | I27: 0.010381793 | J27: 0.010381793 | K27: 0.010381793 | L27: 0.010381793
B28: Placements with Banks | C28: =C11/FS!C47 -> 0.012244411 | D28: =D11/FS!D47 -> 0.026621987 | E28: =E11/FS!E47 -> 0.037406768 | F28: =F11/FS!F47 -> 0.047340841 | G28: =G11/FS!G47 -> 0.062248109 | H28: =H11/FS!I47 -> 0.017547299 | I28: 0.017547299 | J28: 0.017547299 | K28: 0.017547299 | L28: 0.017547299
B29: Securities purchased under resale agreements | C29: =C12/FS!C48 -> #DIV/0! | D29: =D12/FS!D48 -> 0.053462486 | E29: =E12/FS!E48 -> 0.14503876 | F29: =F12/FS!F48 -> #DIV/0! | G29: =G12/FS!G48 -> 0.12511223 | H29: =H12/FS!I48 -> 0.74710145 | I29: 0.74710145 | J29: 0.74710145 | K29: 0.74710145 | L29: 0.74710145
B30: Financial assets recognized through profit or loss
B31: Derivatives | C31: =C14/FS!C49 -> 0.010327962 | D31: =D14/FS!D49 -> 0.0071015512 | E31: =E14/FS!E49 -> 0.036840901 | F31: =F14/FS!F49 -> 0.013236915 | G31: =G14/FS!G49 -> 0.051578062 | H31: =H14/FS!I49 -> 0.028452416 | I31: 0.028452416 | J31: 0.028452416 | K31: 0.028452416 | L31: 0.028452416
B32: Other financial instruments | C32: =C15/C271 -> 0.1008637 | D32: =D15/D271 -> 0.048397449 | E32: =E15/E271 -> 0.018959585 | F32: =F15/F271 -> 0.051050071 | G32: =G15/G271 -> 0.039853349 | H32: =H15/H271 -> 0.051431274 | I32: 0.05 | J32: 0.05 | K32: 0.05 | L32: 0.05
B33: Financial assets at amortized cost - loans and advances to other customers | C33: =C16/FS!C52 -> 0.1052367 | D33: =D16/FS!D52 -> 0.10958949 | E33: =E16/FS!E52 -> 0.11236402 | F33: =F16/FS!F52 -> 0.09260771 | G33: =G16/FS!G52 -> 0.07736578 | H33: =H16/FS!I52 -> 0.12484157 | I33: 0.155 | J33: 0.12484157 | K33: 0.127 | L33: 0.127
B34: Overdrafts | H34: 0.28 | I34: 0.28 | J34: 0.28 | K34: 0.28 | L34: 0.28
B35: Trade finance | H35: 0.155 | I35: 0.155 | J35: 0.155 | K35: 0.155 | L35: 0.155
B36: Lease/hire purchase receivable | H36: 0.16 | I36: 0.16 | J36: 0.16 | K36: 0.16 | L36: 0.16
B37: Credit cards | H37: 0.28 | I37: 0.28 | J37: 0.28 | K37: 0.28 | L37: 0.28
B38: Pawning
B39: Staff loans
B40: Housing loans | H40: 0.15 | I40: 0.15 | J40: 0.15 | K40: 0.15 | L40: 0.15
B41: Personal loans
B42: Term loans
B43: Short term
B44: Long term | H44: =H47+2% -> 0.16 | I44: 0.16 | J44: 0.16 | K44: 0.16 | L44: 0.16
B45: Bills of exchange
B47: Average AWPLR throughout the year | H47: 0.14 | I47: 0.14 | J47: 0.14 | K47: 0.14 | L47: 0.14
B50: Financial assets at amortized cost - debt and other financial instruments | C50: =C17/FS!C53 -> 0.072088775 | D50: =D17/FS!D53 -> 0.076490797 | E50: =E17/FS!E53 -> 0.073039739 | F50: =F17/FS!F53 -> 0.043682949 | G50: =G17/FS!G53 -> 0.067338091 | H50: =H17/FS!I53 -> 0.067945748 | I50: 0.067945748 | J50: 0.067945748 | K50: 0.067945748 | L50: 0.067945748
B52: Financial assets measured at fair value through other comprehensive income | C52: =C18/FS!C54 -> 0.099087296 | D52: =D18/FS!D54 -> 0.081907626 | E52: =E18/FS!E54 -> 0.076286449 | F52: =F18/FS!F54 -> 0.064773797 | G52: =G18/FS!G54 -> 0.065588744 | H52: =H18/FS!I54 -> 0.16009566 | I52: 0.15 | J52: 0.15 | K52: 0.15 | L52: 0.15
B53: Interest accrued on impaired loans and advances to other customers | C53: =C19/C289 -> 0.00115976 | D53: =D19/D289 -> 0.0004159417 | E53: =E19/E289 -> 0.0014076651 | F53: =F19/F289 -> 0.0031829656 | G53: =G19/G289 -> 0.0011410957 | H53: =H19/H289 -> 0.0011209748 | I53: 0.0011 | J53: 0.0011 | K53: 0.0011 | L53: 0.0011
B55: Interest on opening cash | E55: =E9/FS!D45 -> 0.029098614 | F55: =F9/FS!E45 -> 0.019629938 | G55: =G9/FS!F45 -> 0.0087355719 | H55: =H9/FS!G45 -> 0.013635896 | I55: 0.0136 | J55: 0.0136 | K55: 0.0136 | L55: 0.0136
B58: Interest expense | C58: 64481804 | D58: 72933030 | E58: 80931352 | F58: 73218911 | G58: 66401846 | H58: 137727868 | I58: =I63+I69 -> 2.2269493e+08 | J58: =J63+J69 -> 2.3202049e+08 | K58: =K63+K69 -> 2.6615841e+08 | L58: =L63+L69 -> 3.0080788e+08 | N58: =FS!P8/9*12 -> 2.18251e+08 | P58: 113361974 | Q58: 47404088 | R58: =P58*2 -> 226723948
B60: Due to banks | C60: 2069416 | D60: 2313673 | E60: 2484166 | F60: 2845641 | G60: 3326777 | H60: 4019415
B61: Derivative financial liabilities | C61: 38702 | D61: 57860 | E61: 63161 | F61: 65473 | G61: 196903 | H61: 422823
B62: Securities sold under repurchase agreements | C62: 5943417 | D62: 3815335 | E62: 3256622 | F62: 3516363 | G62: 6190149 | H62: 21906770
B63: Financial liabilities at amortised cost – due to depositors | C63: 53385259 | D63: 62397741 | E63: 69503417 | F63: 61416382 | G63: 51533473 | H63: 105008989 | I63: =I501*I71 -> 1.8999111e+08 | J63: =J501*J71 -> 1.8899667e+08 | K63: =K501*K71 -> 2.1457743e+08 | L63: =L501*L71 -> 2.3880391e+08
B64: Refinance borrowings | C64: 352074 | D64: 427958 | E64: 472813 | F64: 578780 | G64: 679976 | H64: 551968
B65: Foreign currency borrowings | C65: 315242 | D65: 814910 | E65: 872931 | F65: 603597 | G65: 624395 | H65: 476698
B66: Subordinated liabilities | C66: 2377694 | D66: 3105553 | E66: 3848979 | F66: 3756921 | G66: 3398554 | H66: 4843571
B67: Interest expense on lease liabilities | E67: 429263 | F67: 435754 | G67: 451619 | H67: 497634
B69: Interest expense except depositors | C69: =C60+C61+C62+C64+C65+C66+C67 -> 11096545 | D69: =D60+D61+D62+D64+D65+D66+D67 -> 10535289 | E69: =E60+E61+E62+E64+E65+E66+E67 -> 11427935 | F69: =F60+F61+F62+F64+F65+F66+F67 -> 11802529 | G69: =G60+G61+G62+G64+G65+G66+G67 -> 14868373 | H69: =H60+H61+H62+H64+H65+H66+H67 -> 32718879 | I69: =I72*(FS!J64+FS!J65+FS!J66+FS!J68) -> 32703824 | J69: =J72*(FS!K64+FS!K65+FS!K66+FS!K68) -> 43023820 | K69: =K72*(FS!L64+FS!L65+FS!L66+FS!L68) -> 51580983 | L69: =L72*(FS!M64+FS!M65+FS!M66+FS!M68) -> 62003975
B71: Deposit interest rate | C71: =C63/C501 -> 0.062273566 | D71: =D63/D501 -> 0.062750974 | E71: =E63/E501 -> 0.065018287 | F71: =F63/F501 -> 0.047734804 | G71: =G63/G501 -> 0.034993927 | H71: =H63/H501 -> 0.053095349 | I71: 0.088 | J71: 0.08 | K71: 0.08 | L71: 0.08
B72: Other financial liabilities | C72: =(C60+C61+C62+C64+C65+C66+C67)/(FS!C64+FS!C65+FS!C66+FS!C68) -> 0.080853936 | D72: =(D60+D61+D62+D64+D65+D66+D67)/(FS!D64+FS!D65+FS!D66+FS!D68) -> 0.078214645 | E72: =(E60+E61+E62+E64+E65+E66+E67)/(FS!E64+FS!E65+FS!E66+FS!E68) -> 0.088131605 | F72: =(F60+F61+F62+F64+F65+F66+F67)/(FS!F64+FS!F65+FS!F66+FS!F68) -> 0.050070807 | G72: =(G60+G61+G62+G64+G65+G66+G67)/(FS!G64+FS!G65+FS!G66+FS!G68) -> 0.057206887 | H72: =(H60+H61+H62+H64+H65+H66+H67)/(FS!I64+FS!I65+FS!I66+FS!I68) -> 0.18004251 | I72: 0.19 | J72: 0.2 | K72: 0.2 | L72: 0.2
B74: Check | C74: =SUM(C60:C67)-C58 -> 0 | D74: =SUM(D60:D67)-D58 -> 0 | E74: =SUM(E60:E67)-E58 -> 0 | F74: =SUM(F60:F67)-F58 -> 0 | G74: =SUM(G60:G67)-G58 -> 0 | H74: =SUM(H60:H67)-H58 -> 0
B78: Fee and commission income | C78: 10510800 | D78: 12494090 | E78: 12874966 | F78: 11839689 | G78: 15917337 | H78: 26191530 | I78: =I89*FS!J52 -> 30373717 | J78: =J89*FS!K52 -> 35658826 | K78: =K89*FS!L52 -> 41280198 | L78: =L89*FS!M52 -> 47701081 | N78: =FS!P10/9*12 -> 29379307 | P78: 14377446 | Q78: 11758745 | R78: =P78*2 -> 28754892
B80: Loans and advances related services | C80: 834468 | D80: 944858 | E80: 881213 | F80: 861317 | G80: 995957 | H80: 683255
B81: Credit and debit cards related services | C81: 3389773 | D81: 4191679 | E81: 4566923 | F81: 3723129 | G81: 6011952 | H81: 9963857
B82: Trade and remittances related services | C82: 3184574 | D82: 3812516 | E82: 3998926 | F82: 4431425 | G82: 5618954 | H82: 11155415
B83: Deposits related services | C83: 1687448 | D83: 1952323 | E83: 1852565 | F83: 1151909 | G83: 1152602 | H83: 1333869
B84: Guarantees related services | C84: 798583 | D84: 1063585 | E84: 942615 | F84: 908508 | G84: 1091690 | H84: 1342030
B85: Other financial services | C85: 615954 | D85: 529129 | E85: 632724 | F85: 763401 | G85: 1046182 | H85: 1713104
B87: Check | C87: =SUM(C80:C85)-C78 -> 0 | D87: =SUM(D80:D85)-D78 -> 0 | E87: =SUM(E80:E85)-E78 -> 0 | F87: =SUM(F80:F85)-F78 -> 0 | G87: =SUM(G80:G85)-G78 -> 0 | H87: =SUM(H80:H85)-H78 -> 0
B89: As a % of loan book | E89: =E78/FS!E52 -> 0.014402828 | F89: =F78/FS!F52 -> 0.01301309 | G89: =G78/FS!G52 -> 0.015459968 | H89: =H78/FS!I52 -> 0.022666983 | I89: 0.025 | J89: 0.025 | K89: 0.025 | L89: 0.025
B93: Fee and commission expense | C93: 1586334 | D93: 1859698 | E93: 2123128 | F93: 2018014 | G93: 3675143 | H93: 6022429 | I93: =I102*I78 -> 7593429.2 | J93: =J102*J78 -> 8201529.9 | K93: =K102*K78 -> 9494445.4 | L93: =L102*L78 -> 10971249 | N93: =FS!P11/9*12 -> 7766089.3 | P93: 3786488 | Q93: 2881243 | R93: =P93*2 -> 7572976
B95: Loans and advances related services | C95: 58313 | D95: 66131 | E95: 54028 | F95: 48591 | G95: 52020 | H95: 57915
B96: Credit and debit cards related services | C96: 1385010 | D96: 1631600 | E96: 1877797 | F96: 1811962 | G96: 3439222 | H96: 5721589
B97: Trade and remittances related services | C97: 44205 | D97: 47204 | E97: 62299 | F97: 55456 | G97: 63092 | H97: 89244
B98: Other financial services | C98: 98806 | D98: 114763 | E98: 129004 | F98: 102005 | G98: 120809 | H98: 153681
B100: Check | C100: =SUM(C95:C98)-C93 -> 0 | D100: =SUM(D95:D98)-D93 -> 0 | E100: =SUM(E95:E98)-E93 -> 0 | F100: =SUM(F95:F98)-F93 -> 0 | G100: =SUM(G95:G98)-G93 -> 0 | H100: =SUM(H95:H98)-H93 -> 0
B102: As a % of fee income | C102: =C93/C78 -> 0.15092419 | D102: =D93/D78 -> 0.14884621 | E102: =E93/E78 -> 0.16490358 | F102: =F93/F78 -> 0.17044485 | G102: =G93/G78 -> 0.23088931 | H102: =H93/H78 -> 0.22993804 | I102: 0.25 | J102: 0.23 | K102: 0.23 | L102: 0.23
B106: Net gains/(losses) from trading | C106: 233956 | D106: -3033236 | E106: 1360833 | F106: 1878060 | G106: 1936007 | H106: 35297450 | I106: =FS!P13/9*12 -> -16199576 | J106: =G106*1.01 -> 1955367.1 | K106: =J106*1.01 -> 1974920.7 | L106: =K106*1.01 -> 1994669.9 | P106: -15531353 | Q106: 32101899 | R106: =P106*2 -> -31062706
B108: Derivative financial instruments | C108: 107201 | D108: -3121949 | E108: 1078749 | F108: 977206 | G108: 1748834 | H108: 35903416
B109: Foreign exchange gains/(losses) from banks and other customers | C109: 107201 | D109: -3121949 | E109: 1078749 | F109: 977206 | G109: 1804014 | H109: 36357421
B110: Financial assets recognised through profit or loss – measured at fair value | G110: -55180 | H110: -454004
B111: Government Securities | C111: 122390 | D111: -4839 | E111: 67548 | F111: 557579 | G111: -162829 | H111: -1169637
B112: Net mark-to-market gains/(losses) | C112: 94672 | D112: -24572 | E112: 26386 | F112: 226036 | G112: -583205 | H112: -1320747
B113: Net capital gains | C113: 27718 | D113: 19733 | E113: 41162 | F113: 331543 | G113: 420376 | H113: 150809
B114: Equities | C114: 4365 | D114: 93552 | E114: 214536 | F114: 343275 | G114: 350002 | H114: 563971
B115: Net mark-to-market gains/(losses) | C115: -9046 | D115: 80151 | E115: 200299 | F115: 303612 | G115: 105673 | H115: 348256
B116: Net capital gains | C116: 3251 | D116: 1026 | E116: 916 | F116: 20468 | G116: 207954 | H116: 175531
B117: Dividend income | C117: 10160 | D117: 12375 | E117: 13321 | F117: 19195 | G117: 36375 | H117: 40184
B119: Check | C119: =SUM(C115:C117,C112:C113,C109:C110)-C106 -> 0 | D119: =SUM(D115:D117,D112:D113,D109:D110)-D106 -> 0 | E119: =SUM(E115:E117,E112:E113,E109:E110)-E106 -> 0 | F119: =SUM(F115:F117,F112:F113,F109:F110)-F106 -> 0 | G119: =SUM(G115:G117,G112:G113,G109:G110)-G106 -> 0 | H119: =SUM(H115:H117,H112:H113,H109:H110)-H106 -> 0
B123: Net other operating income | C123: 720026 | D123: 11373098 | E123: 6081876 | F123: 7770754 | G123: 10002216 | H123: -3771999 | I123: =FS!P15/9*12 -> 25159709 | J123: =I123*1.05 -> 26417695 | K123: =J123*1.05 -> 27738580 | L123: =K123*1.05 -> 29125509 | P123: 17086020 | Q123: -12524129 | R123: =P123*2 -> 34172040
B125: Gains/(losses) on sale of property, plant and equipment | C125: -18774 | D125: 9311 | E125: 19731 | F125: 5820 | G125: 4054 | H125: 20118
B126: Gains on revaluation of foreign exchange | C126: 489824 | D126: 11185438 | E126: 5783595 | F126: 7395513 | G126: 8832749 | H126: -5133408
B127: Recoveries o/a loans written off | C127: 32820 | D127: 21288 | E127: 20360 | F127: 157103 | G127: 316277 | H127: 449028
B128: Dividend income from subsidiaries | C128: 0 | D128: 0 | E128: 0 | F128: 0 | G128: =-4111+4111 -> 0 | H128: 0
B129: Dividend income from other equity securities | C129: =37938+4111-4111 -> 37938 | D129: 34119 | E129: 40076 | F129: 28739 | G129: 48638 | H129: 54571
B130: Profit due to change in ownership | C130: 5262 | D130: 3344 | E130: 14498 | F130: 0
B131: Rental and other income | C131: 178218 | D131: 122942 | E131: 218114 | F131: 183579 | G131: 795214 | H131: 829742
B132: Less: Profit due to change in ownership | C132: -5262 | D132: -3344 | E132: -14498 | F132: 0 | G132: 5284 | H132: 7950
B134: Check | C134: =SUM(C125:C131)+C132-C123 -> 0 | D134: =SUM(D125:D131)+D132-D123 -> 0 | E134: =SUM(E125:E131)+E132-E123 -> 0 | F134: =SUM(F125:F131)+F132-F123 -> 0 | G134: =SUM(G125:G131)+G132-G123 -> 0 | H134: =SUM(H125:H131)+H132-H123 -> 0
B138: Impairment charges and other losses | C138: 989315 | D138: 8833362 | E138: 11331523 | F138: 21419532 | G138: 25139926 | H138: 71924260 | I138: =I151*I305 -> 35328926 | J138: =J151*J305 -> 30095011 | K138: =K151*K305 -> 34609262 | L138: =L151*L305 -> 39800652 | N138: =FS!P17/9*12 -> 34376147 | P138: 13210963 | Q138: 35218619 | R138: =P138*2 -> 26421926
B140: Loans and advances to other customers | C140: 988639 | D140: 8379540 | E140: 10309857 | F140: 18124673 | G140: 14947268 | H140: 22296719
B141: Individual impairment | C141: -22317 | D141: -1002000 | E141: 1938437 | F141: 3983706
B142: Collective impairment | C142: 1211813 | D142: 9381540 | E142: 8371420 | F142: 14140967
B144: Other financial assets and off-balance sheet credit exposures | C144: 0 | D144: 452856 | E144: 1020414 | F144: 3291313 | G144: =6948387+3242610 -> 10190997 | H144: =47281554+2196056 -> 49477610
B145: Total impairment charges | C145: 988639 | D145: 8832396 | E145: 11330271 | F145: 21415986 | G145: 25138265 | H145: 71774329
...

Sheet Ratios
C2: =FS!C4 -> 2017 | D2: =FS!D4 -> 2018 | E2: =FS!E4 -> 2019 | F2: =FS!F4 -> 2020 | G2: =FS!G4 -> 2021 | H2: =FS!I4 -> 2022 | I2: =FS!J4 -> 2023F | J2: =FS!K4 -> 2024F | K2: =FS!L4 -> 2025F | L2: =FS!M4 -> 2026F
B3: Avg. yield on interest earning assets | C3: =FS!C7/(FS!C49+FS!C50+FS!C51+FS!C52+FS!C53+FS!C54) -> 0.10172748 | D3: =FS!D7/(FS!D49+FS!D50+FS!D51+FS!D52+FS!D53+FS!D54) -> 0.10328201 | E3: =FS!E7/(FS!E49+FS!E50+FS!E51+FS!E52+FS!E53+FS!E54) -> 0.1057257 | F3: =FS!F7/(FS!F49+FS!F50+FS!F51+FS!F52+FS!F53+FS!F54) -> 0.081144905 | G3: =FS!G7/(FS!G49+FS!G50+FS!G51+FS!G52+FS!G53+FS!G54) -> 0.074717288 | H3: =FS!I7/(FS!I49+FS!I50+FS!I51+FS!I52+FS!I53+FS!I54) -> 0.10748751 | I3: =FS!J7/(FS!J49+FS!J50+FS!J51+FS!J52+FS!J53+FS!J54) -> 0.13149674 | J3: =FS!K7/(FS!K49+FS!K50+FS!K51+FS!K52+FS!K53+FS!K54) -> 0.1142421 | K3: =FS!L7/(FS!L49+FS!L50+FS!L51+FS!L52+FS!L53+FS!L54) -> 0.11545382 | L3: =FS!M7/(FS!M49+FS!M50+FS!M51+FS!M52+FS!M53+FS!M54) -> 0.11603704
B4: Avg. cost on interest bearing funds | C4: =FS!C8/(FS!C64+FS!C65+FS!C66+FS!C67+FS!C68) -> 0.064837643 | D4: =FS!D8/(FS!D64+FS!D65+FS!D66+FS!D67+FS!D68) -> 0.064595781 | E4: =FS!E8/(FS!E64+FS!E65+FS!E66+FS!E67+FS!E68) -> 0.067518664 | F4: =FS!F8/(FS!F64+FS!F65+FS!F66+FS!F67+FS!F68) -> 0.048096509 | G4: =FS!G8/(FS!G64+FS!G65+FS!G66+FS!G67+FS!G68) -> 0.038326172 | H4: =FS!I8/(FS!I64+FS!I65+FS!I66+FS!I67+FS!I68) -> 0.063778484 | I4: =FS!J8/(FS!J64+FS!J65+FS!J66+FS!J67+FS!J68) -> 0.095531498 | J4: =FS!K8/(FS!K64+FS!K65+FS!K66+FS!K67+FS!K68) -> 0.090014943 | K4: =FS!L8/(FS!L64+FS!L65+FS!L66+FS!L67+FS!L68) -> 0.090526292 | L4: =FS!M8/(FS!M64+FS!M65+FS!M66+FS!M67+FS!M68) -> 0.091290321
B5: Net interest margin | C5: =FS!C9/(FS!C49+FS!C50+FS!C51+FS!C52+FS!C53+FS!C54) -> 0.038684441 | D5: =FS!D9/(FS!D49+FS!D50+FS!D51+FS!D52+FS!D53+FS!D54) -> 0.039742648 | E5: =FS!E9/(FS!E49+FS!E50+FS!E51+FS!E52+FS!E53+FS!E54) -> 0.039543682 | F5: =FS!F9/(FS!F49+FS!F50+FS!F51+FS!F52+FS!F53+FS!F54) -> 0.033264729 | G5: =FS!G9/(FS!G49+FS!G50+FS!G51+FS!G52+FS!G53+FS!G54) -> 0.037362719 | H5: =FS!I9/(FS!I49+FS!I50+FS!I51+FS!I52+FS!I53+FS!I54) -> 0.040920576 | I5: =FS!J9/(FS!J49+FS!J50+FS!J51+FS!J52+FS!J53+FS!J54) -> 0.035753876 | J5: =FS!K9/(FS!K49+FS!K50+FS!K51+FS!K52+FS!K53+FS!K54) -> 0.024431959 | K5: =FS!L9/(FS!L49+FS!L50+FS!L51+FS!L52+FS!L53+FS!L54) -> 0.024499099 | L5: =FS!M9/(FS!M49+FS!M50+FS!M51+FS!M52+FS!M53+FS!M54) -> 0.024604392
B6: Interest rate spread | C6: =C3-C4 -> 0.036889834 | D6: =D3-D4 -> 0.038686225 | E6: =E3-E4 -> 0.038207039 | F6: =F3-F4 -> 0.033048396 | G6: =G3-G4 -> 0.036391117 | H6: =H3-H4 -> 0.043709029 | I6: =I3-I4 -> 0.035965245 | J6: =J3-J4 -> 0.024227159 | ... L6: =L3-L4 -> 0.024746718
B7: Cost to income (operating) | C7: =FS!C23/FS!C16 -> 0.4112972 | D7: =FS!D23/FS!D16 -> 0.36825623 | E7: =FS!E23/FS!E16 -> 0.38597706 | F7: =FS!F23/FS!F16 -> 0.34227536 | G7: =FS!G23/FS!G16 -> 0.31686186 | H7: =FS!I23/FS!I16 -> 0.26553814 | I7: =FS!J23/FS!J16 -> 0.36014337 | J7: =FS!K23/FS!K16 -> 0.3938361 | K7: =FS!L23/FS!L16 -> 0.40024182 | L7: =FS!M23/FS!M16 -> 0.40865195
B8: Cost to income (with impairments) | C8: =(FS!C23+FS!C17)/FS!C6 -> 0.1847993 | D8: =(FS!D23+FS!D17)/FS!D6 -> 0.23428872 | E8: =(FS!E23+FS!E17)/FS!E6 -> 0.24848571 | F8: =(FS!F23+FS!F17)/FS!F6 -> 0.31376765 | G8: =(FS!G23+FS!G17)/FS!G6 -> 0.33479493 | H8: =(FS!I23+FS!I17)/FS!I6 -> 0.38591847 | I8: =(FS!J23/FS!J6) -> 0.12230364 | J8: =(FS!K23/FS!K6) -> 0.13311063 | K8: =(FS!L23/FS!L6) -> 0.13292398 | L8: =(FS!M23/FS!M6) -> 0.13444637
B9: Impairments/ Gross loans | C9: =Drivers!C315/Drivers!C311 -> 0.023682969 | D9: =Drivers!D315/Drivers!D311 -> 0.033792109 | E9: =Drivers!E315/Drivers!E311 -> 0.039557968 | F9: =Drivers!F315/Drivers!F311 -> 0.054093105 | G9: =Drivers!G315/Drivers!G311 -> 0.059681216 | H9: =Drivers!H315/Drivers!H311 -> 0.07276509 | I9: =Drivers!I315/Drivers!I311 -> 0.07148 | J9: =Drivers!J315/Drivers!J311 -> 0.0521 | ... L9: =Drivers!L315/Drivers!L311 -> 0.0412
B10: Net margin | C10: =FS!C30/FS!C6 -> 0.1438215 | D10: =FS!D30/FS!D6 -> 0.12790484 | E10: =FS!E30/FS!E6 -> 0.11556498 | F10: =FS!F30/FS!F6 -> 0.11243798 | G10: =FS!G30/FS!G6 -> 0.14840533 | H10: =FS!I30/FS!I6 -> 0.087020714 | I10: =FS!J30/FS!J6 -> 0.059137383 | J10: =FS!K30/FS!K6 -> 0.073978971 | K10: =FS!L30/FS!L6 -> 0.069279017 | L10: =FS!M30/FS!M6 -> 0.064732691
B11: ROE | C11: =FS!C30/FS!C82 -> 0.15272352 | D11: =FS!D30/FS!D82 -> 0.14812024 | E11: =FS!E30/FS!E82 -> 0.12807845 | F11: =FS!F30/FS!F82 -> 0.106163 | G11: =FS!G30/FS!G82 -> 0.14326114 | H11: =FS!I30/FS!I82 -> 0.11456626 | I11: =FS!J30/FS!J82 -> 0.087940259 | J11: =FS!K30/FS!K82 -> 0.10323137 | K11: =FS!L30/FS!L82 -> 0.1004223 | L11: =FS!M30/FS!M82 -> 0.096883779
B12: ROA | C12: =FS!C30/FS!C62 -> 0.014385023 | D12: =FS!D30/FS!D62 -> 0.013533348 | E12: =FS!E30/FS!E62 -> 0.012364174 | F12: =FS!F30/FS!F62 -> 0.0096946578 | G12: =FS!G30/FS!G62 -> 0.01224623 | H12: =FS!I30/FS!I62 -> 0.0097615306 | I12: =FS!J30/FS!J62 -> 0.0077457677 | J12: =FS!K30/FS!K62 -> 0.009090326 | K12: =FS!L30/FS!L62 -> 0.0084873126 | L12: =FS!M30/FS!M62 -> 0.0079878194
B13: Equity/ total assets | C13: =FS!C82/FS!C62 -> 0.094189964 | D13: =FS!D82/FS!D62 -> 0.09136731 | E13: =FS!E82/FS!E62 -> 0.096535943 | F13: =FS!F82/FS!F62 -> 0.091318616 | G13: =FS!G82/FS!G62 -> 0.085481868 | H13: =FS!I82/FS!I62 -> 0.085204233 | I13: =FS!J82/FS!J62 -> 0.088079883 | J13: =FS!K82/FS!K62 -> 0.088057786 | K13: =FS!L82/FS!L62 -> 0.084516214 | L13: =FS!M82/FS!M62 -> 0.082447439
B14: Deposits / total assets | C14: =FS!C67/FS!C62 -> 0.7416981 | D14: =FS!D67/FS!D62 -> 0.75336136 | E14: =FS!E67/FS!E62 -> 0.75871332 | F14: =FS!F67/FS!F62 -> 0.72999671 | G14: =FS!G67/FS!G62 -> 0.74244872 | H14: =FS!I67/FS!I62 -> 0.79123865 | I14: =FS!J67/FS!J62 -> 0.81094232 | J14: =FS!K67/FS!K62 -> 0.80000087 | K14: =FS!L67/FS!L62 -> 0.79616944 | L14: =FS!M67/FS!M62 -> 0.79274167
B15: Cash / total assets | C15: =FS!C45/FS!C62 -> 0.029998966 | D15: =FS!D45/FS!D62 -> 0.033605236 | E15: =FS!E45/FS!E62 -> 0.038100321 | F15: =FS!F45/FS!F62 -> 0.029080932 | G15: =FS!G45/FS!G62 -> 0.034956233 | H15: =FS!I45/FS!I62 -> 0.060454583 | I15: =FS!J45/FS!J62 -> 0.039783431 | J15: =FS!K45/FS!K62 -> 0.037144427 | K15: =FS!L45/FS!L62 -> 0.047221241 | L15: =FS!M45/FS!M62 -> 0.044651353
B16: Gross income per employee | C16: =FS!C6/FS!C87 -> 23204.568 | D16: =FS!D6/FS!D87 -> 27781.419 | E16: =FS!E6/FS!E87 -> 29778.967 | F16: =FS!F6/FS!F87 -> 30050.705 | G16: =FS!G6/FS!G87 -> 32270.369 | H16: =FS!I6/FS!I87 -> 54752.381 | I16: =FS!J6/FS!J87 -> 67419.707 | J16: =FS!K6/FS!K87 -> 69462.011 | K16: =FS!L6/FS!L87 -> 78223.659 | L16: =FS!M6/FS!M87 -> 87193.49
B17: Dividend payout | F17: =FS!F36/FS!F34 -> 0.41401274 | G17: =FS!G36/FS!G34 -> 0.38639876 | H17: =FS!I36/FS!I34 -> 0.23425299 | I17: =FS!J36/FS!J34 -> 0.29871124 | J17: =FS!K36/FS!K34 -> 0.35 | K17: =FS!L36/FS!L34 -> 0.35 | L17: =FS!M36/FS!M34 -> 0.35
B20: Gross income per service centre | C20: =FS!C6/FS!C88 -> 412875.56 | D20: =FS!D6/FS!D88 -> 490025.25 | E20: =FS!E6/FS!E88 -> 525230.41 | F20: =FS!F6/FS!F88 -> 529499.7 | G20: =FS!G6/FS!G88 -> 570297.25 | H20: =FS!I6/FS!I88 -> 970197.04 | I20: =FS!J6/FS!J88 -> 1200602.1 | J20: =FS!K6/FS!K88 -> 1243125.3 | K20: =FS!L6/FS!L88 -> 1406892.8 | L20: =FS!M6/FS!M88 -> 1576021.9
B22: Net interest spread | F22: =F3-F4 -> 0.033048396 | G22: =G3-G4 -> 0.036391117 | H22: =H3-H4 -> 0.043709029 | I22: =I3-I4 -> 0.035965245 | J22: =J3-J4 -> 0.024227159 | K22: =K3-K4 -> 0.024927528 | L22: =L3-L4 -> 0.024746718

Sheet more Breakups
C1: 2017 | D1: 2018 | E1: 2019 | F1: 2020 | G1: 2021 | H1: 2022
B4: Interest income from government securities
B5: From Sri Lanka | C5: 22331944 | D5: 20458655 | E5: 23158214 | F5: 31523186 | G5: 46873585 | H5: 67938881
B6: Securities purchased under resale agreements | C6: 81635 | D6: 423571 | E6: 1629021 | F6: 618309 | G6: 363247 | H6: 213978
B7: Financial assets recognised through profit or loss | C7: 296520 | D7: 219287 | E7: 277760 | F7: 662961 | G7: 418180 | H7: 432506
B8: Financial assets at amortised cost – Debt and other financial instruments | C8: 6603815 | D8: 5337755 | E8: 6160065 | F8: 12188371 | G8: 24057370 | H8: 48296686
B9: Financial assets measured at fair value through other comprehensive income | C9: 15349974 | D9: 14478042 | E9: 15091368 | F9: 18053545 | G9: 22034788 | H9: 18995711
B11: From Bangladesh | C11: 1003916 | D11: 727417 | E11: 1318173 | F11: 1823578 | G11: 1419812 | H11: 3285610
B12: Securities purchased under resale agreements | C12: 57518 | D12: 85045 | E12: 277881 | F12: 218464 | G12: 12151 | H12: 919605
B13: Financial assets recognised through profit or loss | C13: 148381 | D13: 47875 | E13: 129265 | F13: 1133464 | G13: 515828 | H13: 846747
B14: Financial assets at amortised cost – Debt and other financial instruments | C14: 798017 | D14: 594497 | E14: 911027 | F14: 471650 | G14: 891833 | H14: 1519258
B16: Maldives
B17: Financial assets at amortised cost – Debt and other financial instruments | C17: 156598 | D17: 201931 | E17: 247379 | F17: 303081 | G17: 520270 | H17: 1226004
B19: Check | C19: =SUM(C6:C9)-C5+SUM(C12:C14)-C11 -> 0 | D19: =SUM(D6:D9)-D5+SUM(D12:D14)-D11 -> 0 | E19: =SUM(E6:E9)-E5+SUM(E12:E14)-E11 -> 0 | F19: =SUM(F6:F9)-F5+SUM(F12:F14)-F11 -> 0 | G19: =SUM(G6:G9)-G5+SUM(G12:G14)-G11 -> 0 | H19: =SUM(H6:H9)-H5+SUM(H12:H14)-H11 -> 0
B20: Check | C20: =(C8+C14+C17)-Drivers!C17 -> -953688 | D20: =(D8+D14+D17)-Drivers!D17 -> -694488 | E20: =(E8+E14+E17)-Drivers!E17 -> -501092 | F20: =(F8+F14+F17)-Drivers!F17 -> -231749 | G20: =(G8+G14+G17)-Drivers!G17 -> -481994 | H20: =(H8+H14+H17)-Drivers!H17 -> -708947
B31: GROSS loans and advances to other customers
B32: (LKR '000 except per share data) | C32: 2017 | D32: 2018 | E32: 2019 | F32: 2020 | G32: 2021 | H32: 2022
B33: By currency
B34: Sri Lankan Rupee | C34: 600058048 | D34: 692648484 | E34: 694387671 | F34: 714427226 | G34: 824624056 | H34: 842120414
B35: United States Dollar | C35: 113192698 | D35: 137588618 | E35: 152785345 | F35: 146750563 | G35: 169120449 | H35: 228254025
B36: Great Britain Pound | C36: 892245 | D36: 952806 | E36: 1297284 | F36: 1512981 | G36: 1369259 | H36: 2307564
B37: Euro | C37: 1500772 | D37: 1850804 | E37: 6671660 | F37: 9548883 | G37: 5507223 | H37: 6239416
B38: Australian Dollar | C38: 690992 | D38: 611436 | E38: 609115 | F38: 708584 | G38: 502605 | H38: 721089
B39: Japanese Yen | C39: 135765 | D39: 176039 | E39: 286695 | F39: 187489 | G39: 175531 | H39: 252705
B40: Singapore dollar | C40: 5504 | D40: 0 | E40: 2512 | F40: 0 | G40: 0 | H40: 0
B41: Bangladesh Taka | C41: 43164009 | D41: 62142187 | E41: 71252778 | F41: 84659542 | G41: 89272959 | H41: 157652152
B42: Maldivian Rufiyaa | C42: 737167 | D42: 1909104 | E42: 3141714 | F42: 3611052 | G42: 4074842 | H42: 8074579
B43: Others | C43: 76737 | D43: 76318 | E43: 302617 | F43: 452798 | G43: 283958 | H43: 548271
C44: =SUM(C34:C43) -> 760453937 | D44: =SUM(D34:D43) -> 897955796 | E44: =SUM(E34:E43) -> 930737391 | F44: =SUM(F34:F43) -> 961859118 | G44: =SUM(G34:G43) -> 1094930882 | H44: =SUM(H34:H43) -> 1246170215
B46: GROSS loans and advances to other customers
B47: By industry
B48: Agriculture and fishing | C48: 71041888 | D48: 84677466 | E48: 68775119 | F48: 78617259 | G48: 93304092 | H48: 126475449 | I48: =H48/$H$63 -> 0.10149131
B49: Arts, entertainment and recreation | D49: 949302 | E49: 1118938 | F49: 1288474 | G49: 1172974 | H49: 1488736 | I49: =H49/$H$63 -> 0.001194649
B50: Construction | C50: 106784977 | D50: 40689218 | E50: 45439269 | F50: 46454293 | G50: 56370508 | H50: 54627371 | I50: =H50/$H$63 -> 0.043836203
B51: Consumption and other | D51: 176273517 | E51: 201412039 | F51: 216286919 | G51: 168260117 | H51: 129274363 | I51: =H51/$H$63 -> 0.10373732
B52: Education | C52: 64040605 | D52: 2670021 | E52: 3225133 | F52: 3470636 | G52: 4295475 | H52: 3774937 | I52: =H52/$H$63 -> 0.0030292306
B53: Financial services | C53: 46764237 | D53: 40046006 | E53: 35777329 | F53: 36023186 | G53: 70326837 | H53: 95254707 | I53: =H53/$H$63 -> 0.076437958
B54: Healthcare, social services and support services | D54: 18546251 | E54: 18605625 | F54: 18480398 | G54: 26354594 | H54: 24631507 | I54: =H54/$H$63 -> 0.019765765
B55: Information technology and communication services | C55: 17479610 | D55: 12835806 | E55: 11403418 | F55: 11633615 | G55: 15155899 | H55: 17387197 | I55: =H55/$H$63 -> 0.013952506
B56: Infrastructure development | C56: 20886155 | D56: 19215514 | E56: 17083131 | F56: 17421563 | G56: 26786632 | H56: 33981732 | I56: =H56/$H$63 -> 0.027268933
B57: Lending to overseas entities | D57: 85552523 | E57: 108985813 | F57: 129398136 | G57: 144737204 | H57: 208063238 | I57: =H57/$H$63 -> 0.16696213
B58: Manufacturing | C58: 115028848 | D58: 103027652 | E58: 123625669 | F58: 122921837 | G58: 147215372 | H58: 152676544 | I58: =H58/$H$63 -> 0.12251661
B59: Professional, scientific, and technical activities | C59: 138916147 | D59: 23318540 | E59: 23782598 | F59: 26000516 | G59: 26850133 | H59: 27476630 | I59: =H59/$H$63 -> 0.022048858
B60: Tourism | C60: 47671546 | D60: 60387096 | E60: 62811790 | F60: 66751110 | G60: 68495166 | H60: 86703188 | I60: =H60/$H$63 -> 0.069575718
B61: Transport and storage | C61: 17190601 | D61: 11480382 | E61: 12906113 | F61: 13055953 | G61: 20968768 | H61: 22594696 | I61: =H61/$H$63 -> 0.018131308
B62: Wholesale and retail trade | C62: 114649323 | D62: 218286502 | E62: 195785407 | F62: 174055223 | G62: 224637111 | H62: 261759920 | I62: =H62/$H$63 -> 0.2100515
C63: =SUM(C48:C62) -> 760453937 | D63: =SUM(D48:D62) -> 897955796 | E63: =SUM(E48:E62) -> 930737391 | F63: =SUM(F48:F62) -> 961859118 | G63: =SUM(G48:G62) -> 1094930882 | H63: =SUM(H48:H62) -> 1246170215
B65: Check | C65: =IF(C63=Drivers!C305,"OK","FLAG") -> OK | D65: =IF(D63=Drivers!D305,"OK","FLAG") -> OK | E65: =IF(E63=Drivers!E305,"OK","FLAG") -> OK | F65: =IF(F63=Drivers!F305,"OK","FLAG") -> OK | G65: =IF(G63=Drivers!G305,"OK","FLAG") -> OK | H65: =IF(H63=Drivers!H305,"OK","FLAG") -> OK
B69: Financial assets at amortised cost – debt and other financial instruments
B72: Bogawantalawa Tea Estate PLC | G72: 80317 | H72: 80317
B73: MTD Walkers PLC | G73: 152870 | H73: 152870
B74: Singer Finance (Lanka) PLC | G74: 328529 | H74: 328529
B75: Ceylon Electricity Board | G75: 5333014 | H75: 5333014
B76: People's Leasing & Finance PLC | G76: 626823 | H76: 626823
B80: Financial liabilities at amortised cost – due to depositors | C80: 857269981 | D80: 994370875 | E80: 1068982587 | F80: 1286616399 | G80: 1472640456 | H80: 1977743661
B82: Deposits
B83: By currency
B84: Sri Lanka Rupee | G84: 1063799085 | H84: 1243427990 | J84: =H84/$H$92 -> 0.62871039
B85: United States Dollar | G85: 249019760 | H85: 473669803 | J85: =H85/$H$92 -> 0.2395001
B86: Great Britain Pound | G86: 10899892 | H86: 16735916 | J86: =H86/$H$92 -> 0.008462126
B87: Euro | G87: 9627165 | H87: 14773285 | J87: =H87/$H$92 -> 0.0074697673
B88: Australian Dollar | G88: 6520439 | H88: 9739962 | J88: =H88/$H$92 -> 0.0049247848
B89: Bangladesh Taka | G89: 119743557 | H89: 190211877 | J89: =H89/$H$92 -> 0.096176204
B90: Maldivian Rufiyaa | G90: 11029795 | H90: 26095923 | J90: =H90/$H$92 -> 0.013194795
B91: Other currencies | G91: 2000763 | H91: 3088905 | J91: =H91/$H$92 -> 0.0015618328
C92: =SUM(C84:C91) -> 0 | D92: =SUM(D84:D91) -> 0 | E92: =SUM(E84:E91) -> 0 | F92: =SUM(F84:F91) -> 0 | G92: =SUM(G84:G91) -> 1472640456 | H92: =SUM(H84:H91) -> 1977743661 | J92: =H92/$H$92 -> 1
B94: By institution/customers
B95: Deposits from banks | G95: 9496875 | H95: 8063822
B96: Deposits from finance companies | G96: 4503781 | H96: 5446405
B97: Deposits from other customers | G97: 1458639800 | H97: 1964233434
B99: Check | C99: =SUM(C84:C91)-SUM(C95:C97)+C92-C80 -> -857269981 | D99: =SUM(D84:D91)-SUM(D95:D97)+D92-D80 -> -994370875 | E99: =SUM(E84:E91)-SUM(E95:E97)+E92-E80 -> -1068982587 | F99: =SUM(F84:F91)-SUM(F95:F97)+F92-F80 -> -1286616399 | G99: =SUM(G84:G91)-SUM(G95:G97)+G92-G80 -> 0 | H99: =SUM(H84:H91)-SUM(H95:H97)+H92-H80 -> 0
B102: Maturity profile - loans
B122: Loan portfolio by province

Sheet COMB N
B2: COMB | F2: COMB
B3: Date | C3: Price to Book Ratio | F3: Date | G3: Last Price
B4: 45183 | C4: 0.5878 | F4: 45183 | G4: 93 | K4: Date | L4: Price Earnings Ratio (P/E)
B5: 45182 | C5: 0.584 | F5: 45182 | G5: 91.5 | K5: 45302 | L5: 5.1872 | W5: Date | X5: Price to Book Ratio
B6: 45181 | C6: 0.577 | F6: 45181 | G6: 90.4 | K6: 45301 | L6: 5.2719 | W6: 45302 | X6: 0.5642
B7: 45180 | C7: 0.5776 | F7: 45180 | G7: 90.5 | K7: 45300 | L7: 5.3284 | W7: 45301 | X7: 0.5734
B8: 45177 | C8: 0.5923 | F8: 45177 | G8: 92.8 | K8: 45299 | L8: 5.368 | W8: 45300 | X8: 0.5796
B9: 45176 | C9: 0.5878 | F9: 45176 | G9: 92.1 | K9: 45296 | L9: 5.3793 | W9: 45299 | X9: 0.5839
B10: 45175 | C10: 0.5885 | F10: 45175 | G10: 92.2 | K10: 45295 | L10: 5.3963 | W10: 45296 | X10: 0.5851
B11: 45174 | C11: 0.6063 | F11: 45174 | G11: 95 | K11: 45294 | L11: 5.4189 | W11: 45295 | X11: 0.587
B12: 45173 | C12: 0.5955 | F12: 45173 | G12: 93.3 | K12: 45293 | L12: 5.4754 | W12: 45294 | X12: 0.5894
B13: 45170 | C13: 0.5642 | F13: 45170 | G13: 88.4 | K13: 45289 | L13: 5.3963 | W13: 45293 | X13: 0.5956
B14: 45169 | C14: 0.5527 | F14: 45169 | G14: 86.6 | K14: 45288 | L14: 5.3284 | W14: 45289 | X14: 0.587
B15: 45167 | C15: 0.5553 | F15: 45167 | G15: 87 | K15: 45287 | L15: 5.2606 | W15: 45288 | X15: 0.5796
B16: 45166 | C16: 0.5553 | F16: 45166 | G16: 87 | K16: 45282 | L16: 5.2493 | W16: 45287 | X16: 0.5722
B17: 45163 | C17: 0.5553 | F17: 45163 | G17: 87 | K17: 45281 | L17: 5.2663 | W17: 45282 | X17: 0.571
... B53: 45112 | C53: 0.5189 | F53: 45112 | G53: 81.3 | K53: 45231 | L53: 4.7351 | W53: 45232 | X53: 0.5194
B54: 45111 | C54: 4.5982 | D54: 4.5982 | F54: 45111 | G54: 80.9 | K54: 45230 | L54: 4.6447 | W54: 45231 | X54: 0.5151
B55: 45105 | C55: 0.4346 | F55: 45105 | G55: 68.1 | K55: 45229 | L55: 4.6843 | W55: 45230 | X55: 0.5052
B56: 45104 | C56: 0.4091 | F56: 45104 | G56: 67.7 | K56: 45226 | L56: 4.6956 | W56: 45229 | X56: 0.5095
B57: 45103 | C57: 0.4128 | F57: 45103 | G57: 68.3 | K57: 45225 | L57: 4.6447 | W57: 45226 | X57: 0.5108
B58: 45100 | C58: 0.3995 | F58: 45100 | G58: 66.1 | K58: 45224 | L58: 4.6843 | W58: 45225 | X58: 0.5052
B59: 45099 | C59: 0.3995 | F59: 45099 | G59: 66.1 | K59: 45223 | L59: 4.7973 | W59: 45224 | X59: 0.5095
B60: 45098 | C60: 0.4001 | F60: 45098 | G60: 66.2 | K60: 45222 | L60: 4.9047 | W60: 45223 | X60: 0.5218
B61: 45097 | C61: 0.3868 | F61: 45097 | G61: 64 | K61: 45219 | L61: 4.9047 | W61: 45222 | X61: 0.5335
B62: 45096 | C62: 0.3928 | F62: 45096 | G62: 65 | K62: 45218 | L62: 4.6165 | W62: 45219 | X62: 0.5335
B63: 45093 | C63: 0.3989 | F63: 45093 | G63: 66 | K63: 45217 | L63: 4.5487 | W63: 45218 | X63: 0.5022
B64: 45092 | C64: 0.4007 | F64: 45092 | G64: 66.3 | K64: 45216 | L64: 4.5656 | W64: 45217 | X64: 0.4948
B65: 45091 | C65: 0.3928 | F65: 45091 | G65: 65 | K65: 45215 | L65: 4.543 | W65: 45216 | X65: 0.4966
B66: 45090 | C66: 0.3692 | F66: 45090 | G66: 61.1 | K66: 45212 | L66: 4.7464 | W66: 45215 | X66: 0.4942
... B1168: 43354 | C1168: 1.0884 | F1168: 43354 | G1168: 105.22 | K1168: 43476 | L1168: 7.187 | W1168: 43479 | X1168: 0.9667
B1169: 43353 | C1169: 1.0884 | F1169: 43353 | G1169: 105.22 | W1169: 43476 | X1169: 0.965
B1170: 43350 | C1170: 1.0964 | F1170: 43350 | G1170: 105.99
B1171: 43349 | C1171: 1.0946 | F1171: 43349 | G1171: 105.82
B1172: 43348 | C1172: 1.0946 | F1172: 43348 | G1172: 105.82
B1173: 43347 | C1173: 1.0928 | F1173: 43347 | G1173: 105.64
B1174: 43346 | C1174: 1.0973 | F1174: 43346 | G1174: 106.07

Sheet charts 1
B2: INCOME STATEMENT (LKR Mn except per sahre data) | C2: =FS!F4 -> 2020 | D2: =FS!G4 -> 2021 | E2: =FS!I4 -> 2022 | F2: =FS!J4 -> 2023F | G2: =FS!K4 -> 2024F | H2: =FS!L4 -> 2025F | L2: Key data | M2: COMB.N | N2: COMB.X | Q2: Key financials (LKR Mn) | R2: =C33 -> 2020 | S2: =D33 -> 2021 | T2: =E33 -> 2022 | U2: =F33 -> 2023F | V2: =G33 -> 2024F | W2: =H33 -> 2025F
B3: =FS!B6 -> Gross income | C3: =FS!F6/1000 -> 151966.41 | D3: =FS!G6/1000 -> 163675.31 | E3: =FS!I6/1000 -> 280386.94 | F3: =FS!J6/1000 -> 348708.88 | G3: =FS!K6/1000 -> 362864.83 | H3: =FS!L6/1000 -> 412721.43 | L3: Historical returns | Q3: Gross income | R3: =C3 -> 151966.41 | S3: =D3 -> 163675.31 | T3: =E3 -> 280386.94 | U3: =F3 -> 348708.88 | V3: =G3 -> 362864.83 | W3: =H3 -> 412721.43
B4: =FS!B7 -> Interest income | C4: =FS!F7/1000 -> 124087.71 | D4: =FS!G7/1000 -> 132818.18 | E4: =FS!I7/1000 -> 222393.08 | F4: =FS!J7/1000 -> 305857.34 | G4: =FS!K7/1000 -> 295139.36 | H4: =FS!L7/1000 -> 337849.48 | L4: 1-year capital gain | M4: =M18/M24-1 -> 0.79841897 | N4: =N18/N24-1 -> 0.90274314 | Q4: =B6 -> Net interest income | R4: =C6 -> 50868.802 | S4: =D6 -> 66416.332 | T4: =E6 -> 84665.211 | U4: =F6 -> 83162.406 | V4: =G6 -> 63118.873 | W4: =H6 -> 71691.068
B5: =FS!B8 -> Less: Interest expense | C5: =FS!F8/1000 -> 73218.911 | D5: =FS!G8/1000 -> 66401.846 | E5: =FS!I8/1000 -> 137727.87 | F5: =FS!J8/1000 -> 222694.93 | G5: =FS!K8/1000 -> 232020.49 | H5: =FS!L8/1000 -> 266158.41 | L5: 1-year dividend yield | M5: =M23/M24 -> 0.088932806 | N5: =N23/N24 -> 0.11221945 | Q5: =B27 -> Profit for the year | R5: =C30 -> 17086.797 | S5: =D30 -> 24290.288 | T5: =E30 -> 24399.472 | U5: =F30 -> 20621.731 | V5: =G30 -> 26844.366 | W5: =H30 -> 28592.935
B6: =FS!B9 -> Net interest income | C6: =FS!F9/1000 -> 50868.802 | D6: =FS!G9/1000 -> 66416.332 | E6: =FS!I9/1000 -> 84665.211 | F6: =FS!J9/1000 -> 83162.406 | G6: =FS!K9/1000 -> 63118.873 | H6: =FS!L9/1000 -> 71691.068 | L6: 1-year total return | M6: =M4+M5 -> 0.88735178 | N6: =N4+N5 -> 1.0149626 | Q6: Loans and advances | R6: =C38 -> 910608.88 | S6: =D38 -> 1029584.1 | T6: =E38 -> 1155492.5 | U6: =F38 -> 1214948.7 | V6: =G38 -> 1426353 | W6: =H38 -> 1651207.9
B7: =FS!B10 -> Fee and commission income | C7: =FS!F10/1000 -> 11839.689 | D7: =FS!G10/1000 -> 15917.337 | E7: =FS!I10/1000 -> 26191.53 | F7: =FS!J10/1000 -> 30373.717 | G7: =FS!K10/1000 -> 35658.826 | H7: =FS!L10/1000 -> 41280.198 | L7: Beta | M7: 0.78 | N7: 0.78 | Q7: =B44 -> Total assets | R7: =C44 -> 1762496.2 | S7: =D44 -> 1983491.1 | T7: =E44 -> 2499553.9 | U7: =F44 -> 2662322.4 | V7: =G44 -> 2953069.7 | W7: =H44 -> 3368903.3
B8: =FS!B11 -> Less: Fee and commission expense | C8: =FS!F11/1000 -> 2018.014 | D8: =FS!G11/1000 -> 3675.143 | E8: =FS!I11/1000 -> 6022.429 | F8: =FS!J11/1000 -> 7593.4292 | G8: =FS!K11/1000 -> 8201.5299 | H8: =FS!L11/1000 -> 9494.4454 | L8: 1-year high | M8: =MAX('Price volume'!$E$4:$E$248) -> 105 | N8: =MAX('Price volume'!$S$4:$S$248) -> 88.8 | Q8: EPS (LKR) | R8: =C31 -> 15.7 | S8: =D31 -> 19.41 | T8: =E31 -> 19.21 | U8: =F31 -> 15.064716 | V8: =G31 -> 19.610515 | W8: =H31 -> 20.88789
B9: =FS!B12 -> Net fee and commission income | C9: =FS!F12/1000 -> 9821.675 | D9: =FS!G12/1000 -> 12242.194 | E9: =FS!I12/1000 -> 20169.101 | F9: =FS!J12/1000 -> 22780.287 | G9: =FS!K12/1000 -> 27457.296 | H9: =FS!L12/1000 -> 31785.752 | L9: 1-year low | M9: =MIN('Price volume'!$E$4:$E$248) -> 50.2 | N9: =MIN('Price volume'!$S$4:$S$248) -> 40.1 | Q9: NAVPS (LKR) | R9: =C56 -> 136.42 | S9: =D56 -> 140.24 | T9: =E56 -> 168.47 | U9: =F56 -> 174.69072 | V9: =G56 -> 193.3115 | W9: =H56 -> 211.22648
B10: =FS!B13 -> Net gains/(losses) from trading | C10: =FS!F13/1000 -> 1878.06 | D10: =FS!G13/1000 -> 1936.007 | E10: =FS!I13/1000 -> 35297.45 | F10: =FS!J13/1000 -> -16199.576 | G10: =FS!K13/1000 -> 1955.3671 | H10: =FS!L13/1000 -> 1974.9207 | L10: Valuation multiples | Q10: Net margin | R10: =Ratios!F10 -> 0.11243798 | S10: =Ratios!G10 -> 0.14840533 | T10: =Ratios!H10 -> 0.087020714 | U10: =Ratios!I10 -> 0.059137383 | V10: =Ratios!J10 -> 0.073978971 | W10: =Ratios!K10 -> 0.069279017
B11: =FS!B14 -> Net gains/(losses) from derecognition of financial assets | C11: =FS!F14/1000 -> 6390.197 | D11: =FS!G14/1000 -> 3001.574 | E11: =FS!I14/1000 -> 276.884 | F11: =FS!J14/1000 -> 3517.6933 | G11: =FS!K14/1000 -> 3693.578 | H11: =FS!L14/1000 -> 3878.2569 | L11: PE ratio | M11: =M18/Valuation!$B$63 -> 5.2059497 | N11: =N18/Valuation!$B$63 -> 4.3649886 | Q11: ROE | R11: =Ratios!F11 -> 0.106163 | S11: =Ratios!G11 -> 0.14326114 | T11: =Ratios!H11 -> 0.11456626 | U11: =Ratios!I11 -> 0.087940259 | V11: =Ratios!J11 -> 0.10323137 | W11: =Ratios!K11 -> 0.1004223
B12: =FS!B15 -> Net other operating income | C12: =FS!F15/1000 -> 7770.754 | D12: =FS!G15/1000 -> 10002.216 | E12: =FS!I15/1000 -> -3771.999 | F12: =FS!J15/1000 -> 25159.709 | G12: =FS!K15/1000 -> 26417.695 | H12: =FS!L15/1000 -> 27738.58 | L12: PB ratio | M12: =M18/Valuation!$B$53 -> 0.55931162 | N12: =N18/Valuation!$B$53 -> 0.46896128 | Q12: ROA | R12: =Ratios!F12 -> 0.0096946578 | S12: =Ratios!G12 -> 0.01224623 | T12: =Ratios!H12 -> 0.0097615306 | U12: =Ratios!I12 -> 0.0077457677 | V12: =Ratios!J12 -> 0.009090326 | W12: =Ratios!K12 -> 0.0084873126
B13: =FS!B16 -> Total operating income | C13: =FS!F16/1000 -> 76729.488 | D13: =FS!G16/1000 -> 93598.323 | E13: =FS!I16/1000 -> 136636.65 | F13: =FS!J16/1000 -> 118420.52 | G13: =FS!K16/1000 -> 122642.81 | H13: =FS!L16/1000 -> 137068.58 | L13: Per share data
B14: =FS!B17 -> Less: Impairment charges and other losses | C14: =FS!F17/1000 -> 21419.532 | D14: =FS!G17/1000 -> 25139.926 | E14: =FS!I17/1000 -> 71924.26 | F14: =FS!J17/1000 -> 35328.926 | G14: =FS!K17/1000 -> 30095.011 | H14: =FS!L17/1000 -> 34609.262 | L14: EPS (TTM) (LKR) | M14: =Valuation!$B$63 -> 17.48 | N14: =Valuation!$B$63 -> 17.48
B15: =FS!B18 -> Net operating income | C15: =FS!F18/1000 -> 55309.956 | D15: =FS!G18/1000 -> 68458.397 | E15: =FS!I18/1000 -> 64712.387 | F15: =FS!J18/1000 -> 83091.594 | G15: =FS!K18/1000 -> 92547.798 | H15: =FS!L18/1000 -> 102459.31 | L15: NAVPS (Sep23) (LKR) | M15: =Valuation!$B$53 -> 162.7 | N15: =Valuation!$B$53 -> 162.7
B16: =FS!B19 -> Less: Expenses | L16: DPS (2023) | M16: =M23 -> 4.5 | N16: =N23 -> 4.5
B17: =FS!B20 -> Personnel expenses | C17: =FS!F20/1000 -> 14992.748 | D17: =FS!G20/1000 -> 16799.212 | E17: =FS!I20/1000 -> 19788.283 | F17: =FS!J20/1000 -> 21767.111 | G17: =FS!K20/1000 -> 23943.822 | H17: =FS!L20/1000 -> 26338.205
B18: =FS!B21 -> Depreciation and amortisation | C18: =FS!F21/1000 -> 3102.695 | D18: =FS!G21/1000 -> 3220.066 | E18: =FS!I21/1000 -> 3598.371 | F18: =FS!J21/1000 -> 4116.991 | G18: =FS!K21/1000 -> 4240.2272 | H18: =FS!L21/1000 -> 4381.8335 | L18: currrent price | M18: =Valuation!B97 -> 91 | N18: =Valuation!B102 -> 76.3
B19: =FS!B22 -> Other operating expenses | C19: =FS!F22/1000 -> 8167.17 | D19: =FS!G22/1000 -> 9638.461 | E19: =FS!I22/1000 -> 12895.587 | F19: =FS!J22/1000 -> 16764.263 | G19: =FS!K22/1000 -> 20117.116 | H19: =FS!L22/1000 -> 24140.539
B20: =FS!B23 -> Total operating expenses | C20: =FS!F23/1000 -> 26262.613 | D20: =FS!G23/1000 -> 29657.739 | E20: =FS!I23/1000 -> 36282.241 | F20: =FS!J23/1000 -> 42648.365 | G20: =FS!K23/1000 -> 48301.165 | H20: =FS!L23/1000 -> 54860.577 | L20: dividend
B21: =FS!B24 -> Operating profit before taxes on financial services | C21: =FS!F24/1000 -> 29047.343 | D21: =FS!G24/1000 -> 38800.658 | E21: =FS!I24/1000 -> 28430.146 | F21: =FS!J24/1000 -> 40443.229 | G21: =FS!K24/1000 -> 44246.633 | H21: =FS!L24/1000 -> 47598.738
B22: =FS!B25 -> Less: Taxes on financial services | C22: =FS!F25/1000 -> 4531.381 | D22: =FS!G25/1000 -> 5845.23 | E22: =FS!I25/1000 -> 3921.381 | F22: =FS!J25/1000 -> 4893.7174 | G22: =FS!K25/1000 -> 5902.7872 | H22: =FS!L25/1000 -> 6756.9895
B23: =FS!B26 -> Operating profit after taxes on financial services | C23: =FS!F26/1000 -> 24515.962 | D23: =FS!G26/1000 -> 32955.428 | E23: =FS!I26/1000 -> 24508.765 | F23: =FS!J26/1000 -> 35549.511 | G23: =FS!K26/1000 -> 38343.846 | H23: =FS!L26/1000 -> 40841.748 | L23: Scirpt dividend | M23: 4.5 | N23: 4.5
B24: =FS!B27 -> Share of profit/(loss) of associate, net of tax | C24: =FS!F27/1000 -> 3.898 | D24: =FS!G27/1000 -> 1.896 | E24: =FS!I27/1000 -> -3.727 | F24: =FS!J27/1000 -> 5.1973333 | G24: =FS!K27/1000 -> 5.2493067 | H24: =FS!L27/1000 -> 5.3017997 | L24: 1-year ago price | M24: ='Price volume'!$E$248 -> 50.6 | N24: ='Price volume'!$S$248 -> 40.1
B25: =FS!B28 -> Profit before tax | C25: =FS!F28/1000 -> 24519.86 | D25: =FS!G28/1000 -> 32957.324 | E25: =FS!I28/1000 -> 24505.038 | F25: =FS!J28/1000 -> 35554.709 | G25: =FS!K28/1000 -> 38349.095 | H25: =FS!L28/1000 -> 40847.05
B26: =FS!B29 -> Less: Income tax expense/(reversal) | C26: =FS!F29/1000 -> 7433.063 | D26: =FS!G29/1000 -> 8667.036 | E26: =FS!I29/1000 -> 105.566 | F26: =FS!J29/1000 -> 14932.978 | G26: =FS!K29/1000 -> 11504.728 | H26: =FS!L29/1000 -> 12254.115
B27: =FS!B30 -> Profit for the year | C27: =FS!F30/1000 -> 17086.797 | D27: =FS!G30/1000 -> 24290.288 | E27: =FS!I30/1000 -> 24399.472 | F27: =FS!J30/1000 -> 20621.731 | G27: =FS!K30/1000 -> 26844.366 | H27: =FS!L30/1000 -> 28592.935
B28: =FS!B31 -> Profit attributable to: Equity holders of the Bank | C28: =FS!F31/1000 -> 16939.95 | D28: =FS!G31/1000 -> 24062.469 | E28: =FS!I31/1000 -> 23811.914 | F28: =FS!J31/1000 -> 19796.862 | G28: =FS!K31/1000 -> 25770.592 | H28: =FS!L31/1000 -> 27449.218 | L28: Shareholding details
B29: =FS!B32 -> Non-controlling interest | C29: =FS!F32/1000 -> 146.847 | D29: =FS!G32/1000 -> 227.819 | E29: =FS!I32/1000 -> 587.558 | F29: =FS!J32/1000 -> 824.86924 | G29: =FS!K32/1000 -> 1073.7747 | H29: =FS!L32/1000 -> 1143.7174 | L29: No of shares (Mn)-voting | N29: =Drivers!I570/1000000 -> 1236.5254
B30: =FS!B33 -> Profit for the year | C30: =FS!F33/1000 -> 17086.797 | D30: =FS!G33/1000 -> 24290.288 | E30: =FS!I33/1000 -> 24399.472 | F30: =FS!J33/1000 -> 20621.731 | G30: =FS!K33/1000 -> 26844.366 | H30: =FS!L33/1000 -> 28592.935 | L30: No of shares (Mn)-non voting | N30: =Drivers!I578/1000000 -> 77.595733
B31: Earnings Per Share (LKR) | C31: =FS!F34 -> 15.7 | D31: =FS!G34 -> 19.41 | E31: =FS!I34 -> 19.21 | F31: =FS!J34 -> 15.064716 | G31: =FS!K34 -> 19.610515 | H31: =FS!L34 -> 20.88789 | L31: Total no of shares (Mn) | N31: =N29+N30 -> 1314.1211
L32: MCAP (Mn)-voting | N32: 113884
B33: BALANCE SHEET (LKR Mn except per sahre data) | C33: =C2 -> 2020 | D33: =D2 -> 2021 | E33: =E2 -> 2022 | F33: =F2 -> 2023F | G33: =G2 -> 2024F | H33: =H2 -> 2025F | L33: MCAP (Mn)-non voting | N33: 6161
B34: Assets | L34: Public holding-voting | N34: 0.9981
B35: Cash and cash equivalents | C35: =FS!F45/1000 -> 51255.03 | D35: =FS!G45/1000 -> 69335.379 | E35: =FS!I45/1000 -> 151109.49 | F35: =FS!J45/1000 -> 105916.32 | G35: =FS!K45/1000 -> 109690.08 | H35: =FS!L45/1000 -> 159083.79 | L35: Public holding-non voting | N35: 0.9988
B36: Balances with banks and derivatives | C36: =(FS!F46+FS!F47+FS!F48+FS!F49)/1000 -> 134417.32 | D36: =(FS!G46+FS!G47+FS!G48+FS!G49)/1000 -> 75521.784 | E36: =(FS!I46+FS!I47+FS!I48+FS!I49)/1000 -> 184542.46 | F36: =(FS!J46+FS!J47+FS!J48+FS!J49)/1000 -> 135653.99 | G36: =(FS!K46+FS!K47+FS!K48+FS!K49)/1000 -> 182279.86 | H36: =(FS!L46+FS!L47+FS!L48+FS!L49)/1000 -> 200873.78 | L36: Top 5 shareholders - COMB.N
B37: Financial assets through profit or loss (fair value) | C37: =FS!F50/1000 -> 35189.471 | D37: =FS!G50/1000 -> 23436.123 | E37: =FS!I50/1000 -> 24873.057 | F37: =FS!J50/1000 -> 98932.873 | G37: =FS!K50/1000 -> 155960.06 | H37: =FS!L50/1000 -> 171556.07 | L37: DFCC Bank PLC A/C 1 | N37: 0.1211
B38: Loans and advances to other customers | C38: =(FS!F52+FS!F51)/1000 -> 910608.88 | D38: =(FS!G52+FS!G51)/1000 -> 1029584.1 | E38: =(FS!I52+FS!I51)/1000 -> 1155492.5 | F38: =(FS!J52+FS!J51)/1000 -> 1214948.7 | G38: =(FS!K52+FS!K51)/1000 -> 1426353 | H38: =(FS!L52+FS!L51)/1000 -> 1651207.9 | L38: Mr.Y. S. H. I. Silva | N38: 0.0989
B39: Debt and other financial instruments | C39: =FS!F53/1000 -> 302059.53 | D39: =FS!G53/1000 -> 385390.6 | E39: =FS!I53/1000 -> 761650.23 | F39: =FS!J53/1000 -> 709291.12 | G39: =FS!K53/1000 -> 668358.32 | H39: =FS!L53/1000 -> 737754.18 | L39: Employees' Provident Fund | N39: 0.0861
B40: Financial assets through other comprehensive income | C40: =FS!F54/1000 -> 278716.79 | D40: =FS!G54/1000 -> 335953.8 | E40: =FS!I54/1000 -> 118652.26 | F40: =FS!J54/1000 -> 296954.73 | G40: =FS!K54/1000 -> 326650.2 | H40: =FS!L54/1000 -> 359315.22 | L40: Mr. D. P. Pieris | N40: 0.0771
B41: Investment in associate | C41: =(FS!F55+FS!F56)/1000 -> 64.155 | D41: =(FS!G55+FS!G56)/1000 -> 60.428 | E41: =(FS!I55+FS!I56)/1000 -> 55.302 | F41: =(FS!J55+FS!J56)/1000 -> 55.302 | G41: =(FS!K55+FS!K56)/1000 -> 55.302 | H41: =(FS!L55+FS!L56)/1000 -> 55.302 | L41: Int. Finance Corporation | N41: 0.0711
B42: PPE and intangible assets | C42: =(FS!F57+FS!F58+FS!F59)/1000 -> 27254.262 | D42: =(FS!G57+FS!G58+FS!G59)/1000 -> 27089.673 | E42: =(FS!I57+FS!I58+FS!I59)/1000 -> 31640.157 | F42: =(FS!J57+FS!J58+FS!J59)/1000 -> 33001.756 | G42: =(FS!K57+FS!K58+FS!K59)/1000 -> 34328.752 | H42: =(FS!L57+FS!L58+FS!L59)/1000 -> 38181.843 | L42: Top 5 shareholders - COMB.X
B43: Deferred tax and other assets | C43: =(FS!F60+FS!F61)/1000 -> 22930.719 | D43: =(FS!G60+FS!G61)/1000 -> 37119.282 | E43: =(FS!I60+FS!I61)/1000 -> 71538.424 | F43: =(FS!J60+FS!J61)/1000 -> 67567.647 | G43: =(FS!K60+FS!K61)/1000 -> 49394.112 | H43: =(FS!L60+FS!L61)/1000 -> 50875.166 | L43: Employees' Trust Fund Board | N43: 0.0778
B44: Total assets | C44: =FS!F62/1000 -> 1762496.2 | D44: =FS!G62/1000 -> 1983491.1 | E44: =FS!I62/1000 -> 2499553.9 | F44: =FS!J62/1000 -> 2662322.4 | G44: =FS!K62/1000 -> 2953069.7 | H44: =FS!L62/1000 -> 3368903.3 | L44: Akbar Brothers (Pvt) Ltd. | N44: 0.0485
B45: Liabilities | L45: GF Capital Global Limited | N45: 0.0259
B46: Liabilities Due to banks and derivatives | C46: =(FS!F64+FS!F65+FS!F66)/1000 -> 181160.84 | D46: =(FS!G64+FS!G65+FS!G66)/1000 -> 227318.25 | E46: =(FS!I64+FS!I65+FS!I66)/1000 -> 165578.27 | F46: =(FS!J64+FS!J65+FS!J66)/1000 -> 148644.19 | G46: =(FS!K64+FS!K65+FS!K66)/1000 -> 179897.31 | H46: =(FS!L64+FS!L65+FS!L66)/1000 -> 205072.22 | L46: Mr. M. F. Hashim | N46: 0.018
B47: Financial liabilities at amortised cost – due to depositors | C47: =FS!F67/1000 -> 1286616.4 | D47: =FS!G67/1000 -> 1472640.5 | E47: =FS!I67/1000 -> 1977743.7 | F47: =FS!J67/1000 -> 2158989.9 | G47: =FS!K67/1000 -> 2362458.3 | H47: =FS!L67/1000 -> 2682217.8 | L47: M. J. F. Exports (Pvt) Ltd | N47: 0.0171
B48: Financial liabilities at amortised cost – other borrowings | C48: =FS!F68/1000 -> 54555.933 | D48: =FS!G68/1000 -> 32587.051 | E48: =FS!I68/1000 -> 16150.356 | F48: =FS!J68/1000 -> 23481.198 | G48: =FS!K68/1000 -> 35221.797 | H48: =FS!L68/1000 -> 52832.696
B49: Tax and other liabilities | C49: =(FS!F69+FS!F70+FS!F71+FS!F73)/1000 -> 79214.272 | D49: =(FS!G69+FS!G70+FS!G71+FS!G73)/1000 -> 81392.862 | E49: =(FS!I69+FS!I70+FS!I71+FS!I73)/1000 -> 127109.04 | F49: =(FS!J69+FS!J70+FS!J71+FS!J73)/1000 -> 96710.066 | G49: =(FS!K69+FS!K70+FS!K71+FS!K73)/1000 -> 115451.51 | H49: =(FS!L69+FS!L70+FS!L71+FS!L73)/1000 -> 144053.57
B50: Total liabilities | C50: =FS!F74/1000 -> 1601547.4 | D50: =FS!G74/1000 -> 1813938.6 | E50: =FS!I74/1000 -> 2286581.3 | F50: =FS!J74/1000 -> 2427825.4 | G50: =FS!K74/1000 -> 2693028.9 | H50: =FS!L74/1000 -> 3084176.3
B51: Equity
B52: Stated capital | C52: =FS!F76/1000 -> 52187.747 | D52: =FS!G76/1000 -> 54566.957 | E52: =FS!I76/1000 -> 58149.621 | F52: =FS!J76/1000 -> 62948.003 | G52: =FS!K76/1000 -> 69242.803 | H52: =FS!L76/1000 -> 72704.943
B53: Reserves and non-controlling interest | C53: =(FS!F77+FS!F78+FS!F79+FS!F81)/1000 -> 108760.96 | D53: =(FS!G77+FS!G78+FS!G79+FS!G81)/1000 -> 114985.57 | E53: =(FS!I77+FS!I78+FS!I79+FS!I81)/1000 -> 154822.95 | F53: =(FS!J77+FS!J78+FS!J79+FS!J81)/1000 -> 171549.04 | G53: =(FS!K77+FS!K78+FS!K79+FS!K81)/1000 -> 190797.98 | H53: =(FS!L77+FS!L78+FS!L79+FS!L81)/1000 -> 212022.01
B54: Total equity | C54: =FS!F82/1000 -> 160948.71 | D54: =FS!G82/1000 -> 169552.53 | E54: =FS!I82/1000 -> 212972.57 | F54: =FS!J82/1000 -> 234497.04 | G54: =FS!K82/1000 -> 260040.78 | H54: =FS!L82/1000 -> 284726.95
B55: Total liabilities and equity | C55: =FS!F83/1000 -> 1762496.2 | D55: =FS!G83/1000 -> 1983491.1 | E55: =FS!I83/1000 -> 2499553.9 | F55: =FS!J83/1000 -> 2662322.4 | G55: =FS!K83/1000 -> 2953069.7 | H55: =FS!L83/1000 -> 3368903.3
B56: Net Asset Value Per Share (LKR) | C56: =FS!F85 -> 136.42 | D56: =FS!G85 -> 140.24 | E56: =FS!I85 -> 168.47 | F56: =FS!J85 -> 174.69072 | G56: =FS!K85 -> 193.3115 | H56: =FS!L85 -> 211.22648
B57: Memorandum information

Sheet chart 2
C4: LKR Bn | D4: 2019 | E4: =D4+1 -> 2020 | F4: =E4+1 -> 2021 | G4: =F4+1 -> 2022 | H4: =FS!J4 -> 2023F | I4: =FS!K4 -> 2024F | J4: =FS!L4 -> 2025F | K4: =FS!M4 -> 2026F
C5: Loans and advanves to customers (LHS) (LKR Bn) | D5: =FS!E52/1000000 -> 893.91931 | E5: =FS!F52/1000000 -> 909.82917 | F5: =FS!G52/1000000 -> 1029.5841 | G5: =FS!I52/1000000 -> 1155.4925 | H5: =FS!J52/1000000 -> 1214.9487 | I5: =FS!K52/1000000 -> 1426.353 | J5: =FS!L52/1000000 -> 1651.2079 | K5: =FS!M52/1000000 -> 1908.0432
C6: Growth YoY (%) (RHS) | D6: =FS!E52/FS!D52-1 -> 0.030321544 | E6: =FS!F52/FS!E52-1 -> 0.017797871 | F6: =FS!G52/FS!F52-1 -> 0.1316235 | G6: =FS!I52/FS!G52-1 -> 0.1222906 | H6: =FS!J52/FS!I52-1 -> 0.051455235 | I6: =FS!K52/FS!J52-1 -> 0.17400271 | J6: =FS!L52/FS!K52-1 -> 0.15764321 | K6: =FS!M52/FS!L52-1 -> 0.15554391
E26: SDFR | F26: SLFR | L26: AWPR | M26: AWDR | N26: Spread
C27: 2019 | D27: 43466 | E27: 0.08 | F27: 0.09 | K27: 43466 | L27: 0.1205 | M27: 0.0885 | N27: =L27-M27 -> 0.032
D28: 43497 | E28: 0.08 | F28: 0.09 | K28: 43497 | L28: 0.123 | M28: 0.0888 | N28: =L28-M28 -> 0.0342
D29: 43525 | E29: 0.08 | F29: 0.09 | K29: 43525 | L29: 0.1223 | M29: 0.0898 | N29: =L29-M29 -> 0.0325
D30: 43556 | E30: 0.08 | F30: 0.09 | K30: 43556 | L30: 0.1207 | M30: 0.0897 | N30: =L30-M30 -> 0.031
D31: 43586 | E31: 0.075 | F31: 0.085 | K31: 43586 | L31: 0.1201 | M31: 0.09 | N31: =L31-M31 -> 0.0301
D32: 43617 | E32: 0.075 | F32: 0.085 | K32: 43617 | L32: 0.1145 | M32: 0.0894 | N32: =L32-M32 -> 0.0251
D33: 43647 | E33: 0.075 | F33: 0.085 | K33: 43647 | L33: 0.1093 | M33: 0.0888 | N33: =L33-M33 -> 0.0205
D34: 43678 | E34: 0.07 | F34: 0.08 | K34: 43678 | L34: 0.1069 | M34: 0.0873 | N34: =L34-M34 -> 0.0196
D35: 43709 | E35: 0.07 | F35: 0.08 | K35: 43709 | L35: 0.1057 | M35: 0.0851 | N35: =L35-M35 -> 0.0206
D36: 43739 | E36: 0.07 | F36: 0.08 | K36: 43739 | L36: 0.1042 | M36: 0.0837 | N36: =L36-M36 -> 0.0205
D37: 43770 | E37: 0.07 | F37: 0.08 | K37: 43770 | L37: 0.1021 | M37: 0.0827 | N37: =L37-M37 -> 0.0194
D38: 43800 | E38: 0.07 | F38: 0.08 | K38: 43800 | L38: 0.1 | M38: 0.082 | N38: =L38-M38 -> 0.018
C39: 2020 | D39: 43831 | E39: 0.065 | F39: 0.075 | K39: 43831 | L39: 0.0968 | M39: 0.0814 | N39: =L39-M39 -> 0.0154
D40: 43862 | E40: 0.065 | F40: 0.075 | K40: 43862 | L40: 0.0951 | M40: 0.0806 | N40: =L40-M40 -> 0.0145
D41: 43891 | E41: 0.0625 | F41: 0.0725 | K41: 43891 | L41: 0.0935 | M41: 0.079 | N41: =L41-M41 -> 0.0145
D42: 43922 | E42: 0.06 | F42: 0.07 | K42: 43922 | L42: 0.0938 | M42: 0.0777 | N42: =L42-M42 -> 0.0161
D43: 43952 | E43: 0.055 | F43: 0.065 | K43: 43952 | L43: 0.0928 | M43: 0.0757 | N43: =L43-M43 -> 0.0171
D44: 43983 | E44: 0.055 | F44: 0.065 | K44: 43983 | L44: 0.0878 | M44: 0.0738 | N44: =L44-M44 -> 0.014
D45: 44013 | E45: 0.045 | F45: 0.055 | K45: 44013 | L45: 0.0779 | M45: 0.0716 | N45: =L45-M45 -> 0.0063
D46: 44044 | E46: 0.045 | F46: 0.055 | K46: 44044 | L46: 0.0701 | M46: 0.0674 | N46: =L46-M46 -> 0.0027
D47: 44075 | E47: 0.045 | F47: 0.055 | K47: 44075 | L47: 0.0642 | M47: 0.0644 | N47: =L47-M47 -> -0.0002
D48: 44105 | E48: 0.045 | F48: 0.055 | K48: 44105 | L48: 0.061 | M48: 0.0623 | N48: =L48-M48 -> -0.0013
D49: 44136 | E49: 0.045 | F49: 0.055 | K49: 44136 | L49: 0.0595 | M49: 0.0601 | N49: =L49-M49 -> -0.0006
D50: 44166 | E50: 0.045 | F50: 0.055 | K50: 44166 | L50: 0.0574 | M50: 0.058 | N50: =L50-M50 -> -0.0006
C51: 2021 | D51: 44197 | E51: 0.045 | F51: 0.055 | K51: 44197 | L51: 0.0582 | M51: 0.0558 | N51: =L51-M51 -> 0.0024
D52: 44228 | E52: 0.045 | F52: 0.055 | K52: 44228 | L52: 0.0572 | M52: 0.0536 | N52: =L52-M52 -> 0.0036
D53: 44256 | E53: 0.045 | F53: 0.055 | K53: 44256 | L53: 0.0567 | M53: 0.052 | N53: =L53-M53 -> 0.0047
D54: 44287 | E54: 0.045 | F54: 0.055 | K54: 44287 | L54: 0.0565 | M54: 0.0507 | N54: =L54-M54 -> 0.0058
D55: 44317 | E55: 0.045 | F55: 0.055 | K55: 44317 | L55: 0.0569 | M55: 0.0497 | N55: =L55-M55 -> 0.0072
D56: 44348 | E56: 0.045 | F56: 0.055 | K56: 44348 | L56: 0.0567 | M56: 0.0487 | N56: =L56-M56 -> 0.008
D57: 44378 | E57: 0.045 | F57: 0.055 | K57: 44378 | L57: 0.05695 | M57: 0.0477 | N57: =L57-M57 -> 0.00925
D58: 44409 | E58: 0.05 | F58: 0.06 | K58: 44409 | L58: 0.0585 | M58: 0.0475 | N58: =L58-M58 -> 0.011
D59: 44440 | E59: 0.05 | F59: 0.06 | K59: 44440 | L59: 0.0639 | M59: 0.0475 | N59: =L59-M59 -> 0.0164
D60: 44470 | E60: 0.05 | F60: 0.06 | K60: 44470 | L60: 0.0718 | M60: 0.0479 | N60: =L60-M60 -> 0.0239
D61: 44501 | E61: 0.05 | F61: 0.06 | K61: 44501 | L61: 0.0789 | M61: 0.0482 | N61: =L61-M61 -> 0.0307
D62: 44531 | E62: 0.05 | F62: 0.06 | K62: 44531 | L62: 0.0833 | M62: 0.0494 | N62: =L62-M62 -> 0.0339
C63: 2022 | D63: 44562 | E63: 0.055 | F63: 0.065 | K63: 44562 | L63: 0.0842 | M63: 0.0501 | N63: =L63-M63 -> 0.0341
D64: 44593 | E64: 0.055 | F64: 0.065 | K64: 44593 | L64: 0.0895 | M64: 0.0507 | N64: =L64-M64 -> 0.0388
D65: 44621 | E65: 0.065 | F65: 0.075 | K65: 44621 | L65: 0.0947 | M65: 0.0517 | N65: =L65-M65 -> 0.043
D66: 44652 | E66: 0.135 | F66: 0.145 | K66: 44652 | L66: 0.1302 | M66: 0.0552 | N66: =L66-M66 -> 0.075
D67: 44682 | E67: 0.135 | F67: 0.145 | K67: 44682 | L67: 0.2049 | M67: 0.0699 | N67: =L67-M67 -> 0.135
D68: 44713 | E68: 0.135 | F68: 0.145 | K68: 44713 | L68: 0.2194 | M68: 0.0841 | N68: =L68-M68 -> 0.1353
D69: 44743 | E69: 0.145 | F69: 0.155 | K69: 44743 | L69: 0.2323 | M69: 0.0956 | N69: =L69-M69 -> 0.1367
D70: 44774 | E70: 0.145 | F70: 0.155 | K70: 44774 | L70: 0.25258 | M70: 0.1049 | N70: =L70-M70 -> 0.14768
D71: 44805 | E71: 0.145 | F71: 0.155 | K71: 44805 | L71: 0.2616 | M71: 0.1163 | N71: =L71-M71 -> 0.1453
D72: 44835 | E72: 0.145 | F72: 0.155 | K72: 44835 | L72: 0.281 | M72: 0.126 | N72: =L72-M72 -> 0.155
D73: 44866 | E73: 0.145 | F73: 0.155 | K73: 44866 | L73: 0.2825 | M73: 0.1337 | N73: =L73-M73 -> 0.1488
D74: 44896 | E74: 0.145 | F74: 0.155 | K74: 44896 | L74: 0.2819 | M74: 0.1406 | N74: =L74-M74 -> 0.1413
C75: 2023 | D75: 44927 | E75: 0.145 | F75: 0.155 | K75: 44927 | L75: 0.2673 | M75: 0.1463 | N75: =L75-M75 -> 0.121
D76: 44958 | E76: 0.145 | F76: 0.155 | K76: 44958 | L76: 0.2471 | M76: 0.1474 | N76: =L76-M76 -> 0.0997
D77: 44986 | E77: 0.155 | F77: 0.165 | K77: 44986 | L77: 0.2242 | M77: 0.1506 | N77: =L77-M77 -> 0.0736
D78: 45017 | E78: 0.155 | F78: 0.165 | K78: 45017 | L78: 0.218 | M78: 0.1512 | N78: =L78-M78 -> 0.0668
D79: 45047 | E79: 0.155 | F79: 0.165 | K79: 45047 | L79: 0.2081 | M79: 0.1523 | N79: =L79-M79 -> 0.0558
D80: 45078 | E80: 0.13 | F80: 0.14 | K80: 45078 | L80: 0.2004 | M80: 0.1509 | N80: =L80-M80 -> 0.0495
D81: 45108 | E81: 0.11 | F81: 0.12 | K81: 45108 | L81: 0.182 | M81: 0.1476 | N81: =L81-M81 -> 0.0344
D82: 45139 | E82: 0.11 | F82: 0.12 | K82: 45139 | L82: 0.1611 | M82: 0.1415 | N82: =L82-M82 -> 0.0196
D83: 45170 | E83: 0.11 | F83: 0.12 | K83: 45170 | L83: 0.1496 | M83: 0.1339 | N83: =L83-M83 -> 0.0157
D84: 45200 | E84: 0.1 | F84: 0.11 | K84: 45200 | L84: 0.1386 | M84: 0.1275 | N84: =L84-M84 -> 0.0111
D85: 45231 | E85: 0.09 | F85: 0.1 | K85: 45231 | L85: 0.1305 | M85: 0.1211 | N85: =L85-M85 -> 0.0094
D86: 45261 | E86: 0.09 | F86: 0.1 | K86: 45261 | L86: 0.1213 | M86: 0.1164 | N86: =L86-M86 -> 0.0049
C87: 2024 | D87: 45292 | E87: 0.09 | F87: 0.1 | K87: 45292 | L87: 0.1187 | M87: 0.1164 | N87: =L87-M87 -> 0.0023
E90: Loans by currency exposure
E91: LKR | F91: ='more Breakups'!H34 -> 842120414
E92: USD | F92: ='more Breakups'!H35 -> 228254025
E93: Bangladeshi Taka | F93: ='more Breakups'!H41 -> 157652152
E94: Other | F94: ='more Breakups'!H44-'more Breakups'!H34-'more Breakups'!H35-'more Breakups'!H41 -> 18143624
E109: Wholesale/ retail trade | F109: ='more Breakups'!H62 -> 261759920
E110: Overseas entities | F110: ='more Breakups'!H57 -> 208063238
E111: Manufacturing | F111: ='more Breakups'!H58 -> 152676544
E112: Consumption | F112: ='more Breakups'!H51 -> 129274363
E113: Agriculture | F113: ='more Breakups'!H48 -> 126475449
E114: Other | F114: ='more Breakups'!H63-'more Breakups'!H62-'more Breakups'!H58-'more Breakups'!H57-'more Breakups'!H51-'more Breakups'!H48 -> 367920701
D129: 2019 | E129: =Drivers!F4 -> 2020 | F129: =Drivers!G4 -> 2021 | G129: =Drivers!H4 -> 2022 | H129: =Drivers!I4 -> 2023F | I129: =Drivers!J4 -> 2024F | J129: =Drivers!K4 -> 2025F
C130: Impairment/ Gross loans | D130: =Drivers!E337 -> 0.039557968 | E130: =Drivers!F337 -> 0.054093105 | F130: =Drivers!G337 -> 0.059681216 | G130: =Drivers!H337 -> 0.07276509 | H130: =Drivers!I337 -> 0.07148 | I130: =Drivers!J337 -> 0.0521 | J130: =Drivers!K337 -> 0.0458
E140: Liquidity coverage ratio (all currency) | F140: Net Stable Funding Ratio
D141: COMB | E141: 518.33 | F141: 193.13
D142: HNB | E142: 509.01 | F142: 148.67
D143: DFCC | E143: 463.22 | F143: 135.63
D144: PABC | E144: 442.74 | F144: 154.24
D145: NTB | E145: 354.56 | F145: 150.27
D146: SEYB | E146: 308.27 | F146: 130.15
D147: SAMP | E147: 299.36 | F147: 172.91
D148: NDB | E148: 269.95 | F148: 141.66
E152: Total capital ratio
D153: DFCC | E153: 13.722
D154: COMB | E154: 14.502
D155: NTB | E155: 15.11
D156: PABC | E156: 17.73
D157: SEYB | E157: 15.29
D158: HNB | E158: 14.73
D159: NDB | E159: 14.46
D160: SAMP | E160: 17.73
D165: Operating income
D166: 2022
C167: Personal Banking | D167: 47315764 | E167: =D167/SUM($D$167:$D$172) -> 0.34628897
C168: Corporate Banking | D168: 28738618 | E168: =D168/SUM($D$167:$D$172) -> 0.21032877
...

Sheet Price volume
A1: COMB N | O1: COMB X
A2: Trade Date | B2: Open (Rs.) | C2: High (Rs.) | D2: Low (Rs.) | E2: Price (LKR) (LHS) | F2: Volume (RHS) | G2: Turnover (Rs.) | H2: TradeVolume | O2: Trade Date | P2: Open (Rs.) | Q2: High (Rs.) | R2: Low (Rs.) | S2: Price (LKR) (LHS) | T2: Volume (RHS) | U2: Turnover (Rs.) | V2: TradeVolume | AF2: COMB | AJ2: Discount
A3: 45307 | E3: 91 | F3: 365108 | O3: 45307 | S3: 76.3 | T3: 6629
A4: 45302 | B4: 93.3 | C4: 93.3 | D4: 91.8 | E4: 92.1 | F4: 526800 | G4: 48653057 | H4: 112 | O4: 45302 | P4: 80 | Q4: 80 | R4: 79 | S4: 79.4 | T4: 969 | U4: 77000.1 | V4: 26 | Z4: Date | AA4: Last Price | AB4: Volume | AC4: SMAVG (15) | AF4: Date | AG4: Last Price
A5: 45301 | B5: 94.3 | C5: 94.7 | E5: 93.3 | F5: 132821 | G5: 12418747 | H5: 66 | O5: 45301 | P5: 81.2 | Q5: 81.2 | R5: 79 | S5: 80 | T5: 13389 | U5: 1070681.3 | V5: 27 | Z5: 45183 | AA5: 81.1 | AB5: 13932 | AC5: 51733 | AF5: 45183 | AG5: 93 | AJ5: =(AG5-AA5)/AG5 -> 0.12795699
A6: 45300 | B6: 95 | C6: 95 | D6: 94 | E6: 94.3 | F6: 19420 | G6: 1829595 | H6: 34 | O6: 45300 | P6: 80.3 | Q6: 81 | R6: 80.2 | S6: 80.5 | T6: 54697 | U6: 4428190.6 | V6: 7 | Z6: 45182 | AA6: 80 | AB6: 15732 | AC6: 65312 | AF6: 45182 | AG6: 91.5 | AJ6: =(AG6-AA6)/AG6 -> 0.12568306
A7: 45299 | B7: 95.2 | C7: 95.5 | D7: 94 | E7: 95 | F7: 351582 | G7: 33402491 | H7: 115 | O7: 45299 | P7: 82 | Q7: 82 | R7: 80 | S7: 80.3 | T7: 31346 | U7: 2524992.8 | V7: 47 | Z7: 45181 | AA7: 80.7 | AB7: 10015 | AC7: 67892 | AF7: 45181 | AG7: 90.4 | AJ7: =(AG7-AA7)/AG7 -> 0.10730088
A8: 45296 | B8: 96.2 | C8: 96.2 | D8: 95 | E8: 95.2 | F8: 238327 | G8: 22689253 | H8: 92 | O8: 45296 | P8: 81.3 | Q8: 82 | R8: 81 | S8: 82 | T8: 52934 | U8: 4337986.3 | V8: 27 | Z8: 45180 | AA8: 80.2 | AB8: 7177 | AC8: 83544 | AF8: 45180 | AG8: 90.5 | AJ8: =(AG8-AA8)/AG8 -> 0.11381215
A9: 45295 | B9: 96 | C9: 96 | D9: 95.2 | E9: 95.5 | F9: 377339 | G9: 36051604 | H9: 86 | O9: 45295 | P9: 82 | Q9: 82 | R9: 81 | S9: 81.3 | T9: 13165 | U9: 1078630 | V9: 10 | Z9: 45177 | AA9: 80.1 | AB9: 59258 | AC9: 86987 | AF9: 45177 | AG9: 92.8 | AJ9: =(AG9-AA9)/AG9 -> 0.13685345
A10: 45294 | B10: 96 | C10: 97.5 | D10: 95.7 | E10: 95.9 | F10: 218632 | G10: 20992987 | H10: 144 | O10: 45294 | P10: 81.7 | Q10: 82.5 | R10: 81.7 | S10: 82 | T10: 6325 | U10: 519213.1 | V10: 21 | Z10: 45176 | AA10: 80.4 | AB10: 13061 | AC10: 87219 | AF10: 45176 | AG10: 92.1 | AJ10: =(AG10-AA10)/AG10 -> 0.12703583
A11: 45293 | B11: 95.5 | C11: 98 | D11: 94.5 | E11: 96.9 | F11: 120591 | G11: 11587529 | H11: 218 | O11: 45293 | P11: 80.9 | Q11: 82.4 | R11: 80.2 | S11: 81.7 | T11: 139364 | U11: 11340538 | V11: 68 | Z11: 45175 | AA11: 80.2 | AB11: 33515 | AC11: 97782 | AF11: 45175 | AG11: 92.2 | AJ11: =(AG11-AA11)/AG11 -> 0.13015184
A12: 45289 | B12: 94.5 | C12: 95.6 | D12: 94.5 | E12: 95.5 | F12: 383942 | G12: 36541263 | H12: 214 | O12: 45289 | P12: 80.1 | Q12: 80.5 | R12: 80 | S12: 80.4 | T12: 34482 | U12: 2763011.5 | V12: 35 | Z12: 45174 | AA12: 83.5 | AB12: 88078 | AC12: 112601 | AF12: 45174 | AG12: 95 | AJ12: =(AG12-AA12)/AG12 -> 0.12105263
A13: 45288 | B13: 93.1 | C13: 94.5 | D13: 92.9 | E13: 94.3 | F13: 645804 | G13: 60737678 | H13: 246 | O13: 45288 | P13: 79 | Q13: 80 | R13: 79 | S13: 79.9 | T13: 25275 | U13: 2019327.4 | V13: 41 | Z13: 45173 | AA13: 81.6 | AB13: 21898 | AC13: 140557 | AF13: 45173 | AG13: 93.3 | AJ13: =(AG13-AA13)/AG13 -> 0.12540193
A14: 45287 | B14: 92.4 | C14: 94 | D14: 91.7 | E14: 93.1 | F14: 78872 | G14: 7325471.7 | H14: 71 | O14: 45287 | P14: 79.9 | Q14: 79.9 | R14: 78.9 | S14: 79 | T14: 5520 | U14: 436025 | V14: 9 | Z14: 45170 | AA14: 79.5 | AB14: 37093 | AC14: 148066 | AF14: 45170 | AG14: 88.4 | AJ14: =(AG14-AA14)/AG14 -> 0.10067873
A15: 45282 | B15: 92.8 | C15: 93.5 | D15: 92.6 | E15: 92.9 | F15: 120088 | G15: 11162754 | H15: 85 | O15: 45282 | P15: 80 | Q15: 80 | R15: 78.5 | S15: 78.9 | T15: 195 | U15: 15423.5 | V15: 5 | Z15: 45169 | AA15: 77.3 | AB15: 18188 | AC15: 170368 | AF15: 45169 | AG15: 86.6 | AJ15: =(AG15-AA15)/AG15 -> 0.1073903
A16: 45281 | B16: 93.7 | C16: 94.2 | D16: 93 | E16: 93.2 | F16: 82579 | G16: 7728981.4 | H16: 80 | O16: 45281 | P16: 80 | Q16: 80 | R16: 80 | S16: 80 | T16: 180 | U16: 14400 | V16: 1 | Z16: 45167 | AA16: 77.7 | AB16: 3645 | AC16: 173886 | AF16: 45167 | AG16: 87 | AJ16: =(AG16-AA16)/AG16 -> 0.10689655
A17: 45280 | B17: 93.6 | C17: 94 | D17: 93.4 | E17: 93.7 | F17: 118865 | G17: 11158281 | H17: 73 | O17: 45280 | P17: 79 | Q17: 79.9 | R17: 79 | S17: 79.2 | T17: 1485 | U17: 117686 | V17: 11 | Z17: 45166 | AA17: 77.9 | AB17: 49578 | AC17: 192631 | AF17: 45166 | AG17: 87 | AJ17: =(AG17-AA17)/AG17 -> 0.1045977
... A725: 44200 | B725: 81 | C725: 83.6 | D725: 81 | E725: 83.3 | F725: 1236817 | G725: 1.0274551e+08 | H725: 481 | O725: 44200 | P725: 70.1 | Q725: 73 | R725: 70.1 | S725: 72.6 | T725: 307193 | U725: 22220966 | V725: 168 | Z725: 44081 | AA725: 57.38 | AB725: 92057 | AC725: 126896 | AF725: 44081 | AG725: 69.38 | AJ725: =(AG725-AA725)/AG725 -> 0.17296051
Z726: 44078 | AA726: 58.25 | AB726: 81105 | AC726: 165822 | AF726: 44078 | AG726: 69.92 | AJ726: =(AG726-AA726)/AG726 -> 0.16690503
Z727: 44077 | AA727: 58.69 | AB727: 117579 | AC727: 180134 | AF727: 44077 | AG727: 70.81 | AJ727: =(AG727-AA727)/AG727 -> 0.17116227
Z728: 44076 | AA728: 58.95 | AB728: 56088 | AC728: 197508 | AF728: 44076 | AG728: 71.16 | AJ728: =(AG728-AA728)/AG728 -> 0.17158516
Z729: 44074 | AA729: 59.13 | AB729: 87715 | AC729: 204299 | AF729: 44074 | AG729: 71.96 | AJ729: =(AG729-AA729)/AG729 -> 0.1782935
Z730: 44071 | AA730: 59.48 | AB730: 35663 | AC730: 208692 | AF730: 44071 | AG730: 72.5 | AJ730: =(AG730-AA730)/AG730 -> 0.17958621
Z731: 44070 | AA731: 59.13 | AB731: 636163 | AC731: 222790 | AF731: 44070 | AG731: 71.25 | AJ731: =(AG731-AA731)/AG731 -> 0.17010526
Z732: 44069 | AA732: 59.39 | AB732: 76223 | AC732: 208085 | AF732: 44069 | AG732: 72.59 | AJ732: =(AG732-AA732)/AG732 -> 0.18184323
Z733: 44068 | AA733: 59.48 | AB733: 51424 | AC733: 240398 | AF733: 44068 | AG733: 73.12 | AJ733: =(AG733-AA733)/AG733 -> 0.18654267
Z734: 44067 | AA734: 60.44 | AB734: 116932 | AC734: 279971 | AF734: 44067 | AG734: 74.37 | AJ734: =(AG734-AA734)/AG734 -> 0.18730671
Z735: 44064 | AA735: 60.62 | AB735: 81254 | AC735: 294414 | AF735: 44064 | AG735: 73.92 | AJ735: =(AG735-AA735)/AG735 -> 0.17992424
Z736: 44063 | AA736: 59.74 | AB736: 165307 | AC736: 302373 | AF736: 44063 | AG736: 73.83 | AJ736: =(AG736-AA736)/AG736 -> 0.19084383
Z737: 44062 | AA737: 59.65 | AB737: 76130 | AC737: 295794 | AF737: 44062 | AG737: 73.92 | AJ737: =(AG737-AA737)/AG737 -> 0.19304654
... Z977: 43648 | AA977: 70.01 | AB977: 30591 | AC977: 13805 | AF977: 43648 | AG977: 81.97 | AJ977: =(AG977-AA977)/AG977 -> 0.14590704
Z978: 43647 | AA978: 70.01 | AF978: 43647 | AG978: 80.84 | AJ978: =(AG978-AA978)/AG978 -> 0.13396833
Z979: 43644 | AA979: 70.01 | AB979: 9526 | AC979: 12277 | AF979: 43644 | AG979: 79.88 | AJ979: =(AG979-AA979)/AG979 -> 0.12356034
Z980: 43643 | AA980: 70.01 | AB980: 7171 | AC980: 12442 | AF980: 43643 | AG980: 79.97 | AJ980: =(AG980-AA980)/AG980 -> 0.12454671
Z981: 43642 | AA981: 69.25 | AB981: 2977 | AC981: 12308 | AF981: 43642 | AG981: 79.53 | AJ981: =(AG981-AA981)/AG981 -> 0.1292594
Z982: 43641 | AA982: 70.1 | AB982: 4 | AC982: 12430 | AF982: 43641 | AG982: 79.45 | AJ982: =(AG982-AA982)/AG982 -> 0.11768408
Z983: 43640 | AA983: 70.1 | AB983: 1412 | AC983: 12472 | AF983: 43640 | AG983: 79.97 | AJ983: =(AG983-AA983)/AG983 -> 0.12342128
Z984: 43637 | AA984: 71.12 | AB984: 632 | AC984: 12399 | AF984: 43637 | AG984: 80.49 | AJ984: =(AG984-AA984)/AG984 -> 0.11641198
Z985: 43636 | AA985: 71.47 | AB985: 123161 | AC985: 12740 | AF985: 43636 | AG985: 81.27 | AJ985: =(AG985-AA985)/AG985 -> 0.1205857
Z986: 43635 | AA986: 71.38 | AB986: 54 | AC986: 5347 | AF986: 43635 | AG986: 81.36 | AJ986: =(AG986-AA986)/AG986 -> 0.1226647
Z987: 43634 | AA987: 71.38 | AB987: 12772 | AC987: 5720 | AF987: 43634 | AG987: 81.71 | AJ987: =(AG987-AA987)/AG987 -> 0.12642271
Z988: 43633 | AA988: 71.12 | AB988: 1820 | AC988: 5080 | AF988: 43633 | AG988: 81.27 | AJ988: =(AG988-AA988)/AG988 -> 0.12489233
Z989: 43630 | AA989: 71.72 | AB989: 8818 | AC989: 5134 | AF989: 43630 | AG989: 80.92 | AJ989: =(AG989-AA989)/AG989 -> 0.11369254
Z990: 43629 | AA990: 69.67 | AB990: 1968 | AC990: 4554 | AF990: 43629 | AG990: 81.1 | AJ990: =(AG990-AA990)/AG990 -> 0.14093711
... Z1068: 43508 | AA1068: 80.18 | AB1068: 109 | AC1068: 43262 | AF1068: 43508 | AG1068: 95.04 | AJ1068: =(AG1068-AA1068)/AG1068 -> 0.15635522
Z1069: 43507 | AA1069: 80.18 | AF1069: 43507 | AG1069: 95.29 | AJ1069: =(AG1069-AA1069)/AG1069 -> 0.15856858
Z1070: 43504 | AA1070: 80.18 | AB1070: 22088 | AC1070: 43339 | AF1070: 43504 | AG1070: 95.29 | AJ1070: =(AG1070-AA1070)/AG1070 -> 0.15856858
Z1071: 43503 | AA1071: 80.43 | AB1071: 1432 | AC1071: 42381 | AF1071: 43503 | AG1071: 95.64 | AJ1071: =(AG1071-AA1071)/AG1071 -> 0.15903388
Z1072: 43502 | AA1072: 79.6 | AB1072: 20068 | AC1072: 42293 | AF1072: 43502 | AG1072: 96.06 | AJ1072: =(AG1072-AA1072)/AG1072 -> 0.17135124
Z1073: 43501 | AA1073: 81.94 | AB1073: 448110 | AC1073: 41283 | AF1073: 43501 | AG1073: 97.52 | AJ1073: =(AG1073-AA1073)/AG1073 -> 0.1597621
Z1074: 43497 | AA1074: 81.19 | AB1074: 24039 | AC1074: 12181 | AF1074: 43497 | AG1074: 97.52 | AJ1074: =(AG1074-AA1074)/AG1074 -> 0.16745283
Z1075: 43496 | AA1075: 81.1 | AB1075: 5034 | AC1075: 11095 | AF1075: 43496 | AG1075: 97.52 | AJ1075: =(AG1075-AA1075)/AG1075 -> 0.16837572
Z1076: 43495 | AA1076: 81.27 | AB1076: 18032 | AC1076: 11962 | AF1076: 43495 | AG1076: 97.52 | AJ1076: =(AG1076-AA1076)/AG1076 -> 0.16663249
Z1077: 43494 | AA1077: 82.11 | AB1077: 23120 | AC1077: 11444 | AF1077: 43494 | AG1077: 97.69 | AJ1077: =(AG1077-AA1077)/AG1077 -> 0.15948408
Z1078: 43493 | AA1078: 81.27 | AB1078: 5042 | AC1078: 9986 | AF1078: 43493 | AG1078: 97.6 | AJ1078: =(AG1078-AA1078)/AG1078 -> 0.16731557
Z1079: 43490 | AA1079: 81.61 | AB1079: 5610 | AC1079: 10339 | AF1079: 43490 | AG1079: 97.09 | AJ1079: =(AG1079-AA1079)/AG1079 -> 0.1594397
Z1080: 43489 | AA1080: 82.02 | AB1080: 33260 | AC1080: 10124 | AF1080: 43489 | AG1080: 96.66 | AJ1080: =(AG1080-AA1080)/AG1080 -> 0.15145872
Z1081: 43488 | AA1081: 80.94 | AB1081: 29757 | AC1081: 7995 | AF1081: 43488 | AG1081: 96.75 | AJ1081: =(AG1081-AA1081)/AG1081 -> 0.16341085
... Z1093: 43469 | AA1093: 79.6 | AB1093: 10342 | AC1093: 11198 | AF1093: 43469 | AG1093: 98.37 | AJ1093: =(AG1093-AA1093)/AG1093 -> 0.19081021
Z1094: 43468 | AA1094: 79.68 | AF1094: 43468 | AG1094: 98.37 | AJ1094: =(AG1094-AA1094)/AG1094 -> 0.18999695
Z1095: 43467 | AA1095: 79.68 | AB1095: 2387 | AC1095: 10637 | AF1095: 43467 | AG1095: 98.8 | AJ1095: =(AG1095-AA1095)/AG1095 -> 0.19352227
Z1096: 43465 | AA1096: 79.6 | AB1096: 1327 | AC1096: 10492 | AF1096: 43465 | AG1096: 98.37 | AJ1096: =(AG1096-AA1096)/AG1096 -> 0.19081021
Z1097: 43462 | AA1097: 80.94 | AB1097: 425 | AC1097: 10413 | AF1097: 43462 | AG1097: 98.37 | AJ1097: =(AG1097-AA1097)/AG1097 -> 0.17718817
Z1098: 43461 | AA1098: 80.43 | AB1098: 6 | AC1098: 10406 | AF1098: 43461 | AG1098: 98.46 | AJ1098: =(AG1098-AA1098)/AG1098 -> 0.18312005
Z1099: 43460 | AA1099: 80.43 | AB1099: 328 | AC1099: 10485 | AF1099: 43460 | AG1099: 98.37 | AJ1099: =(AG1099-AA1099)/AG1099 -> 0.18237267
Z1100: 43458 | AA1100: 81.27 | AB1100: 186 | AC1100: 12627 | AF1100: 43458 | AG1100: 98.29 | AJ1100: =(AG1100-AA1100)/AG1100 -> 0.17316105
Z1101: 43455 | AA1101: 79.68 | AB1101: 461 | AC1101: 12978 | AF1101: 43455 | AG1101: 98.8 | AJ1101: =(AG1101-AA1101)/AG1101 -> 0.19352227
Z1102: 43454 | AA1102: 79.26 | AB1102: 128877 | AC1102: 13863 | AF1102: 43454 | AG1102: 99.23 | AJ1102: =(AG1102-AA1102)/AG1102 -> 0.20124962
Z1103: 43453 | AA1103: 80.18 | AB1103: 1653 | AC1103: 5360 | AF1103: 43453 | AG1103: 98.37 | AJ1103: =(AG1103-AA1103)/AG1103 -> 0.1849141
Z1104: 43452 | AA1104: 81.27 | AB1104: 3902 | AC1104: 5290 | AF1104: 43452 | AG1104: 99.14 | AJ1104: =(AG1104-AA1104)/AG1104 -> 0.18025015
Z1105: 43451 | AA1105: 81.27 | AB1105: 10266 | AC1105: 5200 | AF1105: 43451 | AG1105: 99.23 | AJ1105: =(AG1105-AA1105)/AG1105 -> 0.18099365
Z1106: 43448 | AA1106: 80.43 | AB1106: 5994 | AC1106: 4602 | AF1106: 43448 | AG1106: 99.23 | AJ1106: =(AG1106-AA1106)/AG1106 -> 0.18945883
... Z1124: 43420 | AA1124: 78.84 | AB1124: 239 | AC1124: 56222 | AF1124: 43420 | AG1124: 97.6 | AJ1124: =(AG1124-AA1124)/AG1124 -> 0.19221311
Z1125: 43419 | AA1125: 78.76 | AF1125: 43419 | AG1125: 97.52 | AJ1125: =(AG1125-AA1125)/AG1125 -> 0.1923708
Z1126: 43418 | AA1126: 78.76 | AB1126: 2430 | AC1126: 56241 | AF1126: 43418 | AG1126: 97.26 | AJ1126: =(AG1126-AA1126)/AG1126 -> 0.1902118
Z1127: 43417 | AA1127: 78.84 | AB1127: 537 | AC1127: 56091 | AF1127: 43417 | AG1127: 98.37 | AJ1127: =(AG1127-AA1127)/AG1127 -> 0.19853614
Z1128: 43416 | AA1128: 77.75 | AB1128: 724 | AC1128: 56071 | AF1128: 43416 | AG1128: 98.37 | AJ1128: =(AG1128-AA1128)/AG1128 -> 0.20961675
Z1129: 43413 | AA1129: 79.68 | AB1129: 3992 | AC1129: 56528 | AF1129: 43413 | AG1129: 98.97 | AJ1129: =(AG1129-AA1129)/AG1129 -> 0.19490755
Z1130: 43412 | AA1130: 80.27 | AB1130: 2510 | AC1130: 56482 | AF1130: 43412 | AG1130: 99.14 | AJ1130: =(AG1130-AA1130)/AG1130 -> 0.1903369
Z1131: 43411 | AA1131: 80.43 | AB1131: 5524 | AC1131: 56657 | AF1131: 43411 | AG1131: 101.03 | AJ1131: =(AG1131-AA1131)/AG1131 -> 0.20389983
Z1132: 43409 | AA1132: 83.37 | AB1132: 2869 | AC1132: 57702 | AF1132: 43409 | AG1132: 106.41 | AJ1132: =(AG1132-AA1132)/AG1132 -> 0.216521
Z1133: 43406 | AA1133: 83.78 | AB1133: 265147 | AC1133: 58504 | AF1133: 43406 | AG1133: 105.99 | AJ1133: =(AG1133-AA1133)/AG1133 -> 0.20954807
Z1134: 43405 | AA1134: 83.78 | AB1134: 226658 | AC1134: 41981 | AF1134: 43405 | AG1134: 104.19 | AJ1134: =(AG1134-AA1134)/AG1134 -> 0.19589212
Z1135: 43404 | AA1135: 80.27 | AB1135: 7870 | AC1135: 27457 | AF1135: 43404 | AG1135: 100.85 | AJ1135: =(AG1135-AA1135)/AG1135 -> 0.20406544
Z1136: 43403 | AA1136: 78.17 | AB1136: 194616 | AC1136: 27152 | AF1136: 43403 | AG1136: 97.52 | AJ1136: =(AG1136-AA1136)/AG1136 -> 0.19842084
Z1137: 43402 | AA1137: 78.92 | AB1137: 20506 | AC1137: 14228 | AF1137: 43402 | AG1137: 97.52 | AJ1137: =(AG1137-AA1137)/AG1137 -> 0.19073011
... Z1175: 43346 | AA1175: 78.84 | AB1175: 1278 | AC1175: 18406 | AF1175: 43346 | AG1175: 106.07 | AJ1175: =(AG1175-AA1175)/AG1175 -> 0.25671726
Z1176: 43343 | AA1176: 79.76 | AB1176: 2552 | AC1176: 18419
Z1177: 43342 | AA1177: 79.76 | AB1177: 16027
Z1178: 43341 | AA1178: 78.76 | AB1178: 1355
Z1179: 43340 | AA1179: 78.84 | AB1179: 20024
Z1180: 43339 | AA1180: 78.92 | AB1180: 4156
Z1181: 43336 | AA1181: 79.6 | AB1181: 1991
Z1182: 43335 | AA1182: 79.34 | AB1182: 4339
Z1183: 43333 | AA1183: 79.26 | AB1183: 3964
Z1184: 43332 | AA1184: 79.93 | AB1184: 49108
Z1185: 43329 | AA1185: 79.68 | AB1185: 40725
Z1186: 43328 | AA1186: 79.68 | AB1186: 122611
Z1187: 43327 | AA1187: 79.51 | AB1187: 2306
Z1188: 43326 | AA1188: 80.01 | AB1188: 4204
...

Sheet Quarterly
C1: For the quarter ended
C2: 45192 | D2: 45078 | E2: 44986 | F2: 44896 | G2: 44805 | H2: 44713 | I2: 44621 | J2: 44531
B3: Gross income | C3: 88294597 | D3: 83519041 | E3: 84149226 | F3: 84813856 | G3: 76055638 | H3: 64944217 | I3: 54573233 | J3: 43625180 | L3: =E3+D3+C3+C3 -> 344257461
B4: Interest income | C4: 73758370 | D4: 74872632 | E4: 75939012 | F4: 72136429 | G4: 62139977 | H4: 50269825 | I4: 37846848 | J4: 36591673 | L4: =E4+D4+C4+C4 -> 298328384
B5: Less : Interest expense | C5: 50326278 | D5: 56398189 | E5: 56963785 | F5: 50285038 | G5: 40038742 | H5: 28380265 | I5: 19023823 | J5: 17708621 | L5: =E5+D5+C5+C5 -> 214014530
B6: Net interest income | C6: 23432092 | D6: 18474443 | E6: 18975227 | F6: 21851391 | G6: 22101235 | H6: 21889560 | I6: 18823025 | J6: 18883052 | L6: =E6+D6+C6+C6 -> 84313854
B7: Fee and commission income | C7: 7657034 | D7: 7076778 | E7: 7300668 | F7: 7985635 | G7: 6447150 | H7: 6365740 | I7: 5393005 | J7: 4915199 | L7: =E7+D7+C7+C7 -> 29691514
B8: Less: Fee and commission expense | C8: 2038079 | D8: 1887996 | E8: 1898492 | F8: 1729591 | G8: 1411595 | H8: 1575925 | I8: 1305318 | J8: 1269724
B9: Net fee and commission income | C9: 5618955 | D9: 5188782 | E9: 5402176 | F9: 6256044 | G9: 5035555 | H9: 4789815 | I9: 4087687 | J9: 3645475
B10: Net gains/(losses) from trading | C10: 3381671 | D10: -6555889 | E10: -8975464 | F10: 1173354 | G10: 2022197 | H10: 8560357 | I10: 23541542 | J10: -101050
B11: Net gains/(losses) from derecognition of financial assets | C11: 1713760 | D11: 587244 | E11: 337266 | F11: 105790 | G11: 106832 | H11: 49119 | I11: 15143 | J11: 25076
B12: Net other operating income | C12: 1783762 | D12: 7538276 | E12: 9547744 | F12: 3412648 | G12: 5339482 | H12: -300824 | I12: -12223305 | J12: 2194282
B13: Total operating income | C13: 35930240 | D13: 25232856 | E13: 25286949 | F13: 32799227 | G13: 34605301 | H13: 34988027 | I13: 34244092 | J13: 24646835
B14: Less : Impairment charges and other losses | C14: 12571147 | D14: 6413788 | E14: 6797175 | F14: 19652653 | G14: 17052988 | H14: 29258063 | I14: 5960556 | J14: 7142508
B15: Net operating income | C15: 23359093 | D15: 18819068 | E15: 18489774 | F15: 13146574 | G15: 17552313 | H15: 5729964 | I15: 28283536 | J15: 17504327
B16: Less: Expenses | C16: 10691452 | D16: 10607104 | E16: 10677690 | F16: 10265566 | G16: 7985228 | H16: 9310867 | I16: 8720580 | J16: 8378026
B17: Personnel expenses | C17: 5512768 | D17: 5684029 | E17: 5612486 | F17: 5148402 | G17: 5055534 | H17: 4972094 | I17: 4612253 | J17: 4639350
B18: Depreciation and amortisation | C18: 995181 | D18: 1020578 | E18: 1063760 | F18: 968895 | G18: 905454 | H18: 906117 | I18: 817905 | J18: 798333
B19: Other operating expenses | C19: 4183503 | D19: 3902497 | E19: 4001444 | F19: 4148269 | G19: 2024240 | H19: 3432656 | I19: 3290422 | J19: 2940343
... B26: Profit for the period | C26: 6473131 | D26: 3931444 | E26: 4359030 | F26: 8939067 | G26: 6282655 | H26: -2596954 | I26: 11774704 | J26: 5272945
B27: Profit attributable to:
B28: Equity holders of the Bank | C28: 6233402 | D28: 3750123 | E28: 4216403 | F28: 8775188 | G28: 6095730 | H28: -2743585 | I28: 11684581 | J28: 5217687
B29: Non-controlling interest | C29: 239729 | D29: 181321 | E29: 142627 | F29: 163879 | G29: 186925 | H29: 146631 | I29: 90123 | J29: 55258
B30: Profit for the period | C30: 6473131 | D30: 3931444 | E30: 4359030 | F30: 8939067 | G30: 6282655 | H30: -2596954 | I30: 11774704 | J30: 5272945
B32: Earnings per share | C32: 4.75 | D32: 2.86 | E32: 3.21 | F32: 7.08 | G32: 4.92 | H32: -2.21 | I32: 9.42 | J32: 4.37

Sheet Sheet1
