Workbook

Sheet Cover
B3: Commercial Bank of Ceylon PLC
B4: COMB N
B5: COMB X

Sheet FS
B3: For the year ended December 31,
B4: (LKR '000 except per share data) | C4: 2017 | D4: 2018 | E4: 2019 | F4: 2020 | G4: 2021 | H4: 2022 | I4: 2023 | J4: 2024 | K4: 2025
B5: INCOME STATEMENT
B6: Gross income | C6: 116841755 | D6: - | E6: 150741129 | F6: 151966413 | G6: 163675312 | H6: 280386944 | I6: 341566200 | J6: 274975814 | K6: 365180892
B7: Interest income | C7: 104049102 | D7: - | E7: 129287473 | F7: 124087713 | G7: 132818178 | H7: 222393079 | I7: 297645866 | J7: 275217117 | K7: 301366595
B8: Less: Interest expense | C8: 64481004 | D8: - | E8: 80931352 | F8: 73218911 | G8: 66401846 | H8: 137727868 | I8: 211230507 | J8: 157082433 | K8: 160406053
B9: Net interest income | C9: 39567298 | D9: - | E9: 48356391 | F9: 50868802 | G9: 66416332 | H9: 84665211 | I9: 86415359 | J9: 118134684 | K9: 140960542
B10: Fee and commission income | C10: 10510800 | D10: - | E10: 12874966 | F10: 11839689 | G10: 15917337 | H10: 26191530 | I10: 30653212 | J10: 34480523 | K10: 42592091
B11: Less: Fee and commission expense | C11: 1586334 | D11: - | E11: 2123128 | F11: 2018014 | G11: 3675143 | H11: 6022429 | I11: 8265893 | J11: 10834345 | K11: 13616570
B12: Net fee and commission income | C12: 8924466 | D12: - | E12: 10751838 | F12: 9821675 | G12: 12242194 | H12: 20169101 | I12: 22387319 | J12: 23646178 | K12: 28975521
B13: Net gains/(losses) from trading | C13: 233956 | D13: - | E13: 1360833 | F13: 1878060 | G13: 1936007 | H13: 35297450 | I13: -12481613 | J13: -2201010 | K13: 344
B14: Net gains/(losses) from derecognition of financial assets | C14: 129210 | D14: - | E14: 1135711 | F14: 6390197 | G14: 3001574 | H14: 276884 | I14: 5060242 | J14: -41016836 | K14: 344
B15: Net other operating income | C15: 1918687 | D15: - | E15: 6081876 | F15: 7770754 | G15: 10002216 | H15: -3771999 | I15: 20688493 | J15: 8496020 | K15: 345
B16: Total operating income | C16: 50773617 | D16: - | E16: 67686649 | F16: 67686649 | G16: 93598323 | H16: 136636647 | I16: 122069800 | J16: 107059326 | K16: 191158269
B17: Less: Impairment charges and other losses | C17: 2225914 | D17: -4413 | E17: 11331525 | F17: 21419532 | G17: 25139926 | H17: 71924260 | I17: 38095070 | J17: - | K17: -
B18: Net operating income | C18: 48547703 | D18: - | E18: 56355126 | F18: 56355126 | G18: 68458397 | H18: 64712387 | I18: 83174730 | J18: 169353580 | K18: 168041772
B19: Less: Expenses
B20: Personnel expenses | C20: 11338517 | D20: - | E20: 14008914 | F20: 14992748 | G20: 16799212 | H20: 19788283 | I20: 22824913 | J20: 27907458 | K20: 349
B21: Depreciation and amortisation | C21: 1416927 | D21: - | E21: 2841264 | F21: 3102695 | G21: 3220066 | H21: 3598371 | I21: 4335640 | J21: 4737203 | K21: 350
B22: Other operating expenses | C22: 7618993 | D22: - | E22: 8875316 | F22: 8167170 | G22: 9638461 | H22: 12895587 | I22: 17129279 | J22: 19193697 | K22: 351
B23: Total operating expenses | C23: 20374437 | D23: - | E23: 26125494 | F23: 26125494 | G23: 29657739 | H23: 36282241 | I23: - | J23: 51838358 | K23: 57502998
B24: Operating profit before taxes on financial services | C24: 23280324 | D24: - | E24: 30229632 | F24: 30229632 | G24: 32957324 | H24: 28430146 | I24: 38884898 | J24: 117515492 | K24: 110538774
B25: Less: Taxes on financial services | C25: 4896620 | D25: - | E25: 7255728 | F25: 4531381 | G25: 5845230 | H25: 3921381 | I25: 4961392 | J25: 19706675 | K25: 351
B26: Operating profit after taxes on financial services | C26: 23276646 | D26: - | E26: 22973904 | F26: 22973904 | G26: 32955428 | H26: 24508765 | I26: 33923506 | J26: 97808817 | K26: 92788083
B27: Share of profit/(loss) of associate, net of tax | C27: 3678 | D27: - | E27: 9992 | F27: - | G27: - | H27: -3727 | I27: 3495 | J27: -460 | K27: 379
B28: Profit before tax | C28: 23280324 | D28: 12056211 | E28: 22983896 | F28: 22983896 | G28: 32957324 | H28: 24505038 | I28: 38884898 | J28: 97808357 | K28: 92787421
B29: Less: Income tax expense/(reversal) | C29: 6653817 | D29: - | E29: 5563500 | F29: 7433063 | G29: 8667036 | H29: 105566 | I29: 12027341 | J29: 42121945 | K29: 352
B30: Profit for the year | C30: 16626507 | D30: - | E30: 17420396 | F30: 17420396 | G30: 24290288 | H30: 24399472 | I30: 21899660 | J30: 55686412 | K30: 60937517
B31: Profit attributable to: Equity holders of the Bank | C31: 16605963 | D31: - | E31: 17263259 | F31: 17263259 | G31: 24062469 | H31: 23811914 | I31: 21114675 | J31: 55073240 | K31: 60110183
B32: Non-controlling interest | C32: 20544 | D32: - | E32: 157137 | F32: 157137 | G32: 227819 | H32: 587558 | I32: 784985 | J32: 613172 | K32: 827334
B33: Profit for the year | C33: 16626507 | D33: - | E33: 17420396 | F33: 17420396 | G33: 24290288 | H33: 24399472 | I33: 21899660 | J33: 55686412 | K33: 60937517
B34: Earnings per share Basic earnings per ordinary share (Rs.) | C34: 17.28 | D34: - | E34: 16.8 | F34: 15.7 | G34: 20.15 | H34: 19.21 | I34: 16.07 | J34: 38.44 | K34: 353
B35: Diluted earnings per ordinary share (Rs.) | C35: 17.27 | D35: - | E35: 16.8 | F35: 15.7 | G35: 20.15 | H35: 19.21 | I35: 16.06 | J35: 38.38 | K35: 353
B36: Diviend per share | C36: - | D36: - | E36: - | F36: - | G36: - | H36: - | I36: - | J36: - | K36: -
B38: OCI
B39: Transfer of FV losses reclassification of debt from FVTOCI to AC | C39: - | D39: - | E39: - | F39: - | G39: - | H39: - | I39: - | J39: - | K39: -
B41: IS check | C41: =IF(C18-C23-C25+C27-C29-C30+C31+C32-C33=0,"OK","FLAG") | D41: =IF(D18-D23-D25+D27-D29-D30+D31+D32-D33=0,"OK","FLAG") | E41: =IF(E18-E23-E25+E27-E29-E30+E31+E32-E33=0,"OK","FLAG") | F41: =IF(F18-F23-F25+F27-F29-F30+F31+F32-F33=0,"OK","FLAG") | G41: =IF(G18-G23-G25+G27-G29-G30+G31+G32-G33=0,"OK","FLAG") | H41: =IF(H18-H23-H25+H27-H29-H30+H31+H32-H33=0,"OK","FLAG") | I41: =I18-I23-I25+I27-I29-I30+I31+I32-I33 | J41: =J18-J23-J25+J27-J29-J30+J31+J32-J33 | K41: =K18-K23-K25+K27-K29-K30+K31+K32-K33
B43: BALANCE SHEET
B44: Assets
B45: Cash and cash equivalents | C45: 3031093 | D45: 44355962 | E45: 53681118 | F45: 50250627 | G45: 69335379 | H45: 149393561 | I45: 159701507 | J45: 86848291 | K45: 88857011
B46: Balances with Central Banks | C46: - | D46: 55605535 | E46: 46101232 | F46: 110971105 | G46: 241 | H46: 66439459 | I46: 621633503 | J46: 45270068 | K46: 47809989
B47: Placements with banks | C47: - | D47: 23989815 | E47: 24203909 | F47: -34.06 | G47: 241 | H47: 95899645 | I47: 81506653 | J47: 99303303 | K47: 110223171
B48: Securities purchased under resale agreements | C48: - | D48: 9513512 | E48: 13147584 | F48: 13147534 | G48: 3000490 | H48: 1517308 | I48: 31138729 | J48: 28655962 | K48: 17446102
B49: Derivative financial assets | C49: - | D49: 7909962 | E49: 13809327 | F49: 44.01 | G49: 242 | H49: 8345091 | I49: 7226484 | J49: 4264271 | K49: 5422850
B50: Financial assets recognised through profit or loss – measured at fair value | C50: - | D50: 5520167 | E50: 21468033 | F50: 63.92 | G50: 242 | H50: 24873057 | I50: 29449653 | J50: 9167346 | K50: 111753532
B51: Financial assets at amortised cost – loans and advances to banks | C51: - | D51: 763074 | E51: 757787 | F51: 2.89 | G51: 245 | H51: - | I51: - | J51: - | K51: -
B52: Financial assets at amortised cost – loans and advances to other customers | C52: - | D52: 867611976 | E52: 893919311 | F52: 1.77 | G52: 246 | H52: 1130442579 | I52: 1176360000 | J52: 1384524660 | K52: 1958506596
B53: Financial assets at amortised cost – debt and other financial instruments | C53: - | D53: 89274113 | E53: 107059021 | F53: 182.14 | G53: 250 | H53: 725935929 | I53: 685155537 | J53: 667709691 | K53: 731263697
B54: Financial assets measured at fair value through other comprehensive income | C54: - | D54: 176760611 | E54: 197825017 | F54: 278461369 | G54: 251 | H54: 117056240 | I54: 287732972 | J54: 4090697 | K54: 2911061462
B55: Investments in subsidiaries | C55: 5808 | D55: 80575 | E55: 85397 | F55: 5082437 | G55: 254 | H55: 5808439 | I55: 5808000 | J55: 5088429 | K55: -332880
B56: Investment in associate | C56: - | D56: 105320 | E56: 56821 | F56: 4341 | G56: 255 | H56: 4331 | I56: 59004 | J56: 48431 | K56: -
B57: Property, plant and equipment and right-of-use assets | C57: - | D57: 17015935 | E57: 22423346 | F57: 22312394 | G57: 257 | H57: 25452452 | I57: 297294266 | J57: 270604688 | K57: 31652401
B58: Investment properties | C58: - | D58: - | E58: 46350 | F58: 6710156 | G58: 269 | H58: - | I58: 897825 | J58: 3225 | K58: 775060
B59: Intangible assets | C59: -346360 | D59: 1433961 | E59: 1645714 | F59: 9.71 | G59: 270 | H59: 3536120 | I59: 5489404 | J59: 4221381 | K59: 5008060
B60: Deferred tax assets | C60: - | D60: 188487 | E60: 530165 | F60: -17.51 | G60: 272 | H60: 30041203 | I60: 354411610 | J60: 10832584 | K60: 14409667
B61: Other assets | C61: - | D61: 23011122 | E61: 23243369 | F61: -13.86 | G61: 274 | H61: 40259849 | I61: 37735161 | J61: 29755134 | K61: 140899086
B62: Total assets | C62: - | D62: 1319912237 | E62: 1048941366 | F62: 1736218021 | G62: 1983091144 | H62: 2425793952 | I62: 2655611675 | J62: 2789780828 | K62: 3378846406
B63: Liabilities
B64: Due to banks | C64: - | D64: - | E64: - | F64: 65.12 | G64: - | H64: 65130000 | I64: 47274000 | J64: - | K64: 29724000
B65: Derivative financial liabilities | C65: - | D65: - | E65: - | F65: -0.01 | G65: - | H65: 2881000 | I65: 2319000 | J65: - | K65: 1263000
B66: Securities sold under repurchase agreements | C66: - | D66: - | E66: - | F66: 3947612 | G66: - | H66: 97726000 | I66: 111199000 | J66: - | K66: 110462000
B67: Financial liabilities at amortised cost – due to depositors | C67: - | D67: - | E67: - | F67: 20.36 | G67: - | H67: 1914359000 | I67: 2085046000 | J67: - | K67: 2608852000
B68: Financial liabilities at amortised cost – other borrowings | C68: - | D68: - | E68: - | F68: -13.46 | G68: - | H68: 16150000 | I68: 12756000 | J68: - | K68: 14246000
B69: Current tax liabilities | C69: - | D69: - | E69: - | F69: 34.58 | G69: - | H69: 24475000 | I69: 14952000 | J69: - | K69: 25759000
B70: Deferred tax liabilities | C70: - | D70: - | E70: - | F70: -3.03 | G70: - | H70: - | I70: - | J70: - | K70: -
B71: Other liabilities | C71: - | D71: - | E71: - | F71: 9.09 | G71: - | H71: 39861000 | I71: 55050000 | J71: - | K71: 69681000
B72: Due to subsidiaries | C72: - | D72: - | E72: - | F72: 3389 | G72: - | H72: 115000 | I72: 317000 | J72: - | K72: 139000
B73: Subordinated liabilities | C73: 1535349 | D73: 3105553 | E73: 3848979 | F73: 0.99 | G73: 3398554 | H73: 61401000 | I73: 36483000 | J73: 7242090 | K73: 73322000
B74: Total liabilities | C74: 1158860856 | D74: - | E74: - | F74: 1579071845 | G74: - | H74: 2222099000 | I74: 2365397000 | J74: - | K74: 2933629000
B75: Equity
B76: Stated capital | C76: 278 | D76: - | E76: - | F76: 27.55 | G76: - | H76: 58150000 | I76: 62948000 | J76: - | K76: 91558000
B77: Statutory reserves | C77: 282 | D77: - | E77: - | F77: 10.7 | G77: - | H77: 11353000 | I77: 12376000 | J77: - | K77: 18004000
B78: Retained earnings | C78: 282 | D78: - | E78: - | F78: 56.72 | G78: - | H78: 128604000 | I78: 8558000 | J78: - | K78: 17282000
B79: Other reserves | C79: 283 | D79: - | E79: - | F79: 13.18 | G79: - | H79: - | I79: 131049000 | J79: - | K79: 197476000
B80: Total equity attributable to equity holders of the Bank | C80: 16605963 | D80: - | E80: 17263259 | F80: 149826426 | G80: 24062469 | H80: 23811914 | I80: 21114675 | J80: 55073240 | K80: 60110183
B81: Non-controlling interest | C81: 20544 | D81: - | E81: 157137 | F81: 157137 | G81: 227819 | H81: 587558 | I81: 784985 | J81: 613172 | K81: 827334
B82: Total equity | C82: 108866766 | D82: - | E82: - | F82: 157146126 | G82: - | H82: - | I82: 214931000 | J82: - | K82: -
B83: Total liabilities and equity | C83: 1158860856 | D83: - | E83: - | F83: 1736218021 | G83: - | H83: 2425798000 | I83: 2580328000 | J83: - | K83: 3257948000
B84: Contingent liabilities and commitments | C84: 85 | D84: - | E84: - | F84: 25.75 | G84: - | H84: 549422000 | I84: 668876000 | J84: - | K84: 981205000
B85: Net assets value per ordinary share (Rs.) | C85: 287 | D85: - | E85: - | F85: 4.27 | G85: - | H85: - | I85: - | J85: - | K85: -
B86: Memorandum information | C86: - | D86: - | E86: - | F86: - | G86: - | H86: - | I86: - | J86: - | K86: -
B87: Number of employees | C87: - | D87: - | E87: - | F87: 5057 | G87: - | H87: - | I87: - | J87: - | K87: -
B88: Number of customer service centres | C88: - | D88: - | E88: - | F88: 287 | G88: - | H88: - | I88: - | J88: - | K88: -
B90: BS check | C90: =SUM(C45:C61)-SUM(C64:C73)-SUM(C76:C79)-C81 | D90: =SUM(D45:D61)-SUM(D64:D73)-SUM(D76:D79)-D81 | E90: =SUM(E45:E61)-SUM(E64:E73)-SUM(E76:E79)-E81 | F90: =SUM(F45:F61)-SUM(F64:F73)-SUM(F76:F79)-F81 | G90: =SUM(G45:G61)-SUM(G64:G73)-SUM(G76:G79)-G81 | H90: =SUM(H45:H61)-SUM(H64:H73)-SUM(H76:H79)-H81
B92: Cash / total assets | C92: - | D92: 1319912237 | E92: 1048941366 | F92: 1736218021 | G92: 1983091144 | H92: 2425793952 | I92: 2655611675 | J92: 2789780828 | K92: 3378846406
H93: =((H88/E88)^(1/3))-1
B94: CASH FLOW STATEMENT
B96: Cash flows from operating activities Profit before income tax | C96: 23182944 | D96: 25591208 | E96: 22339105 | F96: 23511312 | G96: 32001203 | H96: 22598385 | I96: 33927001 | J96: 97808357 | K96: 92787421
B97: Adjustments for: | C97: - | D97: - | E97: - | F97: - | G97: - | H97: - | I97: - | J97: - | K97: -
B98: Non-cash items included in profit before tax | C98: 1882763 | D98: 12056211 | E98: 13702213 | F98: 24705430 | G98: 30013192 | H98: 90747133 | I98: 35977444 | J98: 97808357 | K98: 92787421
B99: Change in operating assets | C99: -121579353 | D99: -167137925 | E99: -74749286 | F99: -369030667 | G99: -221556713 | H99: -424402972 | I99: -177671173 | J99: -244015913 | K99: -521753312
B100: Change in operating liabilities | C100: 97246867 | D100: 135473881 | E100: 65515273 | F100: 322115757 | G100: 200391382 | H100: 396536876 | I100: 181162526 | J100: 138769911 | K100: 420789987
B101: (Gains)/losses on sale of property, plant and equipment | C101: -10395 | D101: 3633 | E101: -7958 | F101: -7958 | G101: -5164 | H101: -4054 | I101: -3167 | J101: -15939 | K101: -25515
B102: Share of (profit)/loss of associate, net of tax | C102: - | D102: - | E102: - | F102: - | G102: - | H102: -3727 | I102: 3495 | J102: -460 | K102: 379
B103: Dividends received from investments in associate and subsidiaries | C103: - | D103: - | E103: - | F103: - | G103: -105911 | H103: - | I103: -384601 | J103: - | K103: -
B104: Interest expense on subordinated liabilities | C104: 1535349 | D104: 3105553 | E104: 3848979 | F104: 3756921 | G104: 3398554 | H104: 3398554 | I104: 5247288 | J104: 7242090 | K104: 9230001
B105: Net unrealised gains/(losses) arising from translating the Financial Statements of foreign operations | C105: 438565 | D105: 2557517 | E105: -399787 | F105: 439883 | G105: 1152856 | H105: 1278891 | I105: 18347815 | J105: -11971874 | K105: 2888637
B106: Benefits paid on defined benefit plans | C106: -179865 | D106: -376995 | E106: -194728 | F106: -670487 | G106: -1107421 | H106: -765203 | I106: -601335 | J106: -270771 | K106: -292071
B107: Income tax paid | C107: -4014741 | D107: -5856270 | E107: -8087930 | F107: -7748421 | G107: -8660823 | H107: -8963620 | I107: -11143271 | J107: -20193005 | K107: -19877515
B108: Surcharge tax paid | C108: - | D108: - | E108: - | F108: - | G108: - | H108: -5036184 | I108: - | J108: - | K108: -
...

Sheet Drivers
B3: For the year ended December 31,
B4: (LKR '000 except per share data) | C4: 2017 | D4: 2018 | E4: 2019 | F4: 2020 | G4: 2021 | H4: 2022 | I4: 2023 | J4: 2024 | K4: 2025
B5: INCOME STATEMENT
B7: Interest income | C7: 104049102 | D7: - | E7: 129287473 | F7: 124087713 | G7: 132818178 | H7: 222393079 | I7: - | J7: 275217117 | K7: 301366595
B9: Cash and cash equivalents | C9: 3031093 | D9: 44355962 | E9: 53681118 | F9: 50250627 | G9: 69335379 | H9: 149393561 | I9: 159701507 | J9: 86848291 | K9: 88857011
B10: Balances with Central Banks | C10: - | D10: 55605535 | E10: 46101232 | F10: 110971105 | G10: 241 | H10: 66439459 | I10: 621633503 | J10: 45270068 | K10: 47809989
B11: Placements with Banks | C11: - | D11: 23989815 | E11: 24203909 | F11: -34.06 | G11: 241 | H11: 95899645 | I11: 81506653 | J11: 99303303 | K11: 110223171
B12: Securities purchased under resale agreements | C12: 57518 | D12: 9513512 | E12: 13147584 | F12: 13147534 | G12: 3000490 | H12: 1517308 | I12: 31138729 | J12: 28655962 | K12: 17446102
B13: Financial assets recognized through profit or loss | C13: - | D13: - | E13: - | F13: - | G13: - | H13: - | I13: - | J13: - | K13: -
B14: Derivatives | C14: - | D14: - | E14: - | F14: - | G14: - | H14: - | I14: - | J14: - | K14: -
B15: Other financial instruments | C15: 156598 | D15: 89274113 | E15: 247379 | F15: 182.14 | G15: 250 | H15: 725935929 | I15: 685155537 | J15: 667709691 | K15: 731263697
B16: Financial assets at amortized cost - loans and advances to other customers | C16: - | D16: - | E16: 893919311 | F16: - | G16: - | H16: - | I16: - | J16: 1384524660 | K16: 1958506596
B17: Financial assets at amortized cost - debt and other financial instruments | C17: - | D17: - | E17: - | F17: - | G17: - | H17: - | I17: - | J17: - | K17: -
B18: Financial assets measured at fair value through other comprehensive income | C18: 15349974 | D18: 176760611 | E18: 197825017 | F18: 278461369 | G18: 251 | H18: 117056240 | I18: 287732972 | J18: 4090697 | K18: 2911061462
B19: Interest accrued on impaired loans and advances to other customers | C19: - | D19: - | E19: 893919311 | F19: - | G19: - | H19: - | I19: - | J19: 1384524660 | K19: 1958506596
C20: 2413 | D20: 2661 | E20: 7884 | F20: 11375 | G20: 0 | H20: 0
B22: Check | C22: -857269981 | D22: -994370875 | E22: -1068982587 | F22: -1286616399 | G22: 0 | H22: 0 | I22: - | J22: - | K22: -
B24: Interest rate | C24: - | D24: - | E24: - | F24: - | G24: - | H24: - | I24: - | J24: - | K24: -
B26: Cash and cash equivalents | C26: 3031093 | D26: 44355962 | E26: 53681118 | F26: 50250627 | G26: 69335379 | H26: 149393561 | I26: 159701507 | J26: 86848291 | K26: 88857011
B27: Balances with Central Banks | C27: - | D27: 55605535 | E27: 46101232 | F27: 110971105 | G27: 241 | H27: 66439459 | I27: 621633503 | J27: 45270068 | K27: 47809989
B28: Placements with Banks | C28: - | D28: 23989815 | E28: 24203909 | F28: -34.06 | G28: 241 | H28: 95899645 | I28: 81506653 | J28: 99303303 | K28: 110223171
B29: Securities purchased under resale agreements | C29: 57518 | D29: 9513512 | E29: 13147584 | F29: 13147534 | G29: 3000490 | H29: 1517308 | I29: 31138729 | J29: 28655962 | K29: 17446102
B30: Financial assets recognized through profit or loss | C30: - | D30: - | E30: - | F30: - | G30: - | H30: - | I30: - | J30: - | K30: -
B31: Derivatives | C31: - | D31: - | E31: - | F31: - | G31: - | H31: - | I31: - | J31: - | K31: -
B32: Other financial instruments | C32: 156598 | D32: 89274113 | E32: 247379 | F32: 182.14 | G32: 250 | H32: 725935929 | I32: 685155537 | J32: 667709691 | K32: 731263697
B33: Financial assets at amortized cost - loans and advances to other customers | C33: - | D33: - | E33: 893919311 | F33: - | G33: - | H33: - | I33: - | J33: 1384524660 | K33: 1958506596
B34: Overdrafts | C34: - | D34: - | E34: - | F34: - | G34: - | H34: - | I34: - | J34: - | K34: -
B35: Trade finance | C35: - | D35: - | E35: - | F35: - | G35: - | H35: - | I35: - | J35: - | K35: -
B36: Lease/hire purchase receivable | C36: - | D36: - | E36: - | F36: - | G36: - | H36: - | I36: - | J36: - | K36: -
B37: Credit cards | C37: - | D37: - | E37: - | F37: - | G37: - | H37: - | I37: - | J37: - | K37: -
B38: Pawning | C38: - | D38: - | E38: - | F38: - | G38: - | H38: - | I38: - | J38: - | K38: -
B39: Staff loans | C39: - | D39: - | E39: - | F39: - | G39: - | H39: - | I39: - | J39: - | K39: -
B40: Housing loans | C40: - | D40: - | E40: - | F40: - | G40: - | H40: - | I40: - | J40: - | K40: -
B41: Personal loans | C41: - | D41: - | E41: - | F41: - | G41: - | H41: - | I41: - | J41: - | K41: -
B42: Term loans | C42: - | D42: - | E42: - | F42: - | G42: - | H42: - | I42: - | J42: - | K42: -
B43: Short term | C43: - | D43: - | E43: - | F43: - | G43: - | H43: - | I43: - | J43: - | K43: -
B44: Long term | C44: - | D44: - | E44: - | F44: - | G44: - | H44: - | I44: - | J44: - | K44: -
B45: Bills of exchange | C45: - | D45: - | E45: - | F45: - | G45: - | H45: - | I45: - | J45: - | K45: -
... B50: Financial assets at amortized cost - debt and other financial instruments | C50: - | D50: - | E50: - | F50: - | G50: - | H50: - | I50: - | J50: - | K50: -
B52: Financial assets measured at fair value through other comprehensive income | C52: 15349974 | D52: 176760611 | E52: 197825017 | F52: 278461369 | G52: 251 | H52: 117056240 | I52: 287732972 | J52: 4090697 | K52: 2911061462
B53: Interest accrued on impaired loans and advances to other customers | C53: - | D53: - | E53: 893919311 | F53: - | G53: - | H53: - | I53: - | J53: 1384524660 | K53: 1958506596
B55: Interest on opening cash | C55: - | D55: - | E55: - | F55: - | G55: - | H55: - | I55: - | J55: - | K55: -
B58: Interest expense | C58: 64481004 | D58: 3105553 | E58: 80931352 | F58: 73218911 | G58: 66401846 | H58: 137727868 | I58: 5247288 | J58: 157082433 | K58: 160406053
B60: Due to banks | C60: - | D60: - | E60: - | F60: 65.12 | G60: - | H60: 65130000 | I60: 47274000 | J60: - | K60: 29724000
B61: Derivative financial liabilities | C61: - | D61: - | E61: - | F61: -0.01 | G61: - | H61: 2881000 | I61: 2319000 | J61: - | K61: 1263000
B62: Securities sold under repurchase agreements | C62: - | D62: - | E62: - | F62: 3947612 | G62: - | H62: 97726000 | I62: 111199000 | J62: - | K62: 110462000
B63: Financial liabilities at amortised cost – due to depositors | C63: 857269981 | D63: 994370875 | E63: 1068982587 | F63: 20.36 | G63: 1472640456 | H63: 1914359000 | I63: 2085046000 | J63: - | K63: 2608852000
B64: Refinance borrowings | C64: - | D64: - | E64: - | F64: - | G64: - | H64: - | I64: - | J64: - | K64: -
B65: Foreign currency borrowings | C65: - | D65: - | E65: - | F65: - | G65: - | H65: - | I65: - | J65: - | K65: -
B66: Subordinated liabilities | C66: 1535349 | D66: 3105553 | E66: 3848979 | F66: 0.99 | G66: 3398554 | H66: 61401000 | I66: 36483000 | J66: 7242090 | K66: 73322000
B67: Interest expense on lease liabilities | C67: - | D67: - | E67: - | F67: - | G67: - | H67: - | I67: - | J67: - | K67: -
B69: Interest expense except depositors | C69: - | D69: - | E69: - | F69: - | G69: - | H69: - | I69: - | J69: - | K69: -
B71: Deposit interest rate | C71: - | D71: - | E71: - | F71: - | G71: - | H71: - | I71: - | J71: - | K71: -
B72: Other financial liabilities | C72: - | D72: - | E72: - | F72: - | G72: - | H72: - | I72: - | J72: - | K72: -
B74: Check | C74: -857269981 | D74: -994370875 | E74: -1068982587 | F74: -1286616399 | G74: 0 | H74: 0 | I74: - | J74: - | K74: -
B78: Fee and commission income | C78: 10510800 | D78: - | E78: 12874966 | F78: 11839689 | G78: 15917337 | H78: 26191530 | I78: - | J78: 34480523 | K78: 42592091
B80: Loans and advances related services | C80: - | D80: - | E80: - | F80: - | G80: - | H80: - | I80: - | J80: - | K80: -
B81: Credit and debit cards related services | C81: - | D81: - | E81: - | F81: - | G81: - | H81: - | I81: - | J81: - | K81: -
B82: Trade and remittances related services | C82: - | D82: - | E82: - | F82: - | G82: - | H82: - | I82: - | J82: - | K82: -
B83: Deposits related services | C83: - | D83: - | E83: - | F83: - | G83: - | H83: - | I83: - | J83: - | K83: -
B84: Guarantees related services | C84: - | D84: - | E84: - | F84: - | G84: - | H84: - | I84: - | J84: - | K84: -
B85: Other financial services | C85: 46764237 | D85: 40046006 | E85: 35777329 | F85: 36023186 | G85: 70326837 | H85: 95254707 | I85: - | J85: - | K85: -
B87: Check | C87: -857269981 | D87: -994370875 | E87: -1068982587 | F87: -1286616399 | G87: 0 | H87: 0 | I87: - | J87: - | K87: -
B89: As a % of loan book | C89: - | D89: - | E89: - | F89: - | G89: - | H89: - | I89: - | J89: - | K89: -
B93: Fee and commission expense | C93: 1586334 | D93: - | E93: 2123128 | F93: 2018014 | G93: 3675143 | H93: 6022429 | I93: - | J93: 10834345 | K93: 13616570
B95: Loans and advances related services | C95: - | D95: - | E95: - | F95: - | G95: - | H95: - | I95: - | J95: - | K95: -
B96: Credit and debit cards related services | C96: - | D96: - | E96: - | F96: - | G96: - | H96: - | I96: - | J96: - | K96: -
B97: Trade and remittances related services | C97: - | D97: - | E97: - | F97: - | G97: - | H97: - | I97: - | J97: - | K97: -
B98: Other financial services | C98: 46764237 | D98: 40046006 | E98: 35777329 | F98: 36023186 | G98: 70326837 | H98: 95254707 | I98: - | J98: - | K98: -
B100: Check | C100: -857269981 | D100: -994370875 | E100: -1068982587 | F100: -1286616399 | G100: 0 | H100: 0 | I100: - | J100: - | K100: -
B102: As a % of fee income | C102: - | D102: - | E102: - | F102: - | G102: - | H102: - | I102: - | J102: - | K102: -
B106: Net gains/(losses) from trading | C106: 233956 | D106: - | E106: 1360833 | F106: 1878060 | G106: 1936007 | H106: 35297450 | I106: - | J106: -2201010 | K106: 344
B108: Derivative financial instruments | C108: - | D108: - | E108: - | F108: - | G108: - | H108: - | I108: - | J108: - | K108: -
B109: Foreign exchange gains/(losses) from banks and other customers | C109: - | D109: - | E109: - | F109: - | G109: - | H109: - | I109: - | J109: - | K109: -
B110: Financial assets recognised through profit or loss – measured at fair value | C110: 148381 | D110: 5520167 | E110: 21468033 | F110: 63.92 | G110: 242 | H110: 24873057 | I110: 29449653 | J110: 9167346 | K110: 111753532
B111: Government Securities | C111: - | D111: - | E111: - | F111: - | G111: - | H111: - | I111: - | J111: - | K111: -
B112: Net mark-to-market gains/(losses) | C112: - | D112: - | E112: - | F112: - | G112: - | H112: - | I112: - | J112: - | K112: -
B113: Net capital gains | C113: - | D113: - | E113: - | F113: - | G113: - | H113: - | I113: - | J113: - | K113: -
B114: Equities | C114: - | D114: - | E114: - | F114: - | G114: - | H114: - | I114: - | J114: - | K114: -
B115: Net mark-to-market gains/(losses) | C115: - | D115: - | E115: - | F115: - | G115: - | H115: - | I115: - | J115: - | K115: -
B116: Net capital gains | C116: - | D116: - | E116: - | F116: - | G116: - | H116: - | I116: - | J116: - | K116: -
B117: Dividend income | C117: - | D117: -80575 | E117: -85397 | F117: -98200 | G117: - | H117: - | I117: - | J117: - | K117: -
B119: Check | C119: -857269981 | D119: -994370875 | E119: -1068982587 | F119: -1286616399 | G119: 0 | H119: 0 | I119: - | J119: - | K119: -
B123: Net other operating income | C123: 1918687 | D123: - | E123: 6081876 | F123: 7770754 | G123: 10002216 | H123: -3771999 | I123: - | J123: 8496020 | K123: 345
B125: Gains/(losses) on sale of property, plant and equipment | C125: -10395 | D125: 3633 | E125: -7958 | F125: -7958 | G125: -5164 | H125: -4054 | I125: -3167 | J125: -15939 | K125: -25515
B126: Gains on revaluation of foreign exchange | C126: - | D126: - | E126: - | F126: - | G126: - | H126: - | I126: - | J126: - | K126: -
B127: Recoveries o/a loans written off | C127: - | D127: - | E127: - | F127: - | G127: - | H127: - | I127: - | J127: - | K127: -
B128: Dividend income from subsidiaries | C128: - | D128: -80575 | E128: -85397 | F128: -98200 | G128: - | H128: - | I128: - | J128: - | K128: -
B129: Dividend income from other equity securities | C129: - | D129: - | E129: - | F129: - | G129: - | H129: - | I129: - | J129: - | K129: -
B130: Profit due to change in ownership | C130: - | D130: -3344 | E130: -14498 | F130: - | G130: - | H130: - | I130: - | J130: - | K130: -
B131: Rental and other income | C131: - | D131: - | E131: - | F131: - | G131: - | H131: - | I131: - | J131: - | K131: -
B132: Less: Profit due to change in ownership | C132: - | D132: -3344 | E132: -14498 | F132: - | G132: - | H132: - | I132: - | J132: - | K132: -
B134: Check | C134: -857269981 | D134: -994370875 | E134: -1068982587 | F134: -1286616399 | G134: 0 | H134: 0 | I134: - | J134: - | K134: -
B138: Impairment charges and other losses | C138: - | D138: - | E138: 11331525 | F138: 21419532 | G138: 25139926 | H138: 71924260 | I138: - | J138: - | K138: -
B140: Loans and advances to other customers | C140: - | D140: 867611976 | E140: 893919311 | F140: 1.77 | G140: 246 | H140: 1130442579 | I140: 1176360000 | J140: 1384524660 | K140: 1958506596
B141: Individual impairment | C141: - | D141: - | E141: - | F141: - | G141: - | H141: - | I141: - | J141: - | K141: -
B142: Collective impairment | C142: - | D142: - | E142: - | F142: - | G142: - | H142: - | I142: - | J142: - | K142: -
B144: Other financial assets and off-balance sheet credit exposures | C144: - | D144: - | E144: - | F144: - | G144: - | H144: - | I144: - | J144: - | K144: -
B145: Total impairment charges | C145: - | D145: - | E145: - | F145: - | G145: - | H145: - | I145: - | J145: - | K145: -
B146: Investments in subsidiaries | C146: 5808 | D146: 80575 | E146: 85397 | F146: 5082437 | G146: 254 | H146: 5808439 | I146: 5808000 | J146: 5088429 | K146: -332880
...

Sheet Ratios
C2: =FS!C4 | D2: =FS!D4 | E2: =FS!E4 | F2: =FS!F4 | G2: =FS!G4 | H2: =FS!H4 | I2: =FS!I4 | J2: =FS!J4 | K2: =FS!K4
B3: Avg. yield on interest earning assets | C3: - | D3: - | E3: 0.1046999 | F3: 0.44561866 | G3: 89985.215 | H3: 0.11082788 | I3: 0.13616474 | J3: 0.13297076 | K3: 0.052704821
B4: Avg. cost on interest bearing funds | C4: - | D4: - | E4: - | F4: 18.547308 | G4: - | H4: 0.065702149 | I4: 0.093523009 | J4: - | K4: 0.058022545
B5: Net interest margin | C5: - | D5: - | E5: 0.039160094 | F5: 0.18267794 | G5: 44997.515 | H5: 0.042192255 | I5: 0.039532634 | J5: 0.057076605 | K5: 0.024652036
B6: Interest rate spread | C6: - | D6: - | E6: - | F6: -18.101689 | G6: - | H6: 0.045125727 | I6: 0.042641733 | J6: - | K6: -0.0053177242
B7: Cost to income (operating) | C7: 0.40128 | D7: - | E7: 0.38597706 | F7: 0.38597706 | G7: 0.31686186 | H7: 0.26553814 | I7: - | J7: 0.48420217 | K7: 0.30081355
B8: Cost to income (with impairments) | C8: 0.19342701 | D8: - | E8: 0.24848573 | F8: 0.31286536 | G8: 0.33479493 | H8: 0.38591847 | I8: 0.11153056 | J8: 0.1885197 | K8: 0.15746442
B9: Impairments/ Gross loans | C9: - | D9: -5.0863752e-06 | E9: 0.012676228 | F9: 12101431 | G9: 102194.82 | H9: 0.063624868 | I9: 0.032383854 | J9: - | K9: -
B10: Net margin | C10: 0.14229936 | D10: - | E10: 0.11556498 | F10: 0.1146332 | G10: 0.14840533 | H10: 0.087020714 | I10: 0.064115419 | J10: 0.20251385 | K10: 0.1668694
B11: ROE | C11: 0.15272344 | D11: - | E11: - | F11: 0.11085476 | G11: - | H11: 0.11978437 | I11: 0.10189158 | J11: - | K11: 0.13687137
B12: ROA | C12: - | D12: - | E12: 0.016607597 | F12: 0.01003353 | G12: 0.0122487 | H12: 0.010058345 | I12: 0.0082465596 | J12: 0.019960856 | K12: 0.018035007
B13: Equity/ total assets | C13: - | D13: - | E13: - | F13: 0.090510595 | G13: - | H13: 0.083970426 | I13: 0.080934649 | J13: - | K13: 0.1317661
B14: Deposits / total assets | C14: - | D14: - | E14: - | F14: 1.1726638e-08 | G14: - | H14: 0.78916802 | I14: 0.78514717 | J14: - | K14: 0.77211323
B15: Cash / total assets | C15: - | D15: 0.033605236 | E15: 0.051176472 | F15: 0.028942579 | G15: 0.034963284 | H15: 0.061585429 | I15: 0.060137372 | J15: 0.031130865 | K15: 0.026298032
B16: Gross income per employee | C16: - | D16: - | E16: - | F16: 30050.705 | G16: - | H16: 54752.381 | I16: - | J16: - | K16: -
B17: Dividend payout | C17: - | D17: - | E17: - | F17: - | G17: - | H17: 0.23425299 | I17: - | J17: - | K17: -
B18: Gross income per service centre | C18: - | D18: - | E18: - | F18: 529499.7 | G18: - | H18: 970197.04 | I18: - | J18: - | K18: -
B19: Net interest spread | C19: - | D19: - | E19: - | F19: -18.101689 | G19: - | H19: 0.045125727 | I19: 0.042641733 | J19: - | K19: -0.0053177242
B20: Gross income per service centre | C20: =FS!C6/FS!C88 | D20: =FS!D6/FS!D88 | E20: =FS!E6/FS!E88 | F20: =FS!F6/FS!F88 | G20: =FS!G6/FS!G88 | H20: =FS!H6/FS!H88 | I20: =FS!I6/FS!I88 | J20: =FS!J6/FS!J88 | K20: =FS!K6/FS!K88
B22: Net interest spread | F22: =F3-F4 | G22: =G3-G4 | H22: =H3-H4 | I22: =I3-I4 | J22: =J3-J4 | K22: =K3-K4

Sheet Quarterly
C1: For the quarter ended
C2: Mar 2017 | D2: Jun 2017 | E2: Sep 2017 | F2: Dec 2017 | G2: 44805
B3: Gross income | C3: 27243099 | D3: 55938093 | E3: 85476633 | F3: 116841755 | G3: 76055638
B4: Interest income | C4: 23931177 | D4: 49466361 | E4: 76424541 | F4: 104049102 | G4: 62139977
B5: Less : Interest expense | C5: 15144424 | D5: 31376625 | E5: 47780885 | F5: 64481804 | G5: 40038742
B6: Net interest income | C6: 8786753 | D6: 18089736 | E6: 28643656 | F6: 39567298 | G6: 22101235
B7: Fee and commission income | C7: - | D7: 4859671 | E7: 7496694 | F7: 10510800 | G7: 6447150
B8: Less: Fee and commission expense | C8: - | D8: 777261 | E8: 1178744 | F8: 1586334 | G8: 1411595
B9: Net fee and commission income | C9: - | D9: 4082410 | E9: 6317950 | F9: 8924466 | G9: 5035555
B10: Net gains/(losses) from trading | C10: 789108 | D10: 1271114 | E10: 350857 | F10: 233956 | G10: 2022197
B11: Net gains/(losses) from derecognition of financial assets | C11: - | D11: - | E11: - | F11: - | G11: 106832
B12: Net other operating income | C12: - | D12: - | E12: - | F12: - | G12: 5339482
B13: Total operating income | C13: 11693443 | D13: - | E13: 36517004 | F13: 50773617 | G13: 34605301
B14: Less : Impairment charges and other losses | C14: - | D14: - | E14: - | F14: - | G14: 17052988
B15: Net operating income | C15: 11441564 | D15: 22823634 | E15: 34897960 | F15: 48547703 | G15: 17552313
B16: Less: Expenses | C16: 5009500 | D16: 9937631 | E16: 14939808 | F16: 20374437 | G16: 7985228
B17: Personnel expenses | C17: 2727154 | D17: 5488192 | E17: 8380408 | F17: 11338517 | G17: 5055534
B18: Depreciation and amortisation | C18: 329807 | D18: 690052 | E18: 1044044 | F18: 1416927 | G18: 905454
B19: Other operating expenses | C19: - | D19: - | E19: - | F19: - | G19: 2024240
B20: Operating profit before Taxes on financial services | C20: - | D20: - | E20: - | F20: - | G20: 9567085
B21: Less: Taxes on financial services | C21: - | D21: - | E21: - | F21: - | G21: 907846
B22: Operating profit after Taxes on financial services | C22: - | D22: - | E22: - | F22: - | G22: 8659239
B23: Add/(less): Share of profit/(loss) of associate, net of tax | C23: - | D23: - | E23: - | F23: - | G23: 1220
B24: Profit before income tax | C24: 5306793 | D24: 10609103 | E24: 16406082 | F24: 23280324 | G24: 8660459
B25: Less : Income tax expense / (reversal) | C25: 1493057 | D25: 2954835 | E25: 4632201 | F25: 6653817 | G25: 2377804
B26: Profit for the period | C26: 3813736 | D26: 7654268 | E26: 11773881 | F26: 16626507 | G26: 6282655
B27: Profit attributable to: | C27: - | D27: - | E27: - | F27: -
B28: Equity holders of the Bank | C28: 3819907 | D28: 7657744 | E28: 11769309 | F28: 16605963 | G28: 6095730
B29: Non-controlling interest | C29: -6171 | D29: -3476 | E29: 4572 | F29: 20544 | G29: 186925
B30: Profit for the period | C30: 3813736 | D30: 7654268 | E30: 11773881 | F30: 16626507 | G30: 6282655
B31: Earnings per share | C31: - | D31: - | E31: - | F31: -
B32: Earnings per share | C32: 4.75 | D32: 2.86 | E32: 3.21 | F32: 7.08 | G32: 4.92
